Workbook

Sheet Focal Point Tracking
A1: Submission Checklist 28th November
A2: Principals | B2: Focal Points submitted
A3: Admin. UNDP | B3: yes
A4: ASG DCO | B4: yes
A5: CDC​ | B5: yes
A6: Chair DTN | B6: yes
A7: Chair HLCM​ | B7: yes
A8: Co-Chairs BIG | B8: yes | D8: =54%*87 -> 46.98
A9: DSG​ | B9: yes
A10: ED UN Women | B10: yes
A11: ED UNAIDS | B11: yes
A12: ED UNFPA | B12: yes
A13: ED UNICEF | B13: yes
A14: ED UNITAR | B14: yes
A15: ED UNOPS | B15: yes
A16: ED WFP | B16: yes
A17: ES ECA​ | B17: yes
A18: ES UNFCCC | B18: yes
A19: HC OHCHR | B19: yes
A20: Rector UNU | B20: yes
... A36: USG UNODC | B36: yes
B38: {=COUNTIF(Table2[[Focal Points submitted ]], yes)} -> 0

Sheet UN80 Action Plan (2)
A1: FileSystemObjectType | B1: Id | C1: ServerRedirectedEmbedUri | D1: ServerRedirectedEmbedUrl | E1: ContentTypeId | F1: Title | G1: OData__ColorTag | H1: ComplianceAssetId | I1: Action No. | J1: Work Package | K1: Indicative Action | L1: WP Leads | M1: Milestone 1 | N1: Milestone 1 Deadline | O1: Action Lead(s) | P1: Action Support(s) | Q1: Master-List-ID | R1: Milestone Final | S1: Milestone Final Deadline | T1: ID2 | U1: Modified | V1: Created | W1: AuthorId | X1: EditorId | Y1: OData__UIVersionString | Z1: Attachments | AA1: GUID
A2: 0 | B2: 1 | E2: 0x0100B7189DADE8EA1A40B9BF8DA45310AFE600A178D82D6E6846409061C607AC5C63EE | I2: A01 | J2: WP1: Peace operations (task delegation; review) | K2: Delegate relevant programmatic tasks such as rule of law, governance and child protection – and the associated resources – to UN system entities best equipped to deliver them | L2: USG DPPA;USG DPO | M2: With respect toUSGs DiCarlo and Lacroix would lead, with the participation of UNDP, OCHA, DCO, OHCHR, PBSO, OROLSI, UNICEF, UN Women, and the SRSGs CAAC and SVC | O2: USG Lacroix; USG DiCarlo | P2: David Haeri, Director, DPET, DPO; Asif Khan, Diector, PMD, DPPA | Q2: 14 | T2: 1 | U2: 45989.688 | V2: 45967.006 | W2: 10 | X2: 222 | Y2: 10.0 | Z2: FALSE | AA2: e0b494ac-2ecf-4531-ad3e-a1c996179786
A3: 0 | B3: 2 | E3: 0x0100B7189DADE8EA1A40B9BF8DA45310AFE600A178D82D6E6846409061C607AC5C63EE | I3: A02 | J3: WP1: Peace operations (task delegation; review) | K3: Present comprehensive proposal for the reset of peace operations to Member States upon conclusion of the review mandated by the Pact for the Future | L3: USG DPPA;USG DPO | M3: Review of the future of peace operations completed | N3: 46111.917 | O3: USGs DPPA and DPO, Rosemary DiCarlo and Jean-Pierre Lacroix | P3: Directors PMD and DPET, Asif R. Khan and David Haeri | Q3: 15 | R3: Review of the future of peace operations completed | S3: 46111.917 | T3: 2 | U3: 45987.719 | V3: 45967.006 | W3: 10 | X3: 197 | Y3: 5.0 | Z3: FALSE | AA3: 0a9ea861-8ccc-43e8-ab8c-f6dc51658417
A4: 0 | B4: 3 | E4: 0x0100B7189DADE8EA1A40B9BF8DA45310AFE600A178D82D6E6846409061C607AC5C63EE | I4: A03 | J4: WP2: New Humanitarian Compact | K4: Streamline Humanitarian Needs and Response Plans to become shorter and sharper | L4: USG OCHA | Q4: 16 | T4: 3 | U4: 45973.65 | V4: 45967.006 | W4: 10 | X4: 10 | Y4: 6.0 | Z4: FALSE | AA4: 21c7739b-702b-4143-be35-401ff3713af0
A5: 0 | B5: 4 | E5: 0x0100B7189DADE8EA1A40B9BF8DA45310AFE600A178D82D6E6846409061C607AC5C63EE | I5: A04 | J5: WP2: New Humanitarian Compact | K5: Integrate global supply chains, coordinating procurement of key items, pool use of global freight and logistics, and unbranded in-country services open to the entire UN system | L5: USG OCHA | Q5: 17 | T5: 4 | U5: 45973.65 | V5: 45967.006 | W5: 10 | X5: 10 | Y5: 6.0 | Z5: FALSE | AA5: 7bf06f11-c783-407f-b724-f6eba4e2c925
A6: 0 | B6: 5 | E6: 0x0100B7189DADE8EA1A40B9BF8DA45310AFE600A178D82D6E6846409061C607AC5C63EE | I6: A05 | J6: WP2: New Humanitarian Compact | K6: Scale common services with a Global Services Hub and interoperable digital platforms to help consolidate surge rosters, logistics, security, telecoms and engineering support | L6: USG OCHA | Q6: 18 | T6: 5 | U6: 45967.006 | V6: 45967.006 | W6: 10 | X6: 10 | Y6: 1.0 | Z6: FALSE | AA6: 5897e117-f5fb-4f90-97b9-a4a40228e5ad
A7: 0 | B7: 6 | E7: 0x0100B7189DADE8EA1A40B9BF8DA45310AFE600A178D82D6E6846409061C607AC5C63EE | I7: A06 | J7: WP2: New Humanitarian Compact | K7: Initiate new Humanitarian Data Collaborative, to scale common platforms, collective financing, shared centres, capacities and standards | L7: USG OCHA | Q7: 20 | T7: 6 | U7: 45967.006 | V7: 45967.006 | W7: 10 | X7: 10 | Y7: 1.0 | Z7: FALSE | AA7: 750e3ec7-c96a-4272-90df-edc81a644fec
A8: 0 | B8: 7 | E8: 0x0100B7189DADE8EA1A40B9BF8DA45310AFE600A178D82D6E6846409061C607AC5C63EE | I8: A07 | J8: WP2: New Humanitarian Compact | K8: Initiate Collaborative Humanitarian Diplomacy Initiative to bring agencies together under the coordination of the Emergency Relief Coordinator | L8: USG OCHA | Q8: 21 | T8: 7 | U8: 45967.006 | V8: 45967.006 | W8: 10 | X8: 10 | Y8: 1.0 | Z8: FALSE | AA8: 29159a3e-0b0b-46fd-b622-401cb5c9b3a6
A9: 0 | B9: 8 | E9: 0x0100B7189DADE8EA1A40B9BF8DA45310AFE600A178D82D6E6846409061C607AC5C63EE | I9: A08 | J9: WP2: New Humanitarian Compact | K9: Align agencies’ responsibilities: FAO/WFP/IFAD on food security | L9: USG OCHA | Q9: 22 | T9: 8 | U9: 45967.006 | V9: 45967.006 | W9: 10 | X9: 10 | Y9: 1.0 | Z9: FALSE | AA9: ed9ca06d-3cbe-4227-b153-bb81fbddc316
A10: 0 | B10: 9 | E10: 0x0100B7189DADE8EA1A40B9BF8DA45310AFE600A178D82D6E6846409061C607AC5C63EE | I10: A09 | J10: WP2: New Humanitarian Compact | K10: Align agencies’ responsibilities: UNHCR/IOM on joint institutional approaches (incl. route-based programming) | L10: USG OCHA | Q10: 23 | T10: 9 | U10: 45967.006 | V10: 45967.006 | W10: 10 | X10: 10 | Y10: 1.0 | Z10: FALSE | AA10: d4ddc385-4167-4c55-9c90-104a9215d64a
A11: 0 | B11: 10 | E11: 0x0100B7189DADE8EA1A40B9BF8DA45310AFE600A178D82D6E6846409061C607AC5C63EE | I11: A10 | J11: WP2: New Humanitarian Compact | K11: Align agencies’ responsibilities: UNICEF/WFP/UNHCR/IOM on beneficiary data | L11: USG OCHA | Q11: 24 | T11: 10 | U11: 45967.006 | V11: 45967.006 | W11: 10 | X11: 10 | Y11: 1.0 | Z11: FALSE | AA11: 3a61ded2-8559-448b-8c36-6c7ac87e35e1
A12: 0 | B12: 11 | E12: 0x0100B7189DADE8EA1A40B9BF8DA45310AFE600A178D82D6E6846409061C607AC5C63EE | I12: A11 | J12: WP2: New Humanitarian Compact | K12: Align agencies’ responsibilities: WHO/UNICEF/WFP on health and nutrition | L12: USG OCHA | Q12: 25 | T12: 11 | U12: 45967.006 | V12: 45967.006 | W12: 10 | X12: 10 | Y12: 1.0 | Z12: FALSE | AA12: 699c9758-d4dc-4e87-b1ef-99265d6e0c99
A13: 0 | B13: 12 | E13: 0x0100B7189DADE8EA1A40B9BF8DA45310AFE600A178D82D6E6846409061C607AC5C63EE | I13: A12 | J13: WP3: UNDP/UNOPS | K13: Conduct a thorough assessment of the benefits of a merger between UNDP and UNOPS; analysis to be presented to the Executive Boards in February 2026 | L13: DSG;Administrator UNDP;ED UNOPS | M13: • Draft initial assessment analysis of the ‘as is’ with high level merger options, pros, cons, risk analysis for internal consultations | N13: 46040.958 | O13: 1. Amina Mohammed, DSG, amina.mohammed@un.org 2. Jorge Moreira Da Silva, USG – UNOPS, jorge.moreiradasilva@unops.org 3. Alexander de Croo, USG – UNDP, alexander.de.croo@undp.org | P13: 1. Sonja Leighton-Kone, ASG - UNOPS, sonjalk@unops.org 2. Linda Maguire, ASG - UNDP, linda.maguire@undp.org 3. Rahul Malhotra, Director New York Office, UNOPS, rahulm@unops.org 2.4. Fiona Bayat-Renoux, Deputy Chief of Staff, UNDP, Fiona.bayat-renoux@undp.org 3.5. Jean-Philippe Bernardini, Senior Political Affairs Officer, EOSG, Bernardini@un.org | Q13: 26 | R13: Thorough assessment of selected option(s) provided to Member States and guidance given through a General Assembly decision | S13: 46386.958 | T13: 12 | U13: 45989.913 | V13: 45967.006 | W13: 10 | X13: 125 | Y13: 4.0 | Z13: FALSE | AA13: d14b25b6-baf6-46b1-bc3a-c646635fff65
A14: 0 | B14: 13 | E14: 0x0100B7189DADE8EA1A40B9BF8DA45310AFE600A178D82D6E6846409061C607AC5C63EE | I14: A13 | J14: WP4: UNFPA/UN Women | K14: Conduct a thorough assessment of the benefits of a merger of UNFPA and UN Women and their respective mandates | L14: DSG;ED UNFPA;ED UN Women | M14: Strategic merger assessment is completed for internal consultations, including risk/benefit considerations | N14: 46052.958 | O14: Amina Mohammed, DSG, Amina.mohammed@un.org Sima Bahous, Executive Director, UN Women sima.bahous@unwomen.org Diene Keita, Executive Director, UNFPA, Keita@unfpa.org | P14: Jean Philippe Bernardini, Senior Political Affairs Officer, bernardini@un.org Sam Choritz, Chief of Staff, UNFPA, choritz@unfpa.org Mohammad Naciri, Chief of Staff, UN Women, mohammad.naciri@unwomen.org | Q14: 27 | R14: By mid-2026, a thorough assessment is provided to Member States for a General Assembly decision | S14: 46386.958 | T14: 13 | U14: 45992.803 | V14: 45967.006 | W14: 10 | X14: 83 | Y14: 13.0 | Z14: FALSE | AA14: d9e3af62-a6c8-4989-be12-c94e236b40b4
A15: 0 | B15: 14 | E15: 0x0100B7189DADE8EA1A40B9BF8DA45310AFE600A178D82D6E6846409061C607AC5C63EE | I15: A14 | J15: WP4: UNFPA/UN Women | K15: Conduct a thorough assessment to consider options to optimize normative functions of UNFPA on population statistics and related activities, including those currently undertaken by DESA | L15: DSG;ED UNFPA;ED UN Women | M15: Options for optimization of the UN’s work on population statistics and related activities are finalized for SG consideration and integrated in merger analysis | N15: 46052.958 | O15: 1. Amina Mohammed, DSG, Amina.mohammed@un.org 2. Sima Bahous, Executive Director, UN Women sima.bahous@unwomen.org 3. Diene Keita, Executive Director, UNFPA, Keita@unfpa.org 4. USG Li Junhua, USG DESA, junhua.li@un.org | P15: 1. Jean Philippe Bernardini, Senior Political Affairs Officer, bernardini@un.org 2. Sam Choritz, Chief of Staff, UNFPA, choritz@unfpa.org 3. Mohammad Naciri, Chief of Staff, UN Women, mohammad.naciri@unwomen.org | Q15: 28 | R15: A final assessment is integrated into the UNWomen/UNFPA merger process, as per timelines above. | S15: 46386.958 | T15: 14 | U15: 45992.805 | V15: 45967.006 | W15: 10 | X15: 83 | Y15: 7.0 | Z15: FALSE | AA15: 4d7a9de4-0cc8-4366-b8c4-5dd9982cf91a
A16: 0 | B16: 15 | E16: 0x0100B7189DADE8EA1A40B9BF8DA45310AFE600A178D82D6E6846409061C607AC5C63EE | I16: A15 | J16: WP5: UNCT reconfiguration | K16: Propose a model to reconfigure country teams via system-wide working group, chaired by the Deputy Secretary-General | L16: DSG | M16: Outline of the draft proposals presented to the Secretary-General for guidance | N16: 46029.958 | O16: 1. Amina J. Mohammed, DSG, Amina.mohammed@un.org 2. Jorge Moreira Da Silva, USG – UNOPS, jorge.moreiradasilva@unops.org | P16: 1. Rahul Malhorta, Director, UNOPS, rahulm@unops.org 2. Jean Philippe Bernardini, Senior Political Affairs Officer, bernardini@un.org | Q16: 39 | R16: Member States take action/decide on final set of proposals presented by the SG (report finalized by 31 May 2026 – TBC, depending next reporting cycle) | T16: 15 | U16: 45992.802 | V16: 45967.006 | W16: 10 | X16: 83 | Y16: 4.0 | Z16: FALSE | AA16: 42617088-b056-4e06-9d9e-b79391e942cc
A17: 0 | B17: 16 | E17: 0x0100B7189DADE8EA1A40B9BF8DA45310AFE600A178D82D6E6846409061C607AC5C63EE | I17: A16 | J17: WP5: UNCT reconfiguration | K17: Strengthen and recalibrate the Resident Coordinator system to better leverage knowledge hubs, expertise-on-demand, and non-resident entities | L17: DSG | M17: The parameters for the recalibration of the RC system are defined and being consulted with Member States (e.g. change in DCO structure, more tailored approach) | N17: 46052.958 | O17: 1. Amina J. Mohammed, DSG, Amina.mohammed@un.org 2. Oscar Fernandez-Taranco, DCO fernandez-taranco@un.org | P17: 1. Jean Philippe Bernardini, Senior Political Affairs Officer, bernardini@un.org | Q17: 40 | R17: All measures to recalibrate the RC system (DCO 2.0) are implemented and a decision to enhance the funding model of the RC system is successfully tabled in the | S17: 46386.958 | T17: 16 | U17: 45992.802 | V17: 45967.006 | W17: 10 | X17: 83 | Y17: 6.0 | Z17: FALSE | AA17: ea519c52-4d19-4969-b210-4d312d140e95
A18: 0 | B18: 17 | E18: 0x0100B7189DADE8EA1A40B9BF8DA45310AFE600A178D82D6E6846409061C607AC5C63EE | I18: A17 | J18: WP6: Regional reset | K18: Establish a system-wide working group, chaired by the Deputy Secretary-General, to develop proposals on how to advance a reset of regional capacities for sustainable development, incl. on how to institutionalize Regional Integrated Platforms | L18: DSG | M18: system-wide working group convened and draft outline finalized and shared with the Secretary-General for guidance | N18: 46029.958 | O18: 1. Amina J. Mohammed, DSG, Amina.mohammed@un.org 2. Izumi Nakamitsu, USG – ODA, nakamitsu@un.org | P18: 1. Jean Philippe Bernardini, Senior Political Affairs Officer, bernardini@un.org | Q18: 36 | R18: Aspects of the regional reset under SG prerogative are implemented and decisions taken by Member States on aspects requiring new mandates (report May 2026 -TBC) | T18: 17 | U18: 45990.085 | V18: 45967.006 | W18: 10 | X18: 274 | Y18: 4.0 | Z18: FALSE | AA18: 4a2996a2-167e-41a3-a9f6-2df8237a6e8f
A19: 0 | B19: 18 | E19: 0x0100B7189DADE8EA1A40B9BF8DA45310AFE600A178D82D6E6846409061C607AC5C63EE | I19: A18 | J19: WP6: Regional reset | K19: Systematize the practice of hosting regional capacities within the Regional Economic Commissions, starting with DCO regional directors and teams | L19: DSG | M19: Develop initial proposals for co-hosting for further consultation, taking into consideration the unique regional needs and contexts. | N19: 46052.958 | O19: 1. Amina J. Mohammed, DSG, Amina.mohammed@un.org 2. Izumi Nakamitsu, USG – ODA, nakamitsu@un.org 3. Oscar Fernandez Taranco, ASG – DCO, fernandez-taranco@un.org | P19: 4. Jean Philippe Bernardini, Senior Political Affairs Officer, bernardini@un.org 5. Nadia Hadi, Chief of Staff DCO, hadin@un.org 6. Thilmeeza Hussain, Director, Regional Commission Office, thilmeeza.hussain@un.org | Q19: 37 | R19: Relocation of respective offices to be hosted by RECs is complete or ongoing, according to implementation plan developed for each region by 29 May 2026. | T19: 18 | U19: 45990.087 | V19: 45967.006 | W19: 10 | X19: 274 | Y19: 4.0 | Z19: FALSE | AA19: f1aaf1b1-05df-411a-8e7e-283247847158
A20: 0 | B20: 19 | E20: 0x0100B7189DADE8EA1A40B9BF8DA45310AFE600A178D82D6E6846409061C607AC5C63EE | I20: A19 | J20: WP7: Joint knowledge hubs | K20: Establish Joint Knowledge Hubs to pool knowledge on key issues spread across UN development system entities and avoid duplications, including finding the best placed entities to co-leads (through joint mechanisms) | L20: USG DESA;SG UNCTAD | M20: The first meeting endorsed the concept note, agreed on hub list with leads, and committed to distinct value and collaboration with UN mechanisms. | O20: Rebeca Grynspan, Secretary-General of UNCTAD, rebeca.grynspan@unctad.org LI Junhua, Under-Secretary-General of DESA, junhua.li@un.org | P20: Adnan Issa, Director, Programme Management, UNCTAD, issa@unctad.org Wai Min Kwok, Acting Chief, Office of the USG, DESA, kwok@un.org Carlos Razo, Senior Coordinator, Office of the Secretary General, UNCTAD, carlos.razo@un.org Guenther Gross, Senior Programme Management Officer, Office of the USG, DESA, gross1@un.org | Q20: 33 | R20: Established hubs deliver coherent, efficient UN-wide support, integrating data and knowledge for policy coherence and innovative solutions. | T20: 19 | U20: 45989.922 | V20: 45967.006 | W20: 10 | X20: 277 | Y20: 4.0 | Z20: FALSE | AA20: 1f4433d6-a917-4565-8264-ba1ac0c0274e
A21: 0 | B21: 20 | E21: 0x0100B7189DADE8EA1A40B9BF8DA45310AFE600A178D82D6E6846409061C607AC5C63EE | I21: A20 | J21: WP8: Expertise-on-demand mechanism | K21: Create a pro-active mechanism UN system-wide expertise on demand, particularly from specialized agencies and non-resident entities | L21: SG ITU | M21: Concept endorsed. Legal/financial assessment, catalogue design, & demand protocol and arrangements. | N21: 46052.958 | O21: Leads: ITU: Ms. Doreen Bogdan-Martin, Secretary-General (sgo@itu.int) UNDP Invited to co-Lead: Haoliang Xu, Acting Administrator (haoliang.xu@undp.org) Members: FAO: Mr. Qu Dongyu, Director General (director-general@fao.org; dongyu.qu@fao.org) ICAO: Mr. Juan Carlos Salazar, Secretary-General (OSGinbox@icao.int; jsalazar@icao.int) ILO: Mr. Gilbert F. Houngbo, Director General (ILODirector-General@ilo.org) UNESCO: Mr Khaled El-Enany, Director-General (dg.secretariat@unesco.org) UNIDO: Gerd Müller, Director General (ODG@unido.org) WMO: Ms Celeste Saulo, Secretary-General (sgomm@wmo.int) ITC: Ms. Pamela Coke-Hamilton, Executive Director and ASG (cokehamilton@intracen.org); front office: Ascension Carrasco Rodriguez (carrasco@intracen.org) UN Women: Sima Bahous, Executive Director. Sima Sami Bahous (sima.bahous@unwomen.org) Regional Commissions: Mr. Claver Gatete, Coordinator of the Regional Commissions, ECA Executive Secretary (cgatete@un.org) Ms. Tatiana Molcean, Executive Secretary of ECE (tatiana.molcean@un.org) Mr. Mourad Wahba, Acting Executive of ESCWA Secretary (mourad.wahba@un.org) In addition, invited to contribute as standing members subject to confirmation: WHO: Mr. Tedros Adhanom Ghebreyesus, Director General (dgoffice@who.int; drtedros@who.int) tbc UNCTAD: Ms. Rebeca Grynspan, Secretary-General (rebeca.grynspan@unctad.org) tbc | P21: ITU: Tomas Lamanauskas, Deputy Secretary-General (dsg@itu.int) UNDP: Linda Maquire, Asst Secretary General and Director, Bureau for Management Services (linda.maguire@undp.org) FAO: Beth Crawford, Assistant Director-General/Director, Office of Strategy, Programme and Budget (beth.crawford@fao.org ) ICAO: Michiel Vreedenburgh, Chief Transformation Officer (MVreedenburgh@icao.int) ILO: Ms. Laura Thompson, Assistant Director General, External and Corporate Relations (thompsonl@ilo.org) UNESCO: Jennifer Linkins, Assistant Director-General for Administration and Management (j.linkins@unesco.org) UNIDO: Ms. Cecilia Ugaz Estrada, Deputy to the Director General (C.UGAZESTRADA@unido.org) tbc WMO: Ko Barrett, DSG (dsgo@wmo.int) ITC: Mr. Mondher Mimouni, Director, Division of Market Development (mimouni@intracen.org) UN Women: Nyaradzayi Gumbonzvanda. Deputy Executive Director Normative Support, System Coordination, Programme Results (n.gumbonzvanda@unwomen.org) Regional Commissions: Ms. Thilmeeza Hussain (thilmeeza.hussain@un.org) ECA Mr. Aboubakri Diaw (diaw2@un.org) ECA Mr. Paul John Ladd (paul.ladd@un.org) ECE Ms. Maisaa Youssef (youssef8@un.org) ESCWA Ms. Riwa Nasreddine (nasreddine@un.org) ESCWA Support/Advisor: SA Reform Jens Christian Wandel, USG and Special Adviser to the Secretary-General on Reforms (jens.wandel@un.org) In addition, invited to contribute as standing members subject to confirmation: ILO: Ms. Laura Thompson, Assistant Director General, External and Corporate Relations (thompsonl@ilo.org) WHO: Bruce Aylward, Senior Advisor to the Director-General (aylwardb@who.int) UNCTAD Tbc: | Q21: 34 | R21: EOD fully operational system-wide: expertise catalogue launched, protocols institutionalized, proven replacement of duplicative capacities. | S21: 46375.958 | T21: 20 | U21: 45992.707 | V21: 45967.006 | W21: 10 | X21: 109 | Y21: 15.0 | Z21: FALSE | AA21: 904d4c8d-4c80-4591-a7b8-b33df38b95d4
A22: 0 | B22: 21 | E22: 0x0100B7189DADE8EA1A40B9BF8DA45310AFE600A178D82D6E6846409061C607AC5C63EE | I22: A21 | J22: WP8: Expertise-on-demand mechanism | K22: Consolidate expertise across all pillars at the regional level as an extension of the expertise-on-demand mechanism outlined in the sustainable development pillar | L22: SG ITU | M22: Concept endorsed. Legal/financial assessment, catalogue design, & demand protocol and arrangements. | N22: 46052.958 | O22: Leads: ITU: Ms. Doreen Bogdan-Martin, Secretary-General (sgo@itu.int) UNDP Invited to co-Lead: Haoliang Xu, Acting Administrator (haoliang.xu@undp.org) Members: FAO: Mr. Qu Dongyu, Director General (director-general@fao.org; dongyu.qu@fao.org) ICAO: Mr. Juan Carlos Salazar, Secretary-General (OSGinbox@icao.int; jsalazar@icao.int) ILO: Mr. Gilbert F. Houngbo, Director General (ILODirector-General@ilo.org) UNESCO: Mr Khaled El-Enany, Director-General (dg.secretariat@unesco.org) UNIDO: Gerd Müller, Director General (ODG@unido.org) WMO: Ms Celeste Saulo, Secretary-General (sgomm@wmo.int) ITC: Ms. Pamela Coke-Hamilton, Executive Director and ASG (cokehamilton@intracen.org); front office: Ascension Carrasco Rodriguez (carrasco@intracen.org) UN Women: Sima Bahous, Executive Director. Sima Sami Bahous (sima.bahous@unwomen.org) Regional Commissions: Mr. Claver Gatete, Coordinator of the Regional Commissions, ECA Executive Secretary (cgatete@un.org) Ms. Tatiana Molcean, Executive Secretary of ECE (tatiana.molcean@un.org) Mr. Mourad Wahba, Acting Executive of ESCWA Secretary (mourad.wahba@un.org) In addition, invited to contribute as standing members subject to confirmation: WHO: Mr. Tedros Adhanom Ghebreyesus, Director General (dgoffice@who.int; drtedros@who.int) tbc UNCTAD: Ms. Rebeca Grynspan, Secretary-General (rebeca.grynspan@unctad.org) tbc | P22: ITU: Tomas Lamanauskas, Deputy Secretary-General (dsg@itu.int) UNDP: Linda Maquire, Asst Secretary General and Director, Bureau for Management Services (linda.maguire@undp.org) FAO: Beth Crawford, Assistant Director-General/Director, Office of Strategy, Programme and Budget (beth.crawford@fao.org ) ICAO: Michiel Vreedenburgh, Chief Transformation Officer (MVreedenburgh@icao.int) ILO: Ms. Laura Thompson, Assistant Director General, External and Corporate Relations (thompsonl@ilo.org) UNESCO: Jennifer Linkins, Assistant Director-General for Administration and Management (j.linkins@unesco.org) UNIDO: Ms. Cecilia Ugaz Estrada, Deputy to the Director General (C.UGAZESTRADA@unido.org) tbc WMO: Ko Barrett, DSG (dsgo@wmo.int) ITC: Mr. Mondher Mimouni, Director, Division of Market Development (mimouni@intracen.org) UN Women: Nyaradzayi Gumbonzvanda. Deputy Executive Director Normative Support, System Coordination, Programme Results (n.gumbonzvanda@unwomen.org) Regional Commissions: Ms. Thilmeeza Hussain (thilmeeza.hussain@un.org) ECA Mr. Aboubakri Diaw (diaw2@un.org) ECA Mr. Paul John Ladd (paul.ladd@un.org) ECE Ms. Maisaa Youssef (youssef8@un.org) ESCWA Ms. Riwa Nasreddine (nasreddine@un.org) ESCWA Support/Advisor: SA Reform Jens Christian Wandel, USG and Special Adviser to the Secretary-General on Reforms (jens.wandel@un.org) In addition, invited to contribute as standing members subject to confirmation: ILO: Ms. Laura Thompson, Assistant Director General, External and Corporate Relations (thompsonl@ilo.org) WHO: Bruce Aylward, Senior Advisor to the Director-General (aylwardb@who.int) UNCTAD Tbc: | Q22: 54 | R22: EOD fully operational system-wide: expertise catalogue launched, protocols institutionalized, proven replacement of duplicative capacities. | S22: 46375.958 | T22: 21 | U22: 45992.707 | V22: 45967.006 | W22: 10 | X22: 109 | Y22: 23.0 | Z22: FALSE | AA22: d96e13d9-727a-4ec0-aee0-c9b4d2b5a07f
A23: 0 | B23: 22 | E23: 0x0100B7189DADE8EA1A40B9BF8DA45310AFE600A178D82D6E6846409061C607AC5C63EE | I23: A22 | J23: WP9: Human rights group | K23: Establish a Human Rights Group comprising entities from across the UN system, led by the High Commissioner for Human Rights | L23: HC OHCHR | Q23: 42 | T23: 22 | U23: 45968.775 | V23: 45967.006 | W23: 10 | X23: 10 | Y23: 5.0 | Z23: FALSE | AA23: 74a80a22-72b9-4584-bb25-af27ed6d0ed3
A24: 0 | B24: 23 | E24: 0x0100B7189DADE8EA1A40B9BF8DA45310AFE600A178D82D6E6846409061C607AC5C63EE | I24: A23 | J24: WP10: Senior management coordination forums | K24: Review top management fora to ease the coordination burden for senior leaders and ensure coherent action across pillar, incl. CEB, IASC, UNSDG, EC | L24: USG Policy | Q24: 43 | T24: 23 | U24: 45968.775 | V24: 45967.007 | W24: 10 | X24: 10 | Y24: 6.0 | Z24: FALSE | AA24: cc3b8bbb-212e-43be-9da2-2c0fcc973a65
A25: 0 | B25: 24 | E25: 0x0100B7189DADE8EA1A40B9BF8DA45310AFE600A178D82D6E6846409061C607AC5C63EE | I25: A24 | J25: WP10: Senior management coordination forums | K25: Consider proposals to unify administrative backend support and streamline duplicative agendas without affecting core substantive competencies | L25: USG Policy | Q25: 44 | T25: 24 | U25: 45967.007 | V25: 45967.007 | W25: 10 | X25: 10 | Y25: 1.0 | Z25: FALSE | AA25: 52dc6857-c733-416e-a55e-d414e90e0d00
A26: 0 | B26: 25 | E26: 0x0100B7189DADE8EA1A40B9BF8DA45310AFE600A178D82D6E6846409061C607AC5C63EE | I26: A25 | J26: WP10: Senior management coordination forums | K26: Bring together all Headquarters coordination on country-specific, cross-pillar approaches to crisis prevention and centre capacities around the Regional Monthly Review platform | L26: USG Policy | Q26: 46 | T26: 25 | U26: 45967.007 | V26: 45967.007 | W26: 10 | X26: 10 | Y26: 1.0 | Z26: FALSE | AA26: f8be6931-b546-48fb-8f1a-90e1f46968b5
A27: 0 | B27: 26 | E27: 0x0100B7189DADE8EA1A40B9BF8DA45310AFE600A178D82D6E6846409061C607AC5C63EE | I27: A26 | J27: WP10: Senior management coordination forums | K27: Review existing interagency task forces and working groups | L27: USG Policy | Q27: 47 | T27: 26 | U27: 45967.007 | V27: 45967.007 | W27: 10 | X27: 10 | Y27: 1.0 | Z27: FALSE | AA27: 4517f49b-9a20-45f6-a240-ed97b6217e3b
A28: 0 | B28: 27 | E28: 0x0100B7189DADE8EA1A40B9BF8DA45310AFE600A178D82D6E6846409061C607AC5C63EE | I28: A27 | J28: WP11: Special envoy review | K28: Review and make proposals to Member States regarding SG’s some 30 special envoys, representatives, coordinators and advisers, both thematic and geographic | L28: USG Policy | Q28: 45 | T28: 27 | U28: 45967.007 | V28: 45967.007 | W28: 10 | X28: 10 | Y28: 1.0 | Z28: FALSE | AA28: ad2ff997-e7a8-4052-bf4f-10857483d502
A29: 0 | B29: 28 | E29: 0x0100B7189DADE8EA1A40B9BF8DA45310AFE600A178D82D6E6846409061C607AC5C63EE | I29: A28 | J29: WP12: Regional integrated platforms | K29: Establish lean Regional Integrated Platforms to unite regional leaders across all pillars around joint plans, strategies, crisis response and resource mobilization for cross-cutting issues | L29: ASG DCO;DSG | M29: System-wide working group convened and draft Outline on regional reset to be shared with the SG for guidance, reflecting cross-pillar dimensions | N29: 46029.958 | O29: 1. Amina J. Mohammed, DSG, Amina.mohammed@un.org 2. Izumi Nakamitsu, USG – ODA, nakamitsu@un.org 3. Oscar Fernandez Taranco, ASG – DCO, fernandez-taranco@un.org | P29: 1. Jean Philippe Bernardini, Senior Political Affairs Officer, bernardini@un.org | Q29: 48 | R29: Aspects of the regional reset – including RIPs - under SG prerogative are implemented and decisions taken by Member States (Report May 2026 - TBC) | S29: 46386.958 | T29: 28 | U29: 45990.09 | V29: 45967.007 | W29: 10 | X29: 274 | Y29: 2.0 | Z29: FALSE | AA29: dc3b8c87-c1d7-45fa-b222-7262821a6f7b
A30: 0 | B30: 29 | E30: 0x0100B7189DADE8EA1A40B9BF8DA45310AFE600A178D82D6E6846409061C607AC5C63EE | I30: A29 | J30: WP12: Regional integrated platforms | K30: Harmonize how UN system entities organize their regional work | L30: ASG DCO;DSG | M30: This response is being taken forward under work package 6 - the regional reset and therefore has the same milestones and action members. | Q30: 50 | T30: 29 | U30: 45990.104 | V30: 45967.007 | W30: 10 | X30: 274 | Y30: 2.0 | Z30: FALSE | AA30: 24cffaaa-3eba-446e-aae6-16a0f17f5138
A31: 0 | B31: 30 | E31: 0x0100B7189DADE8EA1A40B9BF8DA45310AFE600A178D82D6E6846409061C607AC5C63EE | I31: A30 | J31: WP13: Shared platform initiative | K31: Initiate a practical Shared Platform Initiative between DSG and ERC | L31: USG OCHA;DSG | M31: Action plan for the Shared Platform Initiative with specific timelines for immediate implementation and progress Report to the SG summarizing next steps | N31: 46052.958 | O31: 1. Amina Mohammed, Deputy Secretary-General, amina.mohammed@un.org 2. Tom Fletcher, Emergency Relief Coordinator and USG OCHA, fletcher@un.org | P31: 1. Garry Conille, Special Adviser, DCO, gconille@unicef.org 2. Edem Wosornu, Director, Crisis Response Division, OCHA, wosornu@un.org 3. Jean Philippe Bernardini, Senior Political Affairs Officer, Bernardini@un.org | Q31: 19 | R31: All initiatives rolled out and implementation finalized, as country contexts required. | S31: 46386.958 | T31: 30 | U31: 45990.093 | V31: 45967.007 | W31: 10 | X31: 274 | Y31: 2.0 | Z31: FALSE | AA31: f9391a1f-67e0-4722-b025-e496a65026f0
A32: 0 | B32: 31 | E32: 0x0100B7189DADE8EA1A40B9BF8DA45310AFE600A178D82D6E6846409061C607AC5C63EE | I32: A31 | J32: WP13: Shared platform initiative | K32: Prepare a proposal to ensure that RC/HCs and planning teams simplify Development Cooperation Frameworks, Humanitarian Response Plans, Peacebuilding Strategies and associated needs analyses for relevant settings | L32: USG OCHA;DSG | M32: Draft of the Proposal for simplifying country-level planning process where necessary (ensuring complementarity between the planning frameworks), with PBSO | N32: 46052.958 | O32: 1. Amina Mohammed, Deputy Secretary-General, amina.mohammed@un.org 2. Tom Fletcher, Emergency Relief Coordinator and USG OCHA, fletcher@un.org | P32: 1. Garry Conille, Special Adviser, DCO, gconille@unicef.org 2. Edem Wosornu, Director, Crisis Response Division, OCHA, wosornu@un.org 3. Jean Philippe Bernardini, Senior Political Affairs Officer, Bernardini@un.org | Q32: 57 | R32: Roll out of the simplified planning process and associated needs analysis system wide by July 2026 | S32: 46232.917 | T32: 31 | U32: 45990.095 | V32: 45967.007 | W32: 10 | X32: 274 | Y32: 2.0 | Z32: FALSE | AA32: 47337149-b408-4432-a000-500398c8e237
A33: 0 | B33: 32 | E33: 0x0100B7189DADE8EA1A40B9BF8DA45310AFE600A178D82D6E6846409061C607AC5C63EE | I33: A32 | J33: WP14: Unified services roadmap | K33: Prepare a Unified Services Roadmap, based on existing reform commitments and two models: some services will be provided by consolidated entities, and others through marketplaces of providers. | L33: Chair HLCM;ED WFP;Co-Chairs BIG | Q33: 63 | T33: 32 | U33: 45968.775 | V33: 45967.007 | W33: 10 | X33: 10 | Y33: 3.0 | Z33: FALSE | AA33: 7a7c388f-60ab-43ba-90cf-b7120019f75c
A34: 0 | B34: 33 | E34: 0x0100B7189DADE8EA1A40B9BF8DA45310AFE600A178D82D6E6846409061C607AC5C63EE | I34: A33 | J34: WP14: Unified services roadmap | K34: Integrate supply chains, taking the New Humanitarian Compact as the concrete starting point | L34: Chair HLCM;ED WFP;Co-Chairs BIG | Q34: 64 | T34: 33 | U34: 45967.007 | V34: 45967.007 | W34: 10 | X34: 10 | Y34: 1.0 | Z34: FALSE | AA34: acac1c02-b94b-4a0d-a18e-9847444880bc
A35: 0 | B35: 34 | E35: 0x0100B7189DADE8EA1A40B9BF8DA45310AFE600A178D82D6E6846409061C607AC5C63EE | I35: A34 | J35: WP14: Unified services roadmap | K35: Conduct assessment for integration of basic information and communication technology services, as well as payroll, human resources, finance, and enterprise resource planning (ERP) systems | L35: Chair HLCM;ED WFP;Co-Chairs BIG | Q35: 65 | T35: 34 | U35: 45967.007 | V35: 45967.007 | W35: 10 | X35: 10 | Y35: 1.0 | Z35: FALSE | AA35: 58a257ab-e9c9-4e75-ad8c-bb789d50dc7f
A36: 0 | B36: 35 | E36: 0x0100B7189DADE8EA1A40B9BF8DA45310AFE600A178D82D6E6846409061C607AC5C63EE | I36: A35 | J36: WP14: Unified services roadmap | K36: Accelerate the move toward a unified service backbone at country level; eliminate costly duplication on the ground | L36: Chair HLCM;ED WFP;Co-Chairs BIG | Q36: 78 | T36: 35 | U36: 45967.007 | V36: 45967.007 | W36: 10 | X36: 10 | Y36: 1.0 | Z36: FALSE | AA36: 144fea0a-f1d2-4250-94ce-e61a381d2b6f
A37: 0 | B37: 36 | E37: 0x0100B7189DADE8EA1A40B9BF8DA45310AFE600A178D82D6E6846409061C607AC5C63EE | I37: A36 | J37: WP14: Unified services roadmap | K37: Harmonize most indirect and programme support costs | L37: Chair HLCM;ED WFP;Co-Chairs BIG | Q37: 67 | T37: 36 | U37: 45967.007 | V37: 45967.007 | W37: 10 | X37: 10 | Y37: 1.0 | Z37: FALSE | AA37: 681c949c-4b29-47d6-af70-2839f47bb211
A38: 0 | B38: 37 | E38: 0x0100B7189DADE8EA1A40B9BF8DA45310AFE600A178D82D6E6846409061C607AC5C63EE | I38: A37 | J38: WP15: Technology | K38: Prepare a proposal to consolidate the fragmented landscape of basic cloud services, network infrastructures, office software and systems under realigned common providers that can serve the entire UN system, building on lessons from the International Computing Centre | L38: USG Policy;Chair DTN;SG ITU | Q38: 77 | T38: 37 | U38: 45967.849 | V38: 45967.007 | W38: 10 | X38: 10 | Y38: 2.0 | Z38: FALSE | AA38: 7a829912-9ce7-425f-8da2-2cd9afd99448
A39: 0 | B39: 38 | E39: 0x0100B7189DADE8EA1A40B9BF8DA45310AFE600A178D82D6E6846409061C607AC5C63EE | I39: A38 | J39: WP15: Technology | K39: Develop baseline of the current innovation landscape and a proposal for a Technology Accelerator Platform (TAP) to the Chief Executives Board | L39: USG Policy;Chair DTN;SG ITU | Q39: 62 | T39: 38 | U39: 45967.007 | V39: 45967.007 | W39: 10 | X39: 10 | Y39: 1.0 | Z39: FALSE | AA39: 979dec43-6b83-4b4b-9a81-3219ad834f2d
A40: 0 | B40: 39 | E40: 0x0100B7189DADE8EA1A40B9BF8DA45310AFE600A178D82D6E6846409061C607AC5C63EE | I40: A39 | J40: WP16: Data | K40: Prepare proposals for the Chief Executives Board at the end of October 2025 on how to guide phased implementation of Data Commons | L40: USG Policy;USG DESA;ED UNICEF | Q40: 71 | T40: 39 | U40: 45967.007 | V40: 45967.007 | W40: 10 | X40: 10 | Y40: 1.0 | Z40: FALSE | AA40: 53196679-9d32-4bc5-ae83-bafaf17b226a
A41: 0 | B41: 40 | E41: 0x0100B7189DADE8EA1A40B9BF8DA45310AFE600A178D82D6E6846409061C607AC5C63EE | I41: A40 | J41: WP16: Data | K41: Scale pooled funding approaches for data to support the Data Commons | L41: USG Policy;USG DESA;ED UNICEF | Q41: 72 | T41: 40 | U41: 45967.007 | V41: 45967.007 | W41: 10 | X41: 10 | Y41: 1.0 | Z41: FALSE | AA41: 270c26ce-fdd5-410f-81b7-bfa9e266e649
A42: 0 | B42: 41 | E42: 0x0100B7189DADE8EA1A40B9BF8DA45310AFE600A178D82D6E6846409061C607AC5C63EE | I42: A41 | J42: WP16: Data | K42: Pool the know-how of data analysts, engineers, and scientists to support the UN system, the new hubs, humanitarian clusters, and country teams alike | L42: USG Policy;USG DESA;ED UNICEF | Q42: 73 | T42: 41 | U42: 45967.007 | V42: 45967.007 | W42: 10 | X42: 10 | Y42: 1.0 | Z42: FALSE | AA42: 311f701a-adf2-4ebf-bc89-aab1de8e1e34
A43: 0 | B43: 42 | E43: 0x0100B7189DADE8EA1A40B9BF8DA45310AFE600A178D82D6E6846409061C607AC5C63EE | I43: A42 | J43: WP17: Training and research | K43: Merge UN Staff System College (UNSSC) into the UN Institute for Training and Research (UNITAR) | L43: ED UNITAR;Rector UNU | M43: Merger roadmap agreed by UNITAR and UNSSC, incl. needs assessment, scope, methodology, and joint plan for functional/financial mapping. Consultations launched. | N43: 46052.958 | O43: Michelle Gyles-McDonnough, Executive Director, UNITAR; GYLES-MCDONNOUGH@unitar.org | P43: UN System Staff College Miguel Panadero, Acting Director; m.panadero@unssc.org Silke Weinlich, Deputy Director; s.weinlich@unssc.org UNITAR Marina Dinca Vasilescu, Director, Operations; Marina.VASILESCU@unitar.org Evariste Karambizi, Director, Division for Peace; Evariste.KARAMBIZI@unitar.org UN Women Kirsi Madi, Deputy Executive Director for Resource Management, Sustainability and Partnerships; kirsi.madi@unwomen.org ITU Doreen Bogdan-Martin, Secretary-Generaldoreen.bogdan@itu.int Regina Valiullina; Regina.Valiullina@itu.int); ITC ILO Andreas Klemmer, Director of Training, International Training Centre of the International Labour Organization (ITC ILO); A.Klemmer@itcilo.org Development Coordination Office Oscar Fernández-Taranco, Assistant Secretary-General for Development Coordination; fernandez-taranco@un.org Helena Fraser, Director, Policy and Programming Branch; fraser@un.org Department of Operational Support Adrian Hills, Chief, Capacity Development and Operational Training Service; hillsa@un.org Mohammad Jeram, Chief of Operational Training Section, CDOTS; jeram@un.org Paola Matarazzo, Chief, Business Process & Systems Support Section, CDOTS; matarazzo@un.org | Q43: 68 | R43: Member states decide on the proposed merger based on the submitted transition plan. | S43: 46356.958 | T43: 42 | U43: 45989.688 | V43: 45967.007 | W43: 10 | X43: 173 | Y43: 3.0 | Z43: FALSE | AA43: f7b29e64-e0c1-4672-aeb6-a14776a4bc9a
A44: 0 | B44: 43 | E44: 0x0100B7189DADE8EA1A40B9BF8DA45310AFE600A178D82D6E6846409061C607AC5C63EE | I44: A43 | J44: WP17: Training and research | K44: Integrate UN Research Institute for Social Development (UNRISD) into the United Nations University (UNU) | L44: ED UNITAR;Rector UNU | Q44: 69 | T44: 43 | U44: 45989.643 | V44: 45967.007 | W44: 10 | X44: 175 | Y44: 3.0 | Z44: FALSE | AA44: 0801fade-5a3f-450b-85bc-4f14df75528f
A45: 0 | B45: 44 | E45: 0x0100B7189DADE8EA1A40B9BF8DA45310AFE600A178D82D6E6846409061C607AC5C63EE | I45: A44 | J45: WP17: Training and research | K45: Establish a Joint UN System Coordination Mechanism co-led by the UNU Rector and UNITAR Executive Director. | L45: ED UNITAR;Rector UNU | M45: Plan in place setting out scope and key considerations of the knowledge mapping exercise and entities to be engaged. | N45: 46052.958 | O45: Tshilidzi Marwala, UNU Rector, rector@unu.edu; Michelle Gyles-McDonnough, UNITAR Executive Director, gyles-mcdonnough@unitar.org | P45: Jonas Haertle, Chief Office of the Executive Director UNITAR, jonas.haertle@unitar.org; Mihoko Kumamoto, Director Division for Prosperity UNITAR, mihoko.kumamoto@unitar.org; Sabine Becker-Thierry, Director UNU Paris, sabine.becker@unu.edu; Francesco Foghetti, UNU Senior Legal Officer, foghetti@unu.edu | Q45: 70 | R45: Blueprint for Joint UN Coordination Machanism endorsed by SG. | S45: 46356.958 | T45: 44 | U45: 45989.374 | V45: 45967.007 | W45: 10 | X45: 154 | Y45: 2.0 | Z45: FALSE | AA45: 43c43cc5-daf3-486a-97e5-46bfc0293430
A46: 0 | B46: 45 | E46: 0x0100B7189DADE8EA1A40B9BF8DA45310AFE600A178D82D6E6846409061C607AC5C63EE | I46: A45 | J46: WP18: Funding mechanisms | K46: Launch a pooled funding review, including a review of administrative agent, secretariat, governance and support cost models, as well as partnership arrangements, to ensure pooled funding is consistently cheaper and more attractive than fragmented approaches | L46: SA Reform;ASG DCO | M46: Analysis, mapping and categorization of all pooled funding and data | N46: 46051.958 | O46: Jens Wandel, USG, EOSG Oscar Fernandez-Taranco, ASG, DCO Elizabeth Spehar, ASG, PBSO Alain Noudehou, Director, MPTFO, UNDP Susan Brown, ASG, Director of the Bureau for External Relations and Advocacy, UNDP Lisa Dougthen, Director,Humanitarian Financing and Resource Mobilization, OCHA | P46: Chris Stokes, Senior Programme Managers Fiona Bayat-Renoux, Deputy Chief of Staff, UNDP Klaus SimioniPederson D1, Chief of our Resource Mobilization Branch, UNFPA Alice Sequi, Chief of the Pooled Fund Branch, OCHA - | Q46: 74 | R46: All actions taken to respond to recommendations, with update published | S46: 46202.917 | T46: 45 | U46: 45989.376 | V46: 45967.007 | W46: 10 | X46: 74 | Y46: 2.0 | Z46: FALSE | AA46: 3359d204-c8df-4798-8c1f-8456ffc29579
A47: 0 | B47: 46 | E47: 0x0100B7189DADE8EA1A40B9BF8DA45310AFE600A178D82D6E6846409061C607AC5C63EE | I47: A46 | J47: WP18: Funding mechanisms | K47: Rationalize the portfolio of pooled funds, with particular focus on the Central Emergency Response Fund, the Peacebuilding Fund, the Joint SDG Fund, and the Country-Based Pooled Funds | L47: SA Reform;ASG DCO | M47: Analysis, mapping and categorization of all pooled funding and data | N47: 46051.958 | O47: Jens Wandel, USG, EOSG Oscar Fernandez-Taranco, ASG, DCO Elizabeth Spehar, ASG, PBSO Alain Noudehou, Director, MPTFO, UNDP Susan Brown, ASG, Director of the Bureau for External Relations and Advocacy, UNDP Lisa Dougthen, Director,Humanitarian Financing and Resource Mobilization, OCHA | P47: Chris Stokes, Senior Programme Managers Fiona Bayat-Renoux, Deputy Chief of Staff, UNDP Klaus SimioniPederson D1, Chief of our Resource Mobilization Branch, UNFPA Alice Sequi, Chief of the Pooled Fund Branch, OCHA - | Q47: 75 | R47: All actions taken to respond to proposals, as agreed by SG and relevant governing bodies | S47: 46370.958 | T47: 46 | U47: 45989.378 | V47: 45967.007 | W47: 10 | X47: 74 | Y47: 2.0 | Z47: FALSE | AA47: 535b6f1c-ecbf-4a29-a048-b5085d858409
A48: 0 | B48: 47 | E48: 0x0100B7189DADE8EA1A40B9BF8DA45310AFE600A178D82D6E6846409061C607AC5C63EE | I48: A47 | J48: WP18: Funding mechanisms | K48: Prepare a proposal on how core funding can become consistently cheaper and more attractive than fragmented approaches, including options to strengthen visibility for core contributors and partners | L48: SA Reform;ASG DCO | M48: Draft paper on strengthening the case for core funding finalized for discussion with stakeholders | N48: 46051.958 | O48: Jens Wandel, USG, EOSG Oscar Fernandez-Taranco, ASG, DCO Elizabeth Spehar, ASG, PBSO Alain Noudehou, Director, MPTFO, UNDP Susan Brown, ASG, Director of the Bureau for External Relations and Advocacy, UNDP Lisa Dougthen, Director,Humanitarian Financing and Resource Mobilization, OCHA | P48: Chris Stokes, Senior Programme Managers Fiona Bayat-Renoux, Deputy Chief of Staff, UNDP Klaus SimioniPederson D1, Chief of our Resource Mobilization Branch, UNFPA Alice Sequi, Chief of the Pooled Fund Branch, OCHA | Q48: 76 | R48: All entities with voluntary core funding to report on steps being taken to respond to the proposal | S48: 46202.917 | T48: 47 | U48: 45989.38 | V48: 45967.007 | W48: 10 | X48: 74 | Y48: 2.0 | Z48: FALSE | AA48: a7ab49f0-1257-49c3-a514-2fe6bf1287d5
A49: 0 | B49: 48 | E49: 0x0100B7189DADE8EA1A40B9BF8DA45310AFE600A178D82D6E6846409061C607AC5C63EE | I49: A48 | J49: WP18: Funding mechanisms | K49: Map existing Funding Compact review mechanisms and integrate discussion into a system-wide management mechanism at least once per year | L49: SA Reform;ASG DCO | M49: Mapping of Funding Compact dialogues at country level and in governing bodies complete. | N49: 46051.958 | O49: Jens Wandel, USG, EOSG Oscar Fernandez-Taranco, ASG, DCO Elizabeth Spehar, ASG, PBSO Alain Noudehou, Director, MPTFO, UNDP Susan Brown, ASG, Director of the Bureau for External Relations and Advocacy, UNDP Lisa Dougthen, Director,Humanitarian Financing and Resource Mobilization, OCHA | P49: Chris Stokes, Senior Programme Managers Fiona Bayat-Renoux, Deputy Chief of Staff, UNDP Klaus SimioniPederson D1, Chief of our Resource Mobilization Branch, UNFPA Alice Sequi, Chief of the Pooled Fund Branch, OCHA | Q49: 91 | R49: Final mapping and recommendations for integrating discussions to be complete. | S49: 46111.917 | T49: 48 | U49: 45989.381 | V49: 45967.007 | W49: 10 | X49: 74 | Y49: 2.0 | Z49: FALSE | AA49: c062af53-d55b-48e4-95d0-7f5f85f73898
A50: 0 | B50: 49 | E50: 0x0100B7189DADE8EA1A40B9BF8DA45310AFE600A178D82D6E6846409061C607AC5C63EE | I50: A49 | J50: WP19: Mandate creation support | K50: Prepare an action plan to improve staff support to Member State during mandate creation, based on mapping of existing capacities per mandating bodies and Member State priorities | L50: USG Policy;USG DGACM | Q50: 80 | T50: 49 | U50: 45967.007 | V50: 45967.007 | W50: 10 | X50: 10 | Y50: 1.0 | Z50: FALSE | AA50: 3387f472-7bd0-4177-bdb7-7412b13ecd10
A51: 0 | B51: 50 | E51: 0x0100B7189DADE8EA1A40B9BF8DA45310AFE600A178D82D6E6846409061C607AC5C63EE | I51: A50 | J51: WP19: Mandate creation support | K51: Prepare an action plan (as part of item 80) to Strengthen support by UN entities to coordinate and promote greater visibility across mandating bodies | L51: USG Policy;USG DGACM | Q51: 81 | T51: 50 | U51: 45967.007 | V51: 45967.007 | W51: 10 | X51: 10 | Y51: 1.0 | Z51: FALSE | AA51: 91eaa9dd-3c54-48ee-9733-c40d84ff19cf
A52: 0 | B52: 51 | E52: 0x0100B7189DADE8EA1A40B9BF8DA45310AFE600A178D82D6E6846409061C607AC5C63EE | I52: A51 | J52: WP19: Mandate creation support | K52: Prepare an action plan to complement the estimates of programme budget implications (PBI) for new mandates with additional info related to activities across the UN System | L52: USG Policy;USG DGACM | Q52: 83 | T52: 51 | U52: 45967.007 | V52: 45967.007 | W52: 10 | X52: 10 | Y52: 1.0 | Z52: FALSE | AA52: f991f37b-e4a0-48c1-aa93-885053e4ce92
A53: 0 | B53: 52 | E53: 0x0100B7189DADE8EA1A40B9BF8DA45310AFE600A178D82D6E6846409061C607AC5C63EE | I53: A52 | J53: WP20: UN budget / programme management | K53: Develop action plan to strengthen internal strategic oversight of the UN system division of labour at all levels to ensure effective, efficient programmatic and operational support, building on existing reforms | L53: CDC | Q53: 88 | T53: 52 | U53: 45967.007 | V53: 45967.007 | W53: 10 | X53: 10 | Y53: 1.0 | Z53: FALSE | AA53: c38cbb5b-4507-487d-b50d-2353bcdb7f62
A54: 0 | B54: 53 | E54: 0x0100B7189DADE8EA1A40B9BF8DA45310AFE600A178D82D6E6846409061C607AC5C63EE | I54: A53 | J54: WP20: UN budget / programme management | K54: As part of the standard budget guidance process, develop an action plan to ensure UN entities systematically review mandate citations in their programmes, incl. based on comparative advantage | L54: CDC | Q54: 89 | T54: 53 | U54: 45967.007 | V54: 45967.007 | W54: 10 | X54: 10 | Y54: 1.0 | Z54: FALSE | AA54: 7aa67e4e-482c-474c-b4a7-5ebbf7821b83
A55: 0 | B55: 54 | E55: 0x0100B7189DADE8EA1A40B9BF8DA45310AFE600A178D82D6E6846409061C607AC5C63EE | I55: A54 | J55: WP20: UN budget / programme management | K55: Prepare proposals by the SG as per Rule 105.6 of ST/SGB/2018/3 for the “GA, with justification, a list of outputs from the previous period which, in the judgement of the SG, can be discontinued” | L55: CDC | Q55: 92 | T55: 54 | U55: 45967.007 | V55: 45967.007 | W55: 10 | X55: 10 | Y55: 1.0 | Z55: FALSE | AA55: 803545fc-59ff-4b29-918b-78c7ffcad19d
A56: 0 | B56: 55 | E56: 0x0100B7189DADE8EA1A40B9BF8DA45310AFE600A178D82D6E6846409061C607AC5C63EE | I56: A55 | J56: WP21: System-wide results management | K56: Develop an action plan to strengthen and harmonize management for results mechanisms across the UN system, including how results are measured and communicated | L56: SA Reform | M56: Draft Concept Paper establishing the intellectual foundation for the proposed Action Plan including communication of systemwide results. | N56: 46051.958 | O56: Jens Wandel, SA, EOSG Fatoumata Ndiay, USG, OIOS Doreen Bogdan-Martin , USG, ITU Francine Pickup, Deputy Director of the Bureau for Policy and Programme | P56: Catalin Marinescu, Head of Strategy and Planning Division, ITU Clarice Wilson, Director of the UNDP Corporate Performance Unit Piyoo Kochar, Specialist, BTAD, UN UN Strategic Planning Network (UNSPN) and Finance and Budget Network under HLCM. | Q56: 93 | R56: Final Action Plan outlining an implementable system-wide pathway for a Results based management mechanism/ communication standards. | S56: 46170.917 | T56: 55 | U56: 45988.479 | V56: 45967.007 | W56: 10 | X56: 74 | Y56: 2.0 | Z56: FALSE | AA56: 62d345b3-df80-45d0-87d6-25d87a1499d1
A57: 0 | B57: 56 | E57: 0x0100B7189DADE8EA1A40B9BF8DA45310AFE600A178D82D6E6846409061C607AC5C63EE | I57: A56 | J57: WP22: Prevention, peacebuilding, peace support | K57: Establish a unified Peacebuilding and Peace Support Office (one ASG to be abolished) | L57: USG DPPA;USG DPO | Q57: 1 | T57: 56 | U57: 45967.007 | V57: 45967.007 | W57: 10 | X57: 10 | Y57: 1.0 | Z57: FALSE | AA57: b0b472bf-b78d-408d-9884-683492f92b6c
A58: 0 | B58: 57 | E58: 0x0100B7189DADE8EA1A40B9BF8DA45310AFE600A178D82D6E6846409061C607AC5C63EE | I58: A57 | J58: WP22: Prevention, peacebuilding, peace support | K58: Establish a single centre of excellence on Women, Peace and Security, bringing together the DPPA and DPO gender units | L58: USG DPPA;USG DPO | Q58: 2 | T58: 57 | U58: 45967.007 | V58: 45967.007 | W58: 10 | X58: 10 | Y58: 1.0 | Z58: FALSE | AA58: b38b2085-c112-4e68-ad32-2d4539783eb8
A59: 0 | B59: 58 | E59: 0x0100B7189DADE8EA1A40B9BF8DA45310AFE600A178D82D6E6846409061C607AC5C63EE | I59: A58 | J59: WP22: Prevention, peacebuilding, peace support | K59: Establish mechanisms – including joint strategies and programmes – to link cross-cutting functions (incl. expertise in data analytics, digital and artificial intelligence) | L59: USG DPPA;USG DPO | Q59: 3 | T59: 58 | U59: 45967.007 | V59: 45967.007 | W59: 10 | X59: 10 | Y59: 1.0 | Z59: FALSE | AA59: 8b4a9d4f-d24c-4ef0-b821-6d85eae50ce6
A60: 0 | B60: 59 | E60: 0x0100B7189DADE8EA1A40B9BF8DA45310AFE600A178D82D6E6846409061C607AC5C63EE | I60: A59 | J60: WP22: Prevention, peacebuilding, peace support | K60: Consolidate two Assistant Secretary-General posts for the Americas, Europe, Asia-Pacific, Middle East into one | L60: USG DPPA;USG DPO | Q60: 6 | T60: 59 | U60: 45967.007 | V60: 45967.007 | W60: 10 | X60: 10 | Y60: 1.0 | Z60: FALSE | AA60: e9f0faad-9d41-41ee-b405-10195008cfc1
A61: 0 | B61: 60 | E61: 0x0100B7189DADE8EA1A40B9BF8DA45310AFE600A178D82D6E6846409061C607AC5C63EE | I61: A60 | J61: WP22: Prevention, peacebuilding, peace support | K61: Combine the Western and Northern Africa divisions | L61: USG DPPA;USG DPO | Q61: 7 | T61: 60 | U61: 45967.007 | V61: 45967.007 | W61: 10 | X61: 10 | Y61: 1.0 | Z61: FALSE | AA61: bbb59de3-d5d9-4846-92ce-6ba3f763bbf3
A62: 0 | B62: 61 | E62: 0x0100B7189DADE8EA1A40B9BF8DA45310AFE600A178D82D6E6846409061C607AC5C63EE | I62: A61 | J62: WP22: Prevention, peacebuilding, peace support | K62: Integrate the UN Mission to Support the Hudaydah Agreement into the Office of the Special Envoy for Yemen | L62: USG DPPA;USG DPO | Q62: 8 | T62: 61 | U62: 45967.007 | V62: 45967.007 | W62: 10 | X62: 10 | Y62: 1.0 | Z62: FALSE | AA62: 3f45561d-3667-4df0-9f54-d0ad74330d75
A63: 0 | B63: 62 | E63: 0x0100B7189DADE8EA1A40B9BF8DA45310AFE600A178D82D6E6846409061C607AC5C63EE | I63: A62 | J63: WP22: Prevention, peacebuilding, peace support | K63: Streamline and align the UN Office for Central Africa (UNOCA) and the Office of the Special Envoy for the Great Lakes | L63: USG DPPA;USG DPO | Q63: 9 | T63: 62 | U63: 45967.007 | V63: 45967.007 | W63: 10 | X63: 10 | Y63: 1.0 | Z63: FALSE | AA63: d4f7e2af-275c-4006-8378-63f1514a07c2
A64: 0 | B64: 63 | E64: 0x0100B7189DADE8EA1A40B9BF8DA45310AFE600A178D82D6E6846409061C607AC5C63EE | I64: A63 | J64: WP22: Prevention, peacebuilding, peace support | K64: Streamline and align the Office of the Special Adviser for Cyprus with the UN Peacekeeping Force in Cyprus (UNFICYP) | L64: USG DPPA;USG DPO | Q64: 10 | T64: 63 | U64: 45967.007 | V64: 45967.007 | W64: 10 | X64: 10 | Y64: 1.0 | Z64: FALSE | AA64: b4732ccb-7c32-4cd8-9c63-3378dcd5c7be
A65: 0 | B65: 64 | E65: 0x0100B7189DADE8EA1A40B9BF8DA45310AFE600A178D82D6E6846409061C607AC5C63EE | I65: A64 | J65: WP22: Prevention, peacebuilding, peace support | K65: Rationalize the Office of the United Nations Representative to the Geneva International Discussions (UNRGID) | L65: USG DPPA;USG DPO | Q65: 11 | T65: 64 | U65: 45967.007 | V65: 45967.007 | W65: 10 | X65: 10 | Y65: 1.0 | Z65: FALSE | AA65: 102dc6de-40d4-4174-aea8-37bc653fcc73
A66: 0 | B66: 65 | E66: 0x0100B7189DADE8EA1A40B9BF8DA45310AFE600A178D82D6E6846409061C607AC5C63EE | I66: A65 | J66: WP22: Prevention, peacebuilding, peace support | K66: Host regional peace and development advisers in Regional Commissions | L66: USG DPPA;USG DPO | Q66: 49 | T66: 65 | U66: 45967.007 | V66: 45967.007 | W66: 10 | X66: 10 | Y66: 1.0 | Z66: FALSE | AA66: 521b7388-e478-4fb9-a56e-461d4762bfc8
A67: 0 | B67: 66 | E67: 0x0100B7189DADE8EA1A40B9BF8DA45310AFE600A178D82D6E6846409061C607AC5C63EE | I67: A66 | J67: WP22: Prevention, peacebuilding, peace support | K67: Begin co-locating special political missions with a regional focus and regional peace and development advisers with Regional Commissions serving as physical hosts (or remote participation) | L67: USG DPPA;USG DPO | Q67: 52 | T67: 66 | U67: 45967.008 | V67: 45967.008 | W67: 10 | X67: 10 | Y67: 1.0 | Z67: FALSE | AA67: acc77a1b-6d81-42b5-8d4b-892ed6777df2
A68: 0 | B68: 67 | E68: 0x0100B7189DADE8EA1A40B9BF8DA45310AFE600A178D82D6E6846409061C607AC5C63EE | I68: A67 | J68: WP22: Prevention, peacebuilding, peace support | K68: Align surge capacity for peace and security, rule of law, disarmament, demobilization and reintegration, security sector reform, small arms control, mission transitions, prevention of extremist violence, and counterterrorism to support regional needs. | L68: USG DPPA;USG DPO | Q68: 55 | T68: 67 | U68: 45967.008 | V68: 45967.008 | W68: 10 | X68: 10 | Y68: 1.0 | Z68: FALSE | AA68: 299d9815-6bd8-464c-8a25-07fe33b567f9
... A71: 0 | B71: 70 | E71: 0x0100B7189DADE8EA1A40B9BF8DA45310AFE600A178D82D6E6846409061C607AC5C63EE | I71: A70 | J71: WP23: Disarmament | K71: Begin co-locating regional disarmament centres, with Regional Commissions serving as physical hosts | L71: USG ODA | Q71: 53 | T71: 70 | U71: 45967.008 | V71: 45967.008 | W71: 10 | X71: 10 | Y71: 1.0 | Z71: FALSE | AA71: 0d60704c-a045-4481-9fc3-5d01ccf2572f
A72: 0 | B72: 71 | E72: 0x0100B7189DADE8EA1A40B9BF8DA45310AFE600A178D82D6E6846409061C607AC5C63EE | I72: A71 | J72: WP24: Drugs, crime, counterterrorism | K72: Integrate the UN Interregional Crime and Justice Research Institute (UNICRI) into the UN Office on Drugs and Crime (UNODC) | L72: USG UNODC;USG OCT | M72: Concept note developed | N72: 46141.917 | O72: John Brandolino; Acting Executive Director, UNODC; john.brandolino@un.org | P72: Candice Welsch; Director for Policy and Public Affairs, UNODC; candice.welsch@un.org | Q72: 4 | R72: ECOSOC resolution adopted | S72: 46233.917 | T72: 71 | U72: 45992.675 | V72: 45967.008 | W72: 10 | X72: 83 | Y72: 4.0 | Z72: FALSE | AA72: 22398f06-76cb-4413-a492-e820dd150289
A73: 0 | B73: 72 | E73: 0x0100B7189DADE8EA1A40B9BF8DA45310AFE600A178D82D6E6846409061C607AC5C63EE | I73: A72 | J73: WP24: Drugs, crime, counterterrorism | K73: Reinforce cooperation on counterterrorism and violent extremism, with clearer reporting lines, joint planning, and resource mobilization. | L73: USG UNODC;USG OCT | M73: By 31 January UNOCT will have circulated an options paper for the consideration of teh Global Counter-Terrorism Coordination Compact Committee. | O73: Mr. Alexandre Zouev, Acting Under-Secretary-General, UNOCT, alexandre.zouev@un.org | P73: Mr. Eihab Omaish, Director for Policy and Coordination, UNOCT, omaish@un.org Mr. Mauro Miedico, Director for Capacity Building, UNOCT, mauro.miedico@un.org | Q73: 12 | R73: By 30 June 2026, the Global Counter-Terrorism Coordination Compact Committee will have taken a decision and collectively committed to specific measures. | T73: 72 | U73: 45987.924 | V73: 45967.008 | W73: 10 | X73: 232 | Y73: 2.0 | Z73: FALSE | AA73: 2f945adb-fe92-42bd-83b8-2504a5da5d27
A74: 0 | B74: 73 | E74: 0x0100B7189DADE8EA1A40B9BF8DA45310AFE600A178D82D6E6846409061C607AC5C63EE | I74: A73 | J74: WP24: Drugs, crime, counterterrorism | K74: The Director overseeing the UNODC Terrorism Prevention Branch would also report to the Under-Secretary-General for Counter-Terrorism. | L74: USG UNODC;USG OCT | M74: By 31 January 2026, Action Members (principals) meet at least two times to discuss ideas. | O74: Mr. Alexandre Zouev, Acting Under-Secretary-General, UNOCT, alexandre.zouev@un.org | P74: Mr. Eihab Omaish, Director for Policy and Coordination, UNOCT, omaish@un.org Mr. Mauro Miedico, Director for Capacity Building, UNOCT, mauro.miedico@un.org Ms. Oguljeren Niyazberdiyeva, Chief, Officer of the Under-Secretary-General, UNOCT, niyazberdiyeva@un.org Mr. Mehdi Knani, Chief of Section, Front Office/OUSG, UNOCT, mehdi.knani@un.org Ms. Tamara Anderson, Chief of Section, Policy, Knowledge and Coordination Branch, UNOCT, andersont@un.org | Q74: 13 | R74: By 31 March 2026, the Director overseeing the UNODC Terrorism Prevention Branch would also report to the Under-Secretary-General for Counter-Terrorism. | T74: 73 | U74: 45991.059 | V74: 45967.008 | W74: 10 | X74: 232 | Y74: 2.0 | Z74: FALSE | AA74: 1a2a8946-c6ae-4992-a3b1-6f665f02ff7f
A75: 0 | B75: 74 | E75: 0x0100B7189DADE8EA1A40B9BF8DA45310AFE600A178D82D6E6846409061C607AC5C63EE | I75: A74 | J75: WP25: UNAIDS | K75: Sunset UNAIDS; mainstreaming capacity and expertise into relevant entities of the UN development system | L75: DSG;ED UNAIDS | M75: UNAIDS Board agrees process for delivering a final plan for full transformation of UNAIDS that is aligned with UN80; AIDS Strategy adopted | N75: 46008.958 | O75: Winnie Byanyima, USG, Executive Director, UNAIDS, byanyimaw@unaids.org | P75: Mahesh Mahalingam, Chief of Staff, maheshm@unaids.org Morten Ussing, Director, Governance, ussingm@unaids.org Christine Stegling, ASG, Deputy Executive Director, steglingc@unaids.org | Q75: 29 | R75: UNAIDS Board approves final transformation plan. | S75: 46365.958 | T75: 74 | U75: 45988.609 | V75: 45967.008 | W75: 10 | X75: 214 | Y75: 5.0 | Z75: FALSE | AA75: 5e6f0c7c-65e8-4b08-804d-b7850d8eeda3
A76: 0 | B76: 75 | E76: 0x0100B7189DADE8EA1A40B9BF8DA45310AFE600A178D82D6E6846409061C607AC5C63EE | I76: A75 | J76: WP26: Other merger review | K76: Provide support for further analysis on other potential mergers Member States may wish to explore | L76: SG | Q76: 32 | T76: 75 | U76: 45987.641 | V76: 45967.008 | W76: 10 | X76: 83 | Y76: 27.0 | Z76: FALSE | AA76: 412937fe-2b81-45ce-9a92-80aac66b84c7
A77: 0 | B77: 76 | E77: 0x0100B7189DADE8EA1A40B9BF8DA45310AFE600A178D82D6E6846409061C607AC5C63EE | I77: A76 | J77: WP27: Environment | K77: Undertake a thorough assessment of current arrangements and make proposals on possible structural changes and programme realignments on environmental issues | L77: USG UNEP;ES UNFCCC | M77: Terms of reference of the assessment finalized, including scope, methodology, timeline and specific outcomes. | N77: 46052.958 | O77: UNDP (development) TBC OHCHR (human rights) TBC DPPA/ PBSO (peace & Security) TBC UNCTAD (trade, minerals) (development secretariat) TBC IFAD (specialized agencies) TBC | P77: UNEP Ligia Noronha, ASG and Head of the NYO, ligia.noronha@un.org Rafael Peralta, Regional Director for North America, peralta@un.org UNFCCC Daniele Violetti, Senior Director, Programmes Coordination, dvioletti@unfccc.int James Grabert, Director, Mitigation, JGrabert@unfccc.int | Q77: 35 | R77: Assessment to reinforce environmental science,strengthen coordination on environment, joint knowledge integration hubs & possible strategic alignments completed | T77: 76 | U77: 45992.675 | V77: 45967.008 | W77: 10 | X77: 282 | Y77: 2.0 | Z77: FALSE | AA77: f1c41b45-5958-4132-8228-3d25d1ed2689
A78: 0 | B78: 77 | E78: 0x0100B7189DADE8EA1A40B9BF8DA45310AFE600A178D82D6E6846409061C607AC5C63EE | I78: A77 | J78: WP28: Other UN Secretariat development realignments | K78: Realign macroeconomic analysis capacities across DESA, UNCTAD, and the Regional Commissions to create a unified "single entry point" for Member States, anchored in joint mechanisms | L78: USG DESA;ES ECA;SG UNCTAD | Q78: 30 | T78: 77 | U78: 45967.008 | V78: 45967.008 | W78: 10 | X78: 10 | Y78: 1.0 | Z78: FALSE | AA78: 88dce2ee-7a28-4014-a628-1fcfa48e6783
A79: 0 | B79: 78 | E79: 0x0100B7189DADE8EA1A40B9BF8DA45310AFE600A178D82D6E6846409061C607AC5C63EE | I79: A78 | J79: WP28: Other UN Secretariat development realignments | K79: Realign UN Secretariat support for LDCs, LLDCs and SIDS across DESA, UNCTAD and OHRLLS | L79: USG DESA;ES ECA;SG UNCTAD | Q79: 31 | T79: 78 | U79: 45967.008 | V79: 45967.008 | W79: 10 | X79: 10 | Y79: 1.0 | Z79: FALSE | AA79: effe4af8-16cb-4bfc-be6b-447a74ba5097
A80: 0 | B80: 79 | E80: 0x0100B7189DADE8EA1A40B9BF8DA45310AFE600A178D82D6E6846409061C607AC5C63EE | I80: A79 | J80: WP28: Other UN Secretariat development realignments | K80: Abolish the Special Coordinator for Development in the Sahel post and its associated office (functions and responsibilities are absorbed and performed by existing entities) | L80: USG DESA;ES ECA;SG UNCTAD | Q80: 38 | T80: 79 | U80: 45967.008 | V80: 45967.008 | W80: 10 | X80: 10 | Y80: 1.0 | Z80: FALSE | AA80: 188cf458-3dcf-436f-be6a-36cd85b5584e
A81: 0 | B81: 80 | E81: 0x0100B7189DADE8EA1A40B9BF8DA45310AFE600A178D82D6E6846409061C607AC5C63EE | I81: A80 | J81: WP29: Mandate registries and tools | K81: For the UN Secretariat, refine mandates.un.org to serve as sustainable registry; Other entities to build out similar registries for their mandating bodies | L81: USG Policy | Q81: 79 | T81: 80 | U81: 45967.008 | V81: 45967.008 | W81: 10 | X81: 10 | Y81: 1.0 | Z81: FALSE | AA81: eef58e84-edfc-4ed7-b3e3-1a2792ea0a1b
A82: 0 | B82: 81 | E82: 0x0100B7189DADE8EA1A40B9BF8DA45310AFE600A178D82D6E6846409061C607AC5C63EE | I82: A81 | J82: WP29: Mandate registries and tools | K82: Develop tools to assist in research for mandate creation | L82: USG Policy | Q82: 82 | T82: 81 | U82: 45967.008 | V82: 45967.008 | W82: 10 | X82: 10 | Y82: 1.0 | Z82: FALSE | AA82: 561df0b6-35b8-4704-8d1c-2bc04469468a
A83: 0 | B83: 82 | E83: 0x0100B7189DADE8EA1A40B9BF8DA45310AFE600A178D82D6E6846409061C607AC5C63EE | I83: A82 | J83: WP30: SG reports | K83: Assess trends in word-limit compliance and develop an action plan for improvements (as part of item 86) | L83: CDC | Q83: 84 | T83: 82 | U83: 45973.669 | V83: 45967.008 | W83: 10 | X83: 10 | Y83: 5.0 | Z83: FALSE | AA83: 89ad93be-2dbc-490a-a9fd-4ea9ae20865f
A84: 0 | B84: 83 | E84: 0x0100B7189DADE8EA1A40B9BF8DA45310AFE600A178D82D6E6846409061C607AC5C63EE | I84: A83 | J84: WP30: SG reports | K84: Assess trends and patterns in report overlap and fragmentation, and develop an action plan for improvement (as part of item 86) | L84: CDC | Q84: 85 | T84: 83 | U84: 45967.008 | V84: 45967.008 | W84: 10 | X84: 10 | Y84: 1.0 | Z84: FALSE | AA84: b7e88b72-f1c4-4d46-87b3-ebdc70359b22
A85: 0 | B85: 84 | E85: 0x0100B7189DADE8EA1A40B9BF8DA45310AFE600A178D82D6E6846409061C607AC5C63EE | I85: A84 | J85: WP30: SG reports | K85: Constitute a cross-departmental working group to develop an action plan for improvements in reporting format options for different types of information requests | L85: CDC | Q85: 86 | T85: 84 | U85: 45967.008 | V85: 45967.008 | W85: 10 | X85: 10 | Y85: 1.0 | Z85: FALSE | AA85: 1c420c13-6b4d-4049-99ed-3a6e20fcd0be
A86: 0 | B86: 85 | E86: 0x0100B7189DADE8EA1A40B9BF8DA45310AFE600A178D82D6E6846409061C607AC5C63EE | I86: A85 | J86: WP30: SG reports | K86: Display per-report download counts on UN ODS and UN Digital Library pages for each document | L86: CDC | Q86: 87 | T86: 85 | U86: 45967.008 | V86: 45967.008 | W86: 10 | X86: 10 | Y86: 1.0 | Z86: FALSE | AA86: 784b15b1-5451-4910-b074-d49cf1006e16
A87: 0 | B87: 86 | E87: 0x0100B7189DADE8EA1A40B9BF8DA45310AFE600A178D82D6E6846409061C607AC5C63EE | I87: A86 | J87: WP31: UN Secretariat efficiencies and improvement | K87: Implement residual actions from Phase I of the Working Group on Efficiencies, as per Rev. estimates for programme budget 2026 and support account for 25/26, not included in or relevant for WP#14 | L87: USG DMSPC;USG DOS | M87: Common Administrative Platform (CAP) in New York established with initial operating capacity and all Executive Office personnel reporting to DOS. | N87: 46052.958 | O87: Catherine Pollard, pollardc@un.org; Atul Khare, khare@un.org | P87: Patrick Carey, Director, careyp@un.org | Q87: 98 | R87: CAP fully operational in /New York. Expansion to additional locations to be undertaken in Phase II. | S87: 46233.917 | T87: 86 | U87: 45990.717 | V87: 45967.008 | W87: 10 | X87: 273 | Y87: 2.0 | Z87: FALSE | AA87: 972c4ad6-e7d1-45f4-8464-d35437fd8531
A88: 0 | B88: 87 | E88: 0x0100B7189DADE8EA1A40B9BF8DA45310AFE600A178D82D6E6846409061C607AC5C63EE | I88: A87 | J88: WP31: UN Secretariat efficiencies and improvement | K88: Implement residual actions from Phase II of the Working Group on Efficiencies, not to be included in or relevant for WP#14 | L88: USG DMSPC;USG DOS | Q88: 99 | T88: 87 | U88: 45967.008 | V88: 45967.008 | W88: 10 | X88: 10 | Y88: 1.0 | Z88: FALSE | AA88: 1ea3bc40-4d71-4b43-8b61-5c6401789136
A89: 0 | B89: 88 | E89: 0x0100B7189DADE8EA1A40B9BF8DA45310AFE600A178D82D6E6846409061C607AC5C63EE | T89: 88 | U89: 45989.721 | V89: 45989.721 | W89: 109 | X89: 109 | Y89: 1.0 | Z89: FALSE | AA89: 103422ce-db87-48df-afa1-0b9fce4307dc
A90: 0 | B90: 89 | E90: 0x0100B7189DADE8EA1A40B9BF8DA45310AFE600A178D82D6E6846409061C607AC5C63EE | T90: 89 | U90: 45989.724 | V90: 45989.724 | W90: 109 | X90: 109 | Y90: 1.0 | Z90: FALSE | AA90: 29f41f3f-5cd0-4473-a16e-120d9fa744eb
A91: 0 | B91: 90 | E91: 0x0100B7189DADE8EA1A40B9BF8DA45310AFE600A178D82D6E6846409061C607AC5C63EE | T91: 90 | U91: 45989.729 | V91: 45989.729 | W91: 109 | X91: 109 | Y91: 1.0 | Z91: FALSE | AA91: 3a2955d5-97fa-4791-9291-5f03880e977b
A92: 0 | B92: 91 | E92: 0x0100B7189DADE8EA1A40B9BF8DA45310AFE600A178D82D6E6846409061C607AC5C63EE | T92: 91 | U92: 45990.077 | V92: 45990.077 | W92: 274 | X92: 274 | Y92: 1.0 | Z92: FALSE | AA92: 290053a7-5973-4542-b1f5-bab5197a4f04

Sheet UN80 Action Plan
A1: WP No. | B1: Work Package | C1: Action No | D1: Indicative Action | E1: WP Leads | F1: Action Lead(s) | G1: Action Support(s) | H1: ActionEntity(s) | I1: Milestone 1 | J1: Milestone 1 Deadline | K1: Milestone Final | L1: Milestone Final Deadline | M1: Sense-checked | N1: Notes
A2: 1 | B2: WP1: Peace operations (task delegation; review) | C2: 14 | D2: Delegate relevant programmatic tasks such as rule of law, governance and child protection – and the associated resources – to UN system entities best equipped to deliver them. | E2: USG DPPA;USG DPO | F2: Rosemary DiCarlo, USG DPPA, rosemary.dicarlo@un.org; Jean-Pierre Lacroix, USG DPO, jean-pierre.lacroix@un.org USGs DPPA and DPO, Rosemary DiCarlo and Jean-Pierre Lacroix, with participation from UNDP, OCHA, DCO, OHCHR, PBSO, OROLSI, UNICEF, UN Women, and the SRSGs CAAC and SVC | G2: David Haeri, Director DPET, DPO, haeri@un.org; Asif Khan, Director PMD, DPPA, khan34@un.org | H2: DPPA;DPO | I2: First discussion held. | J2: 46021 | K2: Clarification on delegation of relevant programmatic tasks. | L2: 46111 | M2: Confirmation needed | N2: Confirmation on standing members; align on ambition between milestone and report proposal; notes on PPB submission end of February.
A3: 1 | B3: WP1: Peace operations (task delegation; review) | C3: 15 | D3: Present comprehensive proposal for the reset of peace operations to Member States upon conclusion of the review mandated by the Pact for the Future. | E3: USG DPPA;USG DPO | F3: Rosemary DiCarlo, USG DPPA, rosemary.dicarlo@un.org; Jean-Pierre Lacroix, USG DPO, jean-pierre.lacroix@un.org | G3: David Haeri, Director DPET, DPO, haeri@un.org; Asif Khan, Director PMD, DPPA, khan34@un.org | H3: DPPA;DPO | I3: Review of the future of peace operations completed | J3: 46111 | K3: Review of the future of peace operations completed. | L3: 46111 | M3: Confirmation needed | N3: Confirmation on standing members; align on ambition between milestone and report proposal; notes on proposals after review and PPB submission end of February.
A4: 2 | B4: WP2: New Humanitarian Compact | C4: 16 | D4: Streamline Humanitarian Needs and Response Plans to become shorter and sharper | E4: USG OCHA | F4: Tom Fletcher, Under-Secretary-General for Humanitarian Affairs and Emergency Relief Coordinator (OCHA) - fletcher@un.org | G4: Hansjoerg Strohmeyer, Policy Director, OCHA - strohmeyerh@un.org | H4: OCHA | M4: Confirmation needed | N4: Milestones and timeline missing
A5: 2 | B5: WP2: New Humanitarian Compact | C5: 17 | D5: Integrate global supply chains, coordinating procurement of key items, pool use of global freight and logistics, and unbranded in-country services open to the entire UN system | E5: USG OCHA | F5: Tom Fletcher, Under-Secretary-General for Humanitarian Affairs and Emergency Relief Coordinator (OCHA) - fletcher@un.org Catherine Russell, Executive Director, UNICEF - crussell@unicef.org Cindy McCain, Executive Director, World Food Programme (WFP) - cindy.mccain@wfp.org Atul Khare, Under-Secretary-General for Operational Support (UN-DOS) - khare@un.org | G5: Hansjoerg Strohmeyer, Policy Director, OCHA - strohmeyerh@un.org AnneMarie Van Den Berg, Assistant-Secretary-General, Office of Supply Chain Management (OSCM), DOS - vandenberga@un.org Corinne Fleischer, Director, Supply Chain, WFP - Corinne.fleischer@wfp.org Leila Gharagozloo Pakkala, Director, Supply Divisions, UNICEF - lpakkala@unicef.org | H5: OCHA;UNICEF;WFP;DOS | I5: Interagency supply chain pilot design endorsed, and starter locations agreed | J5: 46052 | K5: Integrated UN supply chain operational across agencies, with joint procurement and shared logistics in starter countries, improving speed and cost | L5: 46386 | M5: Attention to timeline | N5: Consider final timeline earlier than December
A6: 2 | B6: WP2: New Humanitarian Compact | C6: 18 | D6: Scale common services with a Global Services Hub and interoperable digital platforms to help consolidate surge rosters, logistics, security, telecoms and engineering support | E6: USG OCHA | F6: Tom Fletcher, Under-Secretary-General for Humanitarian Affairs and Emergency Relief Coordinator (OCHA) - fletcher@un.org Filippo Grandi, United Nations High Commissioner for Refugees (UNHCR) - grandi@unhcr.org Cindy McCain, Executive Director, World Food Programme (WFP) - cindy.mccain@wfp.org | G6: Hansjoerg Strohmeyer, Policy Director, OCHA - strohmeyerh@un.org Kelly Tallman Clements - Deputy High Commissioner for Refugees, UNHCR - clements@unhcr.org Carl Skau, Deputy Executive Director and Chief Operating Officer, World Food Programme (WFP) - carl.skau@wfp.org | H6: OCHA;UNHCR;WFP | I6: Initial package of priority common services identified, drawing on existing practices (e.g. fleet, booking, engineering, security/emergency mgmt | J6: 46052 | K6: Priority common services expanded across several contexts with multiple agencies, with a review demonstrating clearer and more efficient shared delivery | L6: 46386 | M6: Attention to timeline | N6: Consider final timeline earlier than December
A7: 2 | B7: WP2: New Humanitarian Compact | C7: 20 | D7: Initiate new Humanitarian Data Collaborative, to scale common platforms, collective financing, shared centres, capacities and standards | E7: USG OCHA | F7: Tom Fletcher, Under-Secretary-General for Humanitarian Affairs and Emergency Relief Coordinator (OCHA), fletcher@un.org Filippo Grandi, United Nations High Commissioner for Refugees (UNHCR) - grandi@unhcr.org Catherine Russell, Executive Director, UNICEF - crussell@unicef.org Cindy McCain, Executive Director, World Food Programme (WFP) - cindy.mccain@wfp.org Amy Pope, Director General, International Organization for Migration (IOM) - dg@iom.int | G7: Hansjoerg Strohmeyer, Policy Director, OCHA - strohmeyerh@un.org Jean-Martin Bauer, Director, Assessments, Planning, Policy and Research, WFP - jean-martin.bauer@wfp.org | H7: OCHA;UNHCR;UNICEF;WFP;IOM | I7: Humanitarian Cluster Data Workplan agreed, with quick wins, starter countries, governance options and a joint data-sharing ambition. | J7: 46052 | K7: Humanitarian Data Collaborative established, scaling platforms, financing and shared capacities and standards. | L7: 46386 | M7: Attention to timeline | N7: Consider final timeline earlier than December
A8: 2 | B8: WP2: New Humanitarian Compact | C8: 21 | D8: Initiate Collaborative Humanitarian Diplomacy Initiative to bring agencies together under the coordination of the Emergency Relief Coordinator | E8: USG OCHA | F8: Tom Fletcher, Under-Secretary-General for Humanitarian Affairs and Emergency Relief Coordinator (OCHA) - fletcher@un.org Filippo Grandi, United Nations High Commissioner for Refugees (UNHCR) - grandi@unhcr.org Catherine Russell, Executive Director, UNICEF - crussell@unicef.org Cindy McCain, Executive Director, World Food Programme (WFP) - cindy.mccain@wfp.org Amy Pope, Director General, International Organization for Migration (IOM) - dg@iom.int | G8: Hansjoerg Strohmeyer, Policy Director, OCHA - strohmeyerh@un.org Fredrick Lee-Ohlsson, Director, OED-DIP, WFP - fredrick.lee-ohlsson@wfp.org Ted Chaiban, Deputy Executive Director, UNICEF - tchaiban@unicef.org Ugochi Daniels, Deputy Director General for Operations, International Organization for Migration (IOM) - udaniels@iom.int Shahrzad Tadjbakhsh, Director, Division of International Protection, UNHCR - tadjbakh@unhcr.org | H8: OCHA;UNHCR;UNICEF;WFP;IOM | I8: Principals’ Humanitarian Diplomacy mechanism launched, with agreed priorities, meeting cadence, and initial crisis list identified | J8: 46052 | K8: Collab. humanitarian diplomacy functioning system-wide with coordinated messaging, shared strategies and clear impact in priority crises | L8: 46386 | M8: Attention to timeline | N8: Consider final timeline earlier than December
A9: 2 | B9: WP2: New Humanitarian Compact | C9: 22 | D9: Align agencies’ responsibilities: FAO/WFP/IFAD on food security | E9: USG OCHA | F9: Rania DAGASH-KAMARA, Assistant Executive Director Partnerships and Innovation - rania.dagash@wfp.org | G9: Laura Turner, Deputy Director of Emergency Coordination, WFP - Laura.Turner@wfp.org Hansjoerg Strohmeyer, Policy Director, OCHA - strohmeyerh@un.org | H9: WFP | I9: RBAs agree on a light, practical approach for more coherent work in fragile settings, clarifying complementary roles, choosing small number of priority countries | J9: 46052 | K9: In priority contexts, RBAs show clearer alignment in practice, with better sequencing and less duplication, and share a short lessons note with UN80 bodies | L9: 46386 | M9: Confirmation needed | N9: Confirmation on standing members; consider final timeline earlier than December
A10: 2 | B10: WP2: New Humanitarian Compact | C10: 23 | D10: Align agencies’ responsibilities: UNHCR/IOM on joint institutional approaches (incl. route-based programming) | E10: USG OCHA | F10: Filippo Grandi, United Nations High Commissioner for Refugees (UNHCR) - grandi@unhcr.org Amy Pope, Director General, International Organization for Migration (IOM) - dg@iom.int | G10: Shahrzad Tadjbakhsh, Director, Division of International Protection, UNHCR - tadjbakh@unhcr.org Ugochi Daniels, Deputy Director General for Operations, IOM - udaniels@iom.int Hansjoerg Strohmeyer, Policy Director, OCHA - strohmeyerh@un.org | H10: UNHCR;IOM | I10: UNHCR and IOM select 2-3 contexts needing clearer roles on mixed movements and agree on a light, context-specific approach to improve complementarity | J10: 46052 | K10: In those contexts, UNHCR and IOM show better complementarity on mixed movements – clearer roles, fewer parallels, better sequencing – and share lessons with UN80 | L10: 46386 | M10: Confirmation needed | N10: Consider final timeline earlier than December; confirmation on milestone definitions
A11: 2 | B11: WP2: New Humanitarian Compact | C11: 24 | D11: Align agencies’ responsibilities: UNICEF/WFP/UNHCR/IOM on beneficiary data | E11: USG OCHA | F11: Filippo Grandi, United Nations High Commissioner for Refugees (UNHCR) - grandi@unhcr.org Amy Pope, Director General, International Organization for Migration (IOM) - dg@iom.int Catherine Russell, Executive Director, UNICEF - crussell@unicef.org Cindy McCain, Executive Director, World Food Programme (WFP) - cindy.mccain@wfp.org | G11: Ryan Beech, WFP - Ryan.Beech@wfp.org Hansjoerg Strohmeyer, Policy Director, OCHA - strohmeyerh@un.org UNICEF/IOM/HCR - To Be Confirmed | H11: UNHCR;IOM;UNICEF;WFP | I11: Agencies endorse shared principles for beneficiary-data alignment and identify 1-2 contexts for early interoperability pilots across HOPE, PRIMES, SCOPE, BRAVE | J11: 46052 | K11: Early pilots show less duplication and better interoperability across beneficiary-data systems, with a short lessons-learned note shared with UN80 bodies | L11: 46386 | M11: Confirmation needed | N11: Confirmation on standing members; consider final timeline earlier than December
A12: 2 | B12: WP2: New Humanitarian Compact | C12: 25 | D12: Align agencies’ responsibilities: WHO/UNICEF/WFP on health and nutrition | E12: USG OCHA | F12: Catherine Russell, Executive Director, UNICEF - crussell@unicef.org Cindy McCain, Executive Director, World Food Programme (WFP) - cindy.mccain@wfp.org | G12: Ted Chaiban, Deputy Executive Director, UNICEF - tchaiban@unicef.org Ilaria Dettori, Director, Nutrition Services, WFP - ilaria.dettori@wfp.org Hansjoerg Strohmeyer, Policy Director, OCHA - strohmeyerh@un.org WHO - To Be Confirmed | H12: UNICEF;WFP | I12: Dedication discussion held with relevant agencies, with initial parameters agreed | J12: 46052 | K12: Clearly defined roles and responsibilities, with information disseminated at the field level and with Member States and Nutrition cluster partners | L12: 46386 | M12: Confirmation needed | N12: Confirmation on standing members; consider final timeline earlier than December
A13: 3 | B13: WP3: UNDP/UNOPS | C13: 26 | D13: Conduct a thorough assessment of the benefits of a merger between UNDP and UNOPS; analysis to be presented to the Executive Boards in February 2026 | E13: DSG;Administrator UNDP;ED UNOPS | F13: Amina Mohammed, DSG, amina.mohammed@un.org; Jorge Moreira Da Silva, USG UNOPS, jorge.moreiradasilva@unops.org; Alexander de Croo, USG UNDP, alexander.de.croo@undp.org | G13: Sonja Leighton-Kone, ASG, UNOPS, sonjalk@unops.org; Linda Maguire, ASG, UNDP, linda.maguire@undp.org; Rahul Malhotra, Director New York Office, UNOPS, rahulm@unops.org; Fiona Bayat-Renoux, Deputy Chief of Staff, UNDP, Fiona.bayat-renoux@undp.org; Jean-Philippe Bernardini, Senior Political Affairs Officer, EOSG, Bernardini@un.org | H13: EOSG (ODSG);UNDP;UNOPS | I13: Draft initial assessment analysis of the ‘as is’ with high level merger options, pros, cons, risk analysis for internal consultations completed | J13: 46040 | K13: Thorough assessment of selected option(s) provided to Member States and guidance given through a General Assembly decision | L13: 46264 | M13: Finalized
A14: 4 | B14: WP4: UNFPA/UN Women | C14: 27 | D14: Conduct a thorough assessment of the benefits of a merger of UNFPA and UN Women and their respective mandates | E14: DSG;ED UNFPA;ED UN Women | F14: Amina Mohammed, DSG, Amina.mohammed@un.org; Sima Bahous, Executive Director, UN Women sima.bahous@unwomen.org; Diene Keita, Executive Director, UNFPA, Keita@unfpa.org | G14: Jean Philippe Bernardini, Senior Political Affairs Officer, EOSG, bernardini@un.org; Sam Choritz, Chief of Staff, UNFPA, choritz@unfpa.org; Mohammad Naciri, Chief of Staff, UN Women, mohammad.naciri@unwomen.org | H14: EOSG (ODSG);UN Women;UNFPA | I14: Strategic merger assessment completed for internal consultations, including risk/benefit considerations | J14: 46052 | K14: By mid-2026, a thorough assessment is provided to Member States for a General Assembly decision | L14: 46233 | M14: Finalized
A15: 4 | B15: WP4: UNFPA/UN Women | C15: 28 | D15: Conduct a thorough assessment to consider options to optimize normative functions of UNFPA on population statistics and related activities, including those currently undertaken by DESA | E15: DSG;ED UNFPA;ED UN Women | F15: Amina Mohammed, DSG, Amina.mohammed@un.org; Sima Bahous, Executive Director, UN Women sima.bahous@unwomen.org; Diene Keita, Executive Director, UNFPA, Keita@unfpa.org | G15: Jean Philippe Bernardini, Senior Political Affairs Officer, bernardini@un.org; Sam Choritz, Chief of Staff, UNFPA, choritz@unfpa.org; Mohammad Naciri, Chief of Staff, UN Women, mohammad.naciri@unwomen.org | H15: EOSG (ODSG);UN Women;UNFPA | I15: Options for optimization of the UN’s work on population statistics and related activities finalized for Secretary-General's consideration and integrated in merger analysis | J15: 46052 | K15: A final assessment integrated into the UN Women/UNFPA merger process, as per timelines above | L15: 46233 | M15: Finalized
A16: 5 | B16: WP5: UNCT reconfiguration | C16: 39 | D16: Propose a model to reconfigure country teams via system-wide working group, chaired by the Deputy Secretary-General | E16: DSG | F16: Amina J. Mohammed, DSG, Amina.mohammed@un.org; Jorge Moreira Da Silva, USG UNOPS, jorge.moreiradasilva@unops.org | G16: Rahul Malhorta, Director, UNOPS, rahulm@unops.org; Jean Philippe Bernardini, Senior Political Affairs Officer, EOSG, bernardini@un.org | H16: EOSG (ODSG);UNOPS | I16: Outline of the draft proposals presented to the Secretary-General for guidance | J16: 46029 | K16: Member States taken action/decided on final set of proposals presented by the Secretary-General (report finalized by 31 May 2026 – TBC, depend on UN80 next reporting cycle) | L16: 46263 | M16: Finalized
A17: 5 | B17: WP5: UNCT reconfiguration | C17: 40 | D17: Strengthen and recalibrate the Resident Coordinator system to better leverage knowledge hubs, expertise-on-demand, and non-resident entities | E17: DSG | F17: Amina J. Mohammed, DSG, Amina.mohammed@un.org; Oscar Fernandez-Taranco, ASG DCO, fernandez-taranco@un.org | G17: Jean Philippe Bernardini, Senior Political Affairs Officer, EOSG, bernardini@un.org | H17: EOSG (ODSG);DCO | I17: The parameters for the recalibration of the RC system defined and being consulted with Member States (e.g., change in DCO structure, more tailored approach) | J17: 46052 | K17: All measures to recalibrate the RC system (DCO 2.0) implemented and a decision to enhance the funding model of the RC system successfully tabled in the General Assembly | L17: 46263 | M17: Finalized
A18: 6 | B18: WP6: Regional reset | C18: 36 | D18: Establish a system-wide working group, chaired by the Deputy Secretary-General, to develop proposals on how to advance a reset of regional capacities for sustainable development, incl. on how to institutionalize Regional Integrated Platforms | E18: DSG | F18: Amina J. Mohammed, DSG, Amina.mohammed@un.org; Izumi Nakamitsu, USG ODA, nakamitsu@un.org | G18: Jean Philippe Bernardini, Senior Political Affairs Officer, EOSG, bernardini@un.org | H18: EOSG (ODSG);ODA | I18: System-wide working group convened and draft outline finalized and shared with the Secretary-General for guidance | J18: 46029 | K18: All aspects of the regional reset under SG prerogative implemented and decisions taken by Member States on aspects requiring new mandates (report May 2026 - TBC, depend on UN80 next reporting cycle) | L18: 46263 | M18: Finalized
A19: 6 | B19: WP6: Regional reset | C19: 37 | D19: Systematize the practice of hosting regional capacities within the Regional Economic Commissions, starting with DCO regional directors and teams | E19: DSG | F19: Amina J. Mohammed, DSG, Amina.mohammed@un.org; Izumi Nakamitsu, USG ODA, nakamitsu@un.org; Oscar Fernandez Taranco, ASG DCO, fernandez-taranco@un.org | G19: Jean Philippe Bernardini, Senior Political Affairs Officer, EOSG, bernardini@un.org; Nadia Hadi, Chief of Staff, DCO, hadin@un.org; Thilmeeza Hussain, Director, Regional Commission Office, thilmeeza.hussain@un.org | H19: EOSG (ODSG);ODA;DCO | I19: Develop initial proposals for co-hosting for further consultation, taking into consideration the unique regional needs and contexts | J19: 46052 | K19: Relocation of respective offices to be hosted by RECs is complete or ongoing, according to implementation plan developed for each region by 29 May 2026 | L19: 46170 | M19: Finalized
A20: 7 | B20: WP7: Joint knowledge hubs | C20: 33 | D20: Establish Joint Knowledge Hubs to pool knowledge on key issues spread across UN development system entities and avoid duplications, including finding the best placed entities to co-leads (through joint mechanisms) | E20: USG DESA;SG UNCTAD | F20: Rebeca Grynspan, SG UNCTAD, rebeca.grynspan@unctad.org; LI Junhua, USG DESA, junhua.li@un.org | G20: Adnan Issa, Director Programme Management, UNCTAD, issa@unctad.org; Wai Min Kwok, Acting Chief Office of the USG, DESA, kwok@un.org; Carlos Razo, Senior Coordinator Office of the Secretary General, UNCTAD, carlos.razo@un.org; Guenther Gross, Senior Programme Management Officer Office of the USG, DESA, gross1@un.org | H20: DESA;UNCTAD | I20: The first meeting endorsed the concept note, agreed on hub list with leads, and committed to distinct value and collaboration with UN mechanisms | J20: 46052 | K20: Established hubs deliver coherent, efficient UN-wide support, integrating data and knowledge for policy coherence and innovative solutions | L20: 46386 | M20: Attention to timeline | N20: Review final deadline if intention is to demonstrate results from implementation before end 2026
A21: 8 | B21: WP8: Expertise-on-demand mechanism | C21: 34 | D21: Create a pro-active mechanism UN system-wide expertise on demand, particularly from specialized agencies and non-resident entities | E21: SG ITU | F21: Leads: ITU: Ms. Doreen Bogdan-Martin, Secretary-General (sgo@itu.int) UNDP Invited to co-Lead: Haoliang Xu, Acting Administrator (haoliang.xu@undp.org) Members: FAO: Mr. Qu Dongyu, Director General (director-general@fao.org; dongyu.qu@fao.org) ICAO: Mr. Juan Carlos Salazar, Secretary-General (OSGinbox@icao.int; jsalazar@icao.int) ILO: Mr. Gilbert F. Houngbo, Director General (ILODirector-General@ilo.org) UNESCO: Mr Khaled El-Enany, Director-General (dg.secretariat@unesco.org) UNIDO: Gerd Müller, Director General (ODG@unido.org) WHO: Mr. Tedros Adhanom Ghebreyesus, Director General (dgoffice@who.int WMO: Ms Celeste Saulo, Secretary-General (sgomm@wmo.int) ITC: Ms. Pamela Coke-Hamilton, Executive Director and ASG (cokehamilton@intracen.org); front office: Ascension Carrasco Rodriguez (carrasco@intracen.org) UN Women: Sima Bahous, Executive Director. Sima Sami Bahous (sima.bahous@unwomen.org) UNCTAD: Ms. Rebeca Grynspan, Secretary-General (rebeca.grynspan@unctad.org) UNCTAD: Ms. Rebeca Grynspan, Secretary-General (rebeca.grynspan@unctad.org) UNOPS: Mr. Jorge Moreira, Executive Director (jorge.moreiradasilva@unops.org) Regional Commissions: Mr. Claver Gatete, Coordinator of the Regional Commissions, ECA Executive Secretary (cgatete@un.org) Ms. Tatiana Molcean, Executive Secretary of ECE (tatiana.molcean@un.org) Mr. Mourad Wahba, Acting Executive of ESCWA Secretary (mourad.wahba@un.org) UNCTAD: Ms. Rebeca Grynspan, Secretary-General (rebeca.grynspan@unctad.org) | G21: Tomas Lamanauskas, DSG, ITU, dsg@itu.int; Linda Maquire, ASG/Director Bureau for Management Services, UNDP, linda.maguire@undp.org; Beth Crawford, ASG/Director Office of Strategy, Programme and Budget, FAO, beth.crawford@fao.org; Michiel Vreedenburgh, Chief Transformation Officer, ICAO, MVreedenburgh@icao.int; Laura Thompson, Assistant Director General External and Corporate Relations, ILO, thompsonl@ilo.org; Jennifer Linkins, Assistant Director-General for Administration and Management, UNESCO, j.linkins@unesco.org; Cecilia Ugaz Estrada, Deputy to the Director General, UNIDO, C.UGAZESTRADA@unido.org -tbc; Bruce Aylward, Senior Advisor to the Director-General, WHO, aylwardb@who.int; Ko Barrett, DSG, WMO, dsgo@wmo.int; Mondher Mimouni, Director Division of Market Development, ITC, mimouni@intracen.org; Nyaradzayi Gumbonzvanda. Deputy Executive Director Normative Support, System Coordination, Programme Results, UN Women, n.gumbonzvanda@unwomen.org; Rahul Malhotra, -, UNOPS, rahulm@unops.org; UNCTAD Tbc: Regional Commissions: Thilmeeza Hussain, -, ECA, thilmeeza.hussain@un.org; Aboubakri Diaw, -, ECA, diaw2@un.org; Paul John Ladd, -, ECE, paul.ladd@un.org; Maisaa Youssef, -, ESCWA, youssef8@un.org; Riwa Nasreddine, -, ESCWA, nasreddine@un.org; Support/Advisor: Jens Christian Wandel, SA Reform, jens.wandel@un.org | H21: ITU;UNDP;FAO;ICAO;ILO;UNESCO;UNIDO;WHO;WMO;ITC;UN Women;UNOPS;ECA;ECE;ESCWA;UNCTAD;SA Reform | I21: Concept endorsed (legal/financial assessment, catalogue design, and demand protocol and arrangements) | J21: 46080 | K21: EOD fully operational system-wide: expertise catalogue launched, protocols institutionalized, proven replacement of duplicative capacities | L21: 46375 | M21: Attention to timeline | N21: Review final deadline if intention is to demonstrate results from implementation before end 2026
A22: 8 | B22: WP8: Expertise-on-demand mechanism | C22: 54 | D22: Consolidate expertise across all pillars at the regional level as an extension of the expertise-on-demand mechanism outlined in the sustainable development pillar | E22: SG ITU | F22: Leads: ITU: Ms. Doreen Bogdan-Martin, Secretary-General (sgo@itu.int) UNDP Invited to co-Lead: Haoliang Xu, Acting Administrator (haoliang.xu@undp.org) Members: FAO: Mr. Qu Dongyu, Director General (director-general@fao.org; dongyu.qu@fao.org) ICAO: Mr. Juan Carlos Salazar, Secretary-General (OSGinbox@icao.int; jsalazar@icao.int) ILO: Mr. Gilbert F. Houngbo, Director General (ILODirector-General@ilo.org) UNESCO: Mr Khaled El-Enany, Director-General (dg.secretariat@unesco.org) UNIDO: Gerd Müller, Director General (ODG@unido.org) WHO: Mr. Tedros Adhanom Ghebreyesus, Director General (dgoffice@who.int) WMO: Ms Celeste Saulo, Secretary-General (sgomm@wmo.int) ITC: Ms. Pamela Coke-Hamilton, Executive Director and ASG (cokehamilton@intracen.org); front office: Ascension Carrasco Rodriguez (carrasco@intracen.org) UN Women: Sima Bahous, Executive Director. Sima Sami Bahous (sima.bahous@unwomen.org) UNCTAD: Ms. Rebeca Grynspan, Secretary-General (rebeca.grynspan@unctad.org) UNOPS: Mr. Jorge Moreira, Executive Director (jorge.moreiradasilva@unops.org) Regional Commissions: Mr. Claver Gatete, Coordinator of the Regional Commissions, ECA Executive Secretary (cgatete@un.org) Ms. Tatiana Molcean, Executive Secretary of ECE (tatiana.molcean@un.org) Mr. Mourad Wahba, Acting Executive of ESCWA Secretary (mourad.wahba@un.org) | G22: Tomas Lamanauskas, DSG, ITU, dsg@itu.int; Linda Maquire, ASG/Director Bureau for Management Services, UNDP, linda.maguire@undp.org; Beth Crawford, ASG/Director Office of Strategy, Programme and Budget, FAO, beth.crawford@fao.org; Michiel Vreedenburgh, Chief Transformation Officer, ICAO, MVreedenburgh@icao.int; Laura Thompson, Assistant Director General External and Corporate Relations, ILO, thompsonl@ilo.org; Jennifer Linkins, Assistant Director-General for Administration and Management, UNESCO, j.linkins@unesco.org; Cecilia Ugaz Estrada, Deputy to the Director General, UNIDO, C.UGAZESTRADA@unido.org -tbc; Bruce Aylward, Senior Advisor to the Director-General, WHO, aylwardb@who.int; Ko Barrett, DSG, WMO, dsgo@wmo.int; Mondher Mimouni, Director Division of Market Development, ITC, mimouni@intracen.org; Nyaradzayi Gumbonzvanda. Deputy Executive Director Normative Support, System Coordination, Programme Results, UN Women, n.gumbonzvanda@unwomen.org; Rahul Malhotra, -, UNOPS, rahulm@unops.org; UNCTAD Tbc: Regional Commissions: Thilmeeza Hussain, -, ECA, thilmeeza.hussain@un.org; Aboubakri Diaw, -, ECA, diaw2@un.org; Paul John Ladd, -, ECE, paul.ladd@un.org; Maisaa Youssef, -, ESCWA, youssef8@un.org; Riwa Nasreddine, -, ESCWA, nasreddine@un.org; Support/Advisor: Jens Christian Wandel, SA Reform, jens.wandel@un.org | H22: ITU;UNDP;FAO;ICAO;ILO;UNESCO;UNIDO;WHO;WMO;ITC;UN Women;UNOPS;ECA;ECE;ESCWA;UNCTAD;SA Reform | I22: Concept endorsed (legal/financial assessment, catalogue design, and demand protocol and arrangements) | J22: 46080 | K22: EOD fully operational system-wide: expertise catalogue launched, protocols institutionalized, proven replacement of duplicative capacities | L22: 46375 | M22: Attention to timeline | N22: Review final deadline if intention is to demonstrate results from implementation before end 2026
A23: 9 | B23: WP9: Human rights group | C23: 42 | D23: Establish a Human Rights Group comprising entities from across the UN system, led by the High Commissioner for Human Rights | E23: HC OHCHR | F23: ASG DCO Oscar Fernandez Taranco, fernandez-taranco@un.org USG DPPA Rosemary Di Carlo, rosemary.dicarlo@un.org USG OCHA Tom Fletcher, fletcher@un.org USG OLA Elinor Hammarskjold, hammarskjold@un.org USG UNAIDS Winifred Byanyima, byanyimaw@unaids.org USG UNEP, inger.andersen@un.org ASG UNDP Haoliang Xu, haoliang.xu@undp.org USG UNFPA Diene Keita, keita@unfpa.org USG UNHCR Filippo Grandi, grandi@unhcr.org ED UNICEF Catherine Russell, crussell@unicef.org ED Sima Sami Bahous, sima.bahous@unwomen.org ED UNESCO, Khaled El-Enany | G23: ASG Brands Kehris, ilze.brandskehris@un.org Karin Lucke , karin.lucke@un.org Kevin Turner, kevin.turner@un.org Dominique Bush, bushd@un.org | I23: Concept adopted | J23: 46052 | K23: Human Rights Group established | L23: 46111 | M23: Finalized
A24: 10 | B24: WP10: Senior management coordination forums | C24: 43 | D24: Review top management fora to ease the coordination burden for senior leaders and ensure coherent action across pillar, incl. CEB, IASC, UNSDG, EC | E24: USG Policy | F24: Guy Ryder, USG for Policy, guy.ryder@un.org | G24: Melanie Ramjoue, Senior Programme Officer, EOSG, ramjoue@un.org | H24: EOSG (USG Policy) | I24: Coordination fora mapped and baseline survey analytics finalized | J24: 46021 | K24: Proposal for streamlining of fora for implementation finalized (where necessary for Member States endorsement) | L24: 46080 | M24: Finalized
A25: 10 | B25: WP10: Senior management coordination forums | C25: 44 | D25: Consider proposals to unify administrative backend support and streamline duplicative agendas without affecting core substantive competencies | E25: USG Policy | F25: Guy Ryder, USG for Policy, guy.ryder@un.org | G25: Melanie Ramjoue, Senior Programme Officer, EOSG, ramjoue@un.org | H25: EOSG (USG Policy) | I25: Coordination forum backend support mapped and baseline analytics finalized | J25: 46052 | K25: Proposal for streamlining of fora for implementation finalized (where necessary for Member States endorsement) | L25: 46080 | M25: Finalized
A26: 10 | B26: WP10: Senior management coordination forums | C26: 46 | D26: Bring together all Headquarters coordination on country-specific, cross-pillar approaches to crisis prevention and centre capacities around the Regional Monthly Review platform | E26: USG Policy | F26: Guy Ryder, USG for Policy, guy.ryder@un.org | G26: Melanie Ramjoue, Senior Programme Officer, EOSG, ramjoue@un.org | H26: EOSG (USG Policy) | I26: Coordination fora mapped and baseline survey analytics finalized | J26: 46021 | K26: Interagency task forces and working groups streamlined around Regional Monthly Review | L26: 46111 | M26: Finalized
A27: 10 | B27: WP10: Senior management coordination forums | C27: 47 | D27: Review existing interagency task forces and working groups | E27: USG Policy | F27: Guy Ryder, USG for Policy, guy.ryder@un.org | G27: Melanie Ramjoue, Senior Programme Officer, EOSG, ramjoue@un.org | H27: EOSG (USG Policy) | I27: Coordination fora mapped and baseline survey analytics finalized | J27: 46021 | K27: Interagency task forces and working groups streamlined around Regional Monthly Review | L27: 46111 | M27: Finalized
A28: 11 | B28: WP11: Special envoy review | C28: 45 | D28: Review and make proposals to Member States regarding SG’s some 30 special envoys, representatives, coordinators and advisers, both thematic and geographic | E28: USG Policy | F28: Guy Ryder, USG for Policy, guy.ryder@un.org | G28: Melanie Ramjoue, Senior Programme Officer, EOSG, ramjoue@un.org | H28: EOSG (USG Policy) | I28: All special envoys mapped | J28: 45995 | K28: Any changes in Special Envoy roster submitted for Member States decision, as required (e.g., in 2027 programme budget) | L28: 46080 | M28: Finalized
A29: 12 | B29: WP12: Regional integrated platforms | C29: 48 | D29: Establish lean Regional Integrated Platforms to unite regional leaders across all pillars around joint plans, strategies, crisis response and resource mobilization for cross-cutting issues | E29: ASG DCO;DSG | F29: Amina J. Mohammed, DSG, Amina.mohammed@un.org; Izumi Nakamitsu, USG ODA, nakamitsu@un.org; Oscar Fernandez Taranco, ASG DCO, fernandez-taranco@un.org | G29: Jean Philippe Bernardini, Senior Political Affairs Officer, EOSG, bernardini@un.org | H29: EOSG (ODSG);ODA;DCO | I29: System-wide working group convened and draft outline on Regional Reset to be shared with the Secretary-General for guidance, reflecting cross-pillar dimensions | J29: 46029 | K29: Aspects of the regional reset – including RIPs – under Secretary-General prerogative implemented and decisions taken by Member States (Report May 2026 - TBC, depend on UN80 next reporting cycle) | L29: 46263 | M29: Finalized
A30: 12 | B30: WP12: Regional integrated platforms | C30: 50 | D30: Harmonize how UN system entities organize their regional work | E30: ASG DCO;DSG | F30: Amina J. Mohammed, DSG, Amina.mohammed@un.org; Izumi Nakamitsu, USG ODA, nakamitsu@un.org; Oscar Fernandez Taranco, ASG DCO, fernandez-taranco@un.org | G30: Jean Philippe Bernardini, Senior Political Affairs Officer, EOSG, bernardini@un.org | H30: EOSG (ODSG);ODA;DCO | I30: System-wide working group convened and draft outline on Regional Reset to be shared with the Secretary-General for guidance, reflecting cross-pillar dimensions | J30: 46029 | K30: Aspects of the regional reset – including RIPs – under Secretary-General prerogative implemented and decisions taken by Member States (Report May 2026 - TBC, depend on UN80 next reporting cycle) | L30: 46263 | M30: Finalized
A31: 13 | B31: WP13: Shared platform initiative | C31: 19 | D31: Initiate a practical Shared Platform Initiative between DSG and ERC | E31: USG OCHA;DSG | F31: Amina Mohammed, DSG, amina.mohammed@un.org; Tom Fletcher, ERC and USG OCHA, fletcher@un.org | G31: Garry Conille, Special Adviser, DCO, gconille@unicef.org; Edem Wosornu, Director Crisis Response Division, OCHA, wosornu@un.org; Jean Philippe Bernardini, Senior Political Affairs Officer, EOSG, Bernardini@un.org | H31: EOSG (ODSG);OCHA | I31: Action plan for the Shared Platform Initiative with specific timelines for immediate implementation and progress report to the Secretary-General summarizing next steps finalized | J31: 46052 | K31: All initiatives rolled out and implementation finalized, as country contexts required | L31: 46233 | M31: Finalized
A32: 13 | B32: WP13: Shared platform initiative | C32: 57 | D32: Prepare a proposal to ensure that RC/HCs and planning teams simplify Development Cooperation Frameworks, Humanitarian Response Plans, Peacebuilding Strategies and associated needs analyses for relevant settings | E32: USG OCHA;DSG | F32: Amina Mohammed, DSG, amina.mohammed@un.org; Tom Fletcher, ERC and USG OCHA, fletcher@un.org | G32: Garry Conille, Special Adviser, DCO, gconille@unicef.org; Edem Wosornu, Director Crisis Response Division, OCHA, wosornu@un.org; Jean Philippe Bernardini, Senior Political Affairs Officer, EOSG, Bernardini@un.org | H32: EOSG (ODSG);OCHA | I32: Draft of the proposal for simplifying country-level planning process where necessary finalized (ensuring complementarity between the planning frameworks); conducted with PBSO | J32: 46052 | K32: Simplified planning process and associated needs analysis system-wide rolled out | L32: 46233 | M32: Confirmation needed | N32: Review membership: PBSO
A33: 14 | B33: WP14: Unified services roadmap | C33: 63 | D33: Prepare a Unified Services Roadmap, based on existing reform commitments and two models: some services will be provided by consolidated entities, and others through marketplaces of providers. | E33: Chair HLCM;ED WFP;Co-Chairs BIG | F33: Catherine Pollard, HLCM Chair, ; HLCM Vice-Chair; BIG-Co Chairs | G33: Remo Lalli remo.lalli@un.org Silvan Scheiwiller scheiwiller@un.org Federico Calciolari federico.calciolari@un.org Larai Musa larai.musa@un.org Peride Blind blind@un.org Antoine Sfeir sfeira@unhcr.org | I33: Integration of HLCM’s Far-Reaching Efficiency Initiatives (FREIs) and BIG’s Global Shared Services (GSS) agenda into one single unified service roadmap outline. | J33: 46052 | K33: Release of the outcome report on the Unified Services Roadmap, outlining progress, results and suggested next steps | L33: 46340 | M33: Attention to timeline | N33: Review final deadline to ensure checkpoint on impact of action before end of December 2026
A34: 14 | B34: WP14: Unified services roadmap | C34: 65 | D34: Conduct assessment for integration of basic information and communication technology services, as well as payroll, human resources, finance, and enterprise resource planning (ERP) systems | E34: Chair HLCM;ED WFP;Co-Chairs BIG | G34: Remo Lalli remo.lalli@un.org Silvan Scheiwiller scheiwiller@un.org Federico Calciolari federico.calciolari@un.org Larai Musa larai.musa@un.org Peride Blind blind@un.org | I34: Release of the assessment framework that will be used to guide decision making on items outlined in A32. | J34: 46053 | K34: Final release of the outcomes of the assessment (cost, risk, complexity, ...) | L34: 46294 | M34: Finalized
A35: 14 | B35: WP14: Unified services roadmap | C35: 66 | D35: Accelerate the move toward a unified service backbone at country level; eliminate costly duplication on the ground | E35: Chair HLCM;ED WFP;Co-Chairs BIG | G35: Larai Musa larai.musa@un.org Peride Blind blind@un.org | I35: Commence the Self Starter Common Back Office/ locally shared service trainings towards accelerated unified common service backbone in countries; Launch survey to identify high impact target countries for supported roll out; Launch an Interagency task forc | J35: 46053 | K35: Release integrated suite of services for common back office, which include knowledge management products and work towards achieving consistent comparative result reporting; Expand the reach of service offerings from BIG to the whole network at country lev | L35: 46340 | M35: Attention to timeline | N35: Review final deadline to ensure checkpoint on impact of action before end of December 2026
A36: 14 | B36: WP14: Unified services roadmap | C36: 67 | D36: Harmonize most indirect and programme support costs | E36: Chair HLCM;ED WFP;Co-Chairs BIG | G36: Larai Musa larai.musa@un.org Peride Blind blind@un.org | I36: Release of the CBO Tracking Tool and CBO Self Starter Reporting methodology for new CBOs; Promote strengthened reporting practices using tracking tool across UN system | J36: 46053 | K36: Identify potential service offerings funded by programme budget that can utilize and build on efficiency measures developed for administrative expenditure; For launched CBOs, release the preliminary efficiency gains per scaled common services in new | L36: 46340 | M36: Attention to timeline | N36: Review final deadline to ensure checkpoint on impact of action before end of December 2026
A37: 15 | B37: WP15: Technology | C37: 61 | D37: Prepare a proposal to consolidate the fragmented landscape of basic cloud services, network infrastructures, office software and systems under realigned common providers that can serve the entire UN system, building on lessons from the International Computing Centre | E37: SG ITU;USG Policy;Chair DTN | F37: SA Reform, DG WIPO, Administrator UNDP, DG WHO, Vice-Chair HLCM | G37: CDO UNDP (Robert Opp, robert.opp@undp.org), CIO ITU (khuloud.odeh@itu.int), CIO FAO (dejan.jakovljevic@fao.org), CITO UN (bmariano@un.org), SPMU EOSG (jauer@un.org) | H37: EOSG (USG Policy) | I37: Systemwide baseline completed: comprehensive mapping of existing ICT capacities, spending, contracts, staffing, shared-service providers, as well as ongoing consolidation initiatives and additional potential | J37: 46068 | K37: ICT Consolidation Framework Proposal endorsed by CEB: unified vendor agreements, harmonized core ICT capacities, and operational shared-service delivery model for UN system entities | L37: 46156 | M37: Finalized
A38: 15 | B38: WP15: Technology | C38: 62 | D38: Develop baseline of the current innovation landscape and a proposal for a Technology Accelerator Platform (TAP) to the Chief Executives Board | E38: USG Policy;Chair DTN;SG ITU | F38: SA Reform, DG WIPO, Administrator UNDP, DG WHO, Vice-Chair HLCM | G38: CDO UNDP (Robert Opp, robert.opp@undp.org), CIO ITU (khuloud.odeh@itu.int), CIO FAO (dejan.jakovljevic@fao.org), CITO UN (bmariano@un.org), SPMU EOSG (jauer@un.org) | H38: EOSG (USG Policy) | I38: Portfolio of high-impact technology acceleration use cases proposed to the Steering Committee, based on priority challenges identified in UN 2.0 and UN80 reports, with tailored delivery setups identified for each use case | J38: 46061 | K38: At least three priority accelerator use cases in deployment systemwide, with clear KPI improvements (e.g., documented efficiency gains and user satisfaction improvements) | L38: 46325 | M38: Finalized
A39: 16 | B39: WP16: Data | C39: 73 | D39: Prepare proposals for the Chief Executives Board at the end of October 2025 on how to guide phased implementation of Data Commons | E39: USG Policy;USG DESA;ED UNICEF | H39: EOSG (USG Policy) | M39: No submission
A40: 16 | B40: WP16: Data | C40: 74 | D40: Scale pooled funding approaches for data to support the Data Commons | E40: USG Policy;USG DESA;ED UNICEF | H40: EOSG (USG Policy) | M40: No submission
A41: 16 | B41: WP16: Data | C41: 75 | D41: Pool the know-how of data analysts, engineers, and scientists to support the UN system, the new hubs, humanitarian clusters, and country teams alike | E41: USG Policy;USG DESA;ED UNICEF | H41: EOSG (USG Policy) | M41: No submission
A42: 17 | B42: WP17: Training and research | C42: 68 | D42: Merge UN Staff System College (UNSSC) into the UN Institute for Training and Research (UNITAR) | E42: ED UNITAR;Rector UNU | F42: Michelle Gyles-McDonnough, Executive Director, UNITAR; GYLES-MCDONNOUGH@unitar.org | G42: UN System Staff College Miguel Panadero, Acting Director; m.panadero@unssc.org Silke Weinlich, Deputy Director; s.weinlich@unssc.org UNITAR Marina Dinca Vasilescu, Director, Operations; Marina.VASILESCU@unitar.org Evariste Karambizi, Director, Division for Peace; Evariste.KARAMBIZI@unitar.org UN Women Nyaradzayi Gumbonzvanda, Deputy Executive Director, n.gumbonzvanda@unwomen.org; Papa Seck, Chief Research and Data; papa.seck@unwomen.org ITU Doreen Bogdan-Martin, Secretary-Generaldoreen.bogdan@itu.int Regina Valiullina; Regina.Valiullina@itu.int); ITC ILO Andreas Klemmer, Director of Training, International Training Centre of the International Labour Organization (ITC ILO); A.Klemmer@itcilo.org Development Coordination Office Oscar Fernández-Taranco, Assistant Secretary-General for Development Coordination; fernandez-taranco@un.org Helena Fraser, Director, Policy and Programming Branch; fraser@un.org Department of Operational Support Adrian Hills, Chief, Capacity Development and Operational Training Service; hillsa@un.org Mohammad Jeram, Chief of Operational Training Section, CDOTS; jeram@un.org Paola Matarazzo, Chief, Business Process & Systems Support Section, CDOTS; matarazzo@un.org | I42: Merger roadmap agreed by UNITAR and UNSSC, incl. needs assessment, scope, methodology, and joint plan for functional/financial mapping. Consultations launched | J42: 46052 | K42: Member states decide on the proposed merger based on the submitted transition plan. | L42: 46356 | M42: Attention to timeline | N42: Review final milestone date, e.g., align with inter-governmental calendar
A43: 17 | B43: WP17: Training and research | C43: 69 | D43: Integrate UN Research Institute for Social Development (UNRISD) into the United Nations University (UNU) | E43: ED UNITAR;Rector UNU | F43: Tshilidzi Marwala, Rector UNU (USG), rector@unu.edu | G43: Xiaomeng Shen Vice Rector Europe shen@ehs.unu.edu Sabine Becker-Thierry Director UNU Paris sabine.becker@unu.edu | I43: UNU Council would have reviewed and endorsed the UN80 report’s recommendations to integrate UNRISD into UNU. | J43: 45995 | K43: A public announcement of UNRISD’s integration into UNU was made, including forward looking timing. | L43: 46386 | M43: Attention to timeline | N43: Review final deadline to ensure checkpoint on impact of action before end of December 2026
A44: 17 | B44: WP17: Training and research | C44: 72 | D44: Establish a Joint UN System Coordination Mechanism co-led by the UNU Rector and UNITAR Executive Director. | E44: ED UNITAR;Rector UNU | F44: Tshilidzi Marwala, UNU Rector, rector@unu.edu; Michelle Gyles-McDonnough, UNITAR Executive Director, gyles-mcdonnough@unitar.org | G44: Jonas Haertle, Chief Office of the Executive Director UNITAR, jonas.haertle@unitar.org; Mihoko Kumamoto, Director Division for Prosperity UNITAR, mihoko.kumamoto@unitar.org; Sabine Becker-Thierry, Director UNU Paris, sabine.becker@unu.edu; Francesco Foghetti, UNU Senior Legal Officer, foghetti@unu.edu | I44: Plan in place setting out scope and key considerations of the knowledge mapping exercise and entities to be engaged | J44: 46052 | K44: Blueprint for Joint UN Coordination Mechanism endorsed by SG. | L44: 46356 | M44: Confirmation needed | N44: Consider being more ambitious, e.g., up to piloting mechanism, e.g. next CEB in May 2026
A45: 18 | B45: WP18: Funding mechanisms | C45: 76 | D45: Launch a pooled funding review, including a review of administrative agent, secretariat, governance and support cost models, as well as partnership arrangements, to ensure pooled funding is consistently cheaper and more attractive than fragmented approaches | E45: SA Reform;ASG DCO | F45: Jens Wandel, USG, EOSG Oscar Fernandez-Taranco, ASG, DCO Elizabeth Spehar, ASG, PBSO Alain Noudehou, Director, MPTFO, UNDP Susan Brown, ASG, Director of the Bureau for External Relations and Advocacy, UNDP Lisa Dougthen, Director,Humanitarian Financing and Resource Mobilization, OCHA | G45: Chris Stokes, Senior Programme Managers Fiona Bayat-Renoux, Deputy Chief of Staff, UNDP Klaus SimioniPederson D1, Chief of our Resource Mobilization Branch, UNFPA Alice Sequi, Chief of the Pooled Fund Branch, OCHA - | I45: Analysis, mapping and categorization of all pooled funding and data. | J45: 46051 | K45: All actions taken to respond to recommendations, with update published | L45: 46202 | M45: Finalized
A46: 18 | B46: WP18: Funding mechanisms | C46: 77 | D46: Rationalize the portfolio of pooled funds, with particular focus on the Central Emergency Response Fund, the Peacebuilding Fund, the Joint SDG Fund, and the Country-Based Pooled Funds | E46: SA Reform;ASG DCO | F46: Jens Wandel, USG, EOSG Oscar Fernandez-Taranco, ASG, DCO Elizabeth Spehar, ASG, PBSO Alain Noudehou, Director, MPTFO, UNDP Susan Brown, ASG, Director of the Bureau for External Relations and Advocacy, UNDP Lisa Dougthen, Director,Humanitarian Financing and Resource Mobilization, OCHA | G46: Chris Stokes, Senior Programme Managers Fiona Bayat-Renoux, Deputy Chief of Staff, UNDP Klaus SimioniPederson D1, Chief of our Resource Mobilization Branch, UNFPA Alice Sequi, Chief of the Pooled Fund Branch, OCHA - | I46: Analysis, mapping and categorization of all pooled funding and data. | J46: 46051 | K46: All actions taken to respond to proposals, as agreed by SG and relevant governing bodies | L46: 46370 | M46: Attention to timeline | N46: Review final deadline to ensure checkpoint on impact of action before end of December 2026
A47: 18 | B47: WP18: Funding mechanisms | C47: 78 | D47: Prepare a proposal on how core funding can become consistently cheaper and more attractive than fragmented approaches, including options to strengthen visibility for core contributors and partners | E47: SA Reform;ASG DCO | F47: Jens Wandel, USG, EOSG Oscar Fernandez-Taranco, ASG, DCO Elizabeth Spehar, ASG, PBSO Alain Noudehou, Director, MPTFO, UNDP Susan Brown, ASG, Director of the Bureau for External Relations and Advocacy, UNDP Lisa Dougthen, Director,Humanitarian Financing and Resource Mobilization, OCHA | G47: Chris Stokes, Senior Programme Managers Fiona Bayat-Renoux, Deputy Chief of Staff, UNDP Klaus SimioniPederson D1, Chief of our Resource Mobilization Branch, UNFPA Alice Sequi, Chief of the Pooled Fund Branch, OCHA | I47: Draft paper on strengthening the case for core funding finalized for discussion with stakeholders. | J47: 46051 | K47: All entities with voluntary core funding to report on steps being taken to respond to the proposal | L47: 46202 | M47: Finalized
A48: 18 | B48: WP18: Funding mechanisms | C48: 91 | D48: Map existing Funding Compact review mechanisms and integrate discussion into a system-wide management mechanism at least once per year | E48: SA Reform;ASG DCO | F48: Jens Wandel, USG, EOSG Oscar Fernandez-Taranco, ASG, DCO Elizabeth Spehar, ASG, PBSO Alain Noudehou, Director, MPTFO, UNDP Susan Brown, ASG, Director of the Bureau for External Relations and Advocacy, UNDP Lisa Dougthen, Director,Humanitarian Financing and Resource Mobilization, OCHA | G48: Chris Stokes, Senior Programme Managers Fiona Bayat-Renoux, Deputy Chief of Staff, UNDP Klaus SimioniPederson D1, Chief of our Resource Mobilization Branch, UNFPA Alice Sequi, Chief of the Pooled Fund Branch, OCHA | I48: Mapping of Funding Compact dialogues at country level and in governing bodies complete | J48: 46051 | K48: Final mapping and recommendations for integrating discussions to be complete. | L48: 46111 | M48: Finalized
A49: 19 | B49: WP19: Mandate creation support | C49: 80 | D49: Prepare an action plan to improve staff support to Member State during mandate creation, based on mapping of existing capacities per mandating bodies and Member State priorities | E49: USG Policy;USG DGACM | F49: Guy Ryder, USG for Policy, guy.ryder@un.org Movses Abelian, USG DGACM, abelian@un.org | G49: Melanie Ramjoue, Senior Programme Officer, ramjoue@un.org Wannes Lint, Intergovernmental Affairs Officer, lint@un.org | H49: EOSG (USG Policy) | I49: Analysis of results of member states survey on mandate creation support finalized | J49: 46052 | K49: Proposals for enhanced mandate creation support submitted to MS for decision (e.g., in next programme budget) | L49: 46080 | M49: Finalized
A50: 19 | B50: WP19: Mandate creation support | C50: 81 | D50: Prepare an action plan (as part of item 80) to strengthen support by UN entities to coordinate and promote greater visibility across mandating bodies | E50: USG Policy;USG DGACM | F50: Guy Ryder, USG for Policy, guy.ryder@un.org Movses Abelian, USG DGACM, abelian@un.org | G50: Melanie Ramjoue, Senior Programme Officer, ramjoue@un.org Wannes Lint, Intergovernmental Affairs Officer, lint@un.org | H50: EOSG (USG Policy) | I50: Survey to assess available support of mandate creation system-wide launched and distributed to different UN system secretariats | J50: 46052 | K50: Joint programme launched before 81st GA session to enable a coordinated platform aggregating mandate creation support across intergovernmental bodies | L50: 46264 | M50: Finalized
A51: 19 | B51: WP19: Mandate creation support | C51: 83 | D51: Prepare an action plan to complement the estimates of programme budget implications (PBI) for new mandates with additional info related to activities across the UN System | E51: USG Policy;USG DGACM | F51: Guy Ryder, USG for Policy, guy.ryder@un.org Movses Abelian, USG DGACM, abelian@un.org | G51: Melanie Ramjoue, Senior Programme Officer, ramjoue@un.org Wannes Lint, Intergovernmental Affairs Officer, lint@un.org OPPFB - TBC | H51: EOSG (USG Policy) | I51: Initial concept note finalized between EOSG, DGACM, and OPPFB | J51: 46052 | K51: Proposals for enhanced mandate creation support submitted to MS for decision (e.g., in the next programme budget) | L51: 46080 | M51: Finalized
A52: 20 | B52: WP20: UN budget / programme management | C52: 88 | D52: Develop action plan to strengthen internal strategic oversight of the UN system division of labour at all levels to ensure effective, efficient programmatic and operational support, building on existing reforms | E52: CDC | M52: No submission
A53: 20 | B53: WP20: UN budget / programme management | C53: 89 | D53: As part of the standard budget guidance process, develop an action plan to ensure UN entities systematically review mandate citations in their programmes, incl. based on comparative advantage | E53: CDC | M53: No submission
A54: 20 | B54: WP20: UN budget / programme management | C54: 92 | D54: Prepare proposals by the SG as per Rule 105.6 of ST/SGB/2018/3 for the “GA, with justification, a list of outputs from the previous period which, in the judgement of the SG, can be discontinued” | E54: CDC | M54: No submission
A55: 21 | B55: WP21: System-wide results management | C55: 93 | D55: Develop an action plan to strengthen and harmonize management for results mechanisms across the UN system, including how results are measured and communicated | E55: SA Reform | F55: Jens Wandel, SA, EOSG Fatoumata Ndiay, USG, OIOS Doreen Bogdan-Martin , USG, ITU Francine Pickup, Deputy Director of the Bureau for Policy and Programme | G55: Catalin Marinescu, Head of Strategy and Planning Division, ITU Clarice Wilson, Director of the UNDP Corporate Performance Unit Piyoo Kochar, Specialist, BTAD, UN UN Strategic Planning Network (UNSPN) and Finance and Budget Network under HLCM. | I55: Draft Concept Paper establishing the intellectual foundation for the proposed Action Plan including communication of systemwide results | J55: 46052 | K55: Final Action Plan outlining an implementable system-wide pathway for a results-based management mechanism / communication standards | L55: 46172 | M55: Finalized
A56: 22 | B56: WP22: Prevention, peacebuilding, peace support | C56: 1 | D56: Establish a unified Peacebuilding and Peace Support Office (one ASG to be abolished) | E56: USG DPPA;USG DPO | F56: USGs DiCarlo and Lacroix | G56: ASG Spehar, director Awa Dabo, OROLSI colleagues, chiefs OUSG Markus Bouillon and Marco Bianchini | I56: GA endorses proposed establishment of unified PBPSO and abolition of one ASG post | J56: 46022 | K56: GA endorses proposed establishment of unified PBPSO and abolition of one ASG post | L56: 46022 | M56: Finalized
A57: 22 | B57: WP22: Prevention, peacebuilding, peace support | C57: 2 | D57: Establish a single centre of excellence on Women, Peace and Security, bringing together the DPPA and DPO gender units | E57: USG DPPA;USG DPO | F57: USGs DiCarlo and Lacroix | G57: Directors PMD and DPET, Asif Khan and David Haeri, and chiefs OUSG Markus Bouillon and Marco Bianchini | I57: GA endorses proposed merger of the separate gender units in DPPA and DPO. Merged gender unit takes up its work, reporting to both USGs | J57: 46022 | K57: GA endorses proposed merger of the separate gender units in DPPA and DPO. Merged gender unit takes up its work, reporting to both USGs | L57: 46022 | M57: Finalized
A58: 22 | B58: WP22: Prevention, peacebuilding, peace support | C58: 3 | D58: Establish mechanisms – including joint strategies and programmes – to link cross-cutting functions (incl. expertise in data analytics, digital and artificial intelligence) | E58: USG DPPA;USG DPO | F58: USGs DiCarlo and Lacroix | G58: DPET and PMD directors David Haeri and Asif Khan, chiefs OUSG Markus Bouillon and Marco Bianchini | I58: Discussions and clarification on mechanisms, including joint strategies and programmes, to link cross-cutting functions | J58: 46111 | K58: Clear division of labour and joint mechanisms | L58: 46386 | M58: Attention to timeline | N58: Review final deadline to ensure checkpoint on impact of action before end of December 2026
A59: 22 | B59: WP22: Prevention, peacebuilding, peace support | C59: 6 | D59: Consolidate two Assistant Secretary-General posts for the Americas, Europe, Asia-Pacific, Middle East into one | E59: USG DPPA;USG DPO | F59: USGs DiCarlo and Lacroix | G59: Chiefs OUSG Marco Bianchini and Markus Bouillon, ASG Khiari | I59: GA endorses proposed consolidation of two ASG posts and offices | J59: 46022 | K59: GA endorses proposed consolidation of two ASG posts and offices | L59: 46022 | M59: Finalized
A60: 22 | B60: WP22: Prevention, peacebuilding, peace support | C60: 7 | D60: Combine the Western and Northern Africa divisions | E60: USG DPPA;USG DPO | F60: USGs DiCarlo and Lacroix | G60: ASG Pobee, chiefs OUSG Marco Bianchini and Markus Bouillon | I60: GA endorses proposed combination of WAD and NAD | J60: 46022 | K60: GA endorses proposed combination of WAD and NAD | L60: 46022 | M60: Finalized
A61: 22 | B61: WP22: Prevention, peacebuilding, peace support | C61: 8 | D61: Integrate the UN Mission to Support the Hudaydah Agreement into the Office of the Special Envoy for Yemen | E61: USG DPPA;USG DPO | F61: USG DiCarlo, ASG Khiari | G61: chief OUSG Markus Bouillon, OASG MEAP | I61: Security Council decision on integration | J61: 46052 | K61: Revised budget for and implementation of integration | L61: 46386 | M61: Attention to timeline | N61: Review final deadline to ensure checkpoint on impact of action before end of December 2026
A62: 22 | B62: WP22: Prevention, peacebuilding, peace support | C62: 9 | D62: Streamline and align the UN Office for Central Africa (UNOCA) and the Office of the Special Envoy for the Great Lakes | E62: USG DPPA;USG DPO | F62: USG DiCarlo and ASG Pobee | G62: Chief OUSG Markus Bouillon, OASG Africa | I62: Relevant Security Council consultations/decisions | J62: 46111 | K62: Revised budget for and implementation of integration | L62: 46386 | M62: Attention to timeline | N62: Review final deadline to ensure checkpoint on impact of action before end of December 2026
A63: 22 | B63: WP22: Prevention, peacebuilding, peace support | C63: 10 | D63: Streamline and align the Office of the Special Adviser for Cyprus with the UN Peacekeeping Force in Cyprus (UNFICYP) | E63: USG DPPA;USG DPO | F63: USGs DiCarlo and Lacroix | G63: Chiefs OUSG DPPA and DPO, Markus Bouillon and Marco Bianchini, director ECAD Kayoko Gotoh | I63: GA endorses revised estimates for OSASG Cyprus | J63: 46022 | K63: Further implementation of strengthened alignment | L63: 46386 | M63: Attention to timeline | N63: Review final deadline to ensure checkpoint on impact of action before end of December 2026
A64: 22 | B64: WP22: Prevention, peacebuilding, peace support | C64: 11 | D64: Rationalize the Office of the United Nations Representative to the Geneva International Discussions (UNRGID) | E64: USG DPPA;USG DPO | F64: USG DiCarlo | G64: Chief OUSG Markus Bouillon, OASG ECAA, director ECAD Kayoko Gotoh | I64: GA endorses revised estimates for UNRGID | J64: 46022 | K64: Full implementation of structural changes | L64: 46386 | M64: Attention to timeline | N64: Review final deadline to ensure checkpoint on impact of action before end of December 2026
A65: 22 | B65: WP22: Prevention, peacebuilding, peace support | C65: 49 | D65: Host regional peace and development advisers in Regional Commissions | E65: USG DPPA;USG DPO | F65: USG DiCarlo | G65: Chief OUSG Markus Bouillon, PMD director/co-chair Joint Programme Asif Khan | I65: Establishing financial and other necessary conditions | J65: 46111 | K65: Hosting of regional PDAs in RECs, financial and other necessary conditions permitting | L65: 46386 | M65: Attention to timeline | N65: Review final deadline to ensure checkpoint on impact of action before end of December 2026
A66: 22 | B66: WP22: Prevention, peacebuilding, peace support | C66: 52 | D66: Begin co-locating special political missions with a regional focus and regional peace and development advisers with Regional Commissions serving as physical hosts (or remote participation) | E66: USG DPPA;USG DPO | F66: USG DiCarlo | G66: Chief OUSG Markus Bouillon | I66: Establishing mandate, budgetary and other necessary measures and challenges | J66: 46111 | K66: Submission of final proposals pertaining to closer collaboration between SPMs and RECs | L66: 46386 | M66: Attention to timeline | N66: Review final deadline to ensure checkpoint on impact of action before end of December 2026
A67: 22 | B67: WP22: Prevention, peacebuilding, peace support | C67: 55 | D67: Align surge capacity for peace and security, rule of law, disarmament, demobilization and reintegration, security sector reform, small arms control, mission transitions, prevention of extremist violence, and counterterrorism to support regional needs. | E67: USG DPPA;USG DPO | F67: USG DiCarlo, ASG Spehar, ODA, OCT | G67: Chief OUSG DPPA Markus Bouillon, PBPSO director Awa Dabo, ODA, OCT | I67: Clarify meaning of this action. | J67: 46111 | K67: Align surge capacities as possible. | L67: 46386 | M67: Confirmation needed | N67: Review ambition and deadline for final milestone
A68: 22 | B68: WP22: Prevention, peacebuilding, peace support | C68: 58 | D68: Integrate peace and development advisory support in all relevant Resident Coordinator Offices to ensure conflict risks are integrated into common country analyses | E68: USG DPPA;USG DPO | F68: USG DiCarlo | G68: Chief OUSG Markus Bouillon, PMD director/co-chair Joint Programme Asif Khan, DCO | I68: Establishing financial and other necessary conditions | J68: 46111 | K68: Provision of PDA support to relevant RCOs, financial and other necessary conditions permitting | L68: 46386 | M68: Confirmation needed | N68: Review ambition and deadline for final milestone
A69: 23 | B69: WP23: Disarmament | C69: 5 | D69: Integrate the UN Institute for Disarmament Research (UNIDIR) into the Office for Disarmament Affairs (ODA) | E69: USG ODA | M69: No submission
A70: 23 | B70: WP23: Disarmament | C70: 53 | D70: Begin co-locating regional disarmament centres, with Regional Commissions serving as physical hosts | E70: USG ODA | M70: No submission
A71: 24 | B71: WP24: Drugs, crime, counterterrorism | C71: 4 | D71: Integrate the UN Interregional Crime and Justice Research Institute (UNICRI) into the UN Office on Drugs and Crime (UNODC) | E71: USG UNODC;USG OCT | F71: John Brandolino; Acting Executive Director, UNODC; john.brandolino@un.org | G71: Candice Welsch; Director for Policy and Public Affairs, UNODC; candice.welsch@un.org | H71: UNODC | I71: Concept note developed | J71: 46141 | K71: ECOSOC resolution adopted | L71: 46233 | M71: Finalized
A72: 24 | B72: WP24: Drugs, crime, counterterrorism | C72: 12 | D72: Reinforce cooperation on counterterrorism and violent extremism, with clearer reporting lines, joint planning, and resource mobilization. | E72: USG UNODC;USG OCT | F72: Mr. Alexandre Zouev, Acting Under-Secretary-General, UNOCT, alexandre.zouev@un.org | G72: Mr. Eihab Omaish, Director for Policy and Coordination, UNOCT, omaish@un.org Mr. Mauro Miedico, Director for Capacity Building, UNOCT, mauro.miedico@un.org | H72: UNOCT | I72: By 31 January UNOCT will have circulated an options paper and a set of key messages on coordination and coherence for the consideration of the Global Counter-Terrorism Coordination Compact Committee | J72: 46052 | K72: By 30 June 2026, the Global Counter-Terrorism Coordination Compact Committee will have taken a decision and collectively committed to specific measures. | L72: 46202 | M72: Finalized
A73: 24 | B73: WP24: Drugs, crime, counterterrorism | C73: 13 | D73: The Director overseeing the UNODC Terrorism Prevention Branch would also report to the Under-Secretary-General for Counter-Terrorism. | E73: USG UNODC;USG OCT | F73: Mr. Alexandre Zouev, Acting Under-Secretary-General, UNOCT, alexandre.zouev@un.org Mr. John Brandolino, Acting Under-Secretary-General, UNODC, john.brandolino@un.org | G73: Mr. Eihab Omaish, Director for Policy and Coordination, UNOCT, omaish@un.org Mr. Mauro Miedico, Director for Capacity Building, UNOCT, mauro.miedico@un.org Ms. Oguljeren Niyazberdiyeva, Chief, Officer of the Under-Secretary-General, UNOCT, niyazberdiyeva@un.org Mr. Mehdi Knani, Chief of Section, Front Office/OUSG, UNOCT, mehdi.knani@un.org Ms. Tamara Anderson, Chief of Section, Policy, Knowledge and Coordination Branch, UNOCT, andersont@un.org Roberto Arbitrio roberto.arbitrio@un.org Kate Fitzpatrick kate.fitzpatrick@un.org Alejandro Matta Maya alejandro.matta@un.org; | H73: UNOCT;UNODC | I73: By 31 January 2026, Action Members (principals) meet at least two times to discuss ideas. | J73: 46052 | K73: By 31 March 2026, the Director overseeing the UNODC Terrorism Prevention Branch would also report to the Under-Secretary-General for Counter-Terrorism. | L73: 46111 | M73: Finalized
A74: 25 | B74: WP25: UNAIDS | C74: 29 | D74: Sunset UNAIDS; mainstreaming capacity and expertise into relevant entities of the UN development system | E74: DSG;ED UNAIDS | F74: Winnie Byanyima, ED UNAIDS, byanyimaw@unaids.org | G74: Mahesh Mahalingam, Chief of Staff, maheshm@unaids.org; Morten Ussing, Director Governance, ussingm@unaids.org; Christine Stegling, ASG Deputy Executive Director, steglingc@unaids.org | H74: UNAIDS | I74: UNAIDS Board agrees process for delivering a final plan for full transformation of UNAIDS that is aligned with UN80; AIDS Strategy adopted. | J74: 46008 | K74: UNAIDS Board approves final transformation plan. | L74: 46365 | M74: Attention to timeline | N74: Consider implementation plan before December 2026
A75: 26 | B75: WP26: Other merger review | C75: 32 | D75: Provide support for further analysis on other potential mergers Member States may wish to explore | E75: SG | M75: No submission
A76: 27 | B76: WP27: Environment | C76: 35 | D76: Undertake a thorough assessment of current arrangements and make proposals on possible structural changes and programme realignments on environmental issues | E76: USG UNEP;ES UNFCCC | F76: UNDP (development) TBC OHCHR (human rights) TBC DPPA/ PBSO (peace & Security) TBC UNCTAD (trade, minerals) (development secretariat) TBC IFAD (specialized agencies) TBC | G76: Ligia Noronha, ASG and Head of the NYO, UNEP, ligia.noronha@un.org; Rafael Peralta, Regional Director for North America, UNEP peralta@un.org; Nicolas Bertrand, Chief of Staff, nicolas.bertrand@un.org; UNEP's Executive Office; Daniele Violetti, Senior Director Programmes Coordination, UNFCCC, dvioletti@unfccc.int; James Grabert, Director Mitigation, UNFCCC, JGrabert@unfccc.int; Joanna MacGregor, Chief Strategy and UN Affairs, UNFCCC, jmacgregor@unfccc.int | I76: Terms of reference of the assessment finalized, including scope, methodology, timeline and specific outcomes | J76: 46052 | K76: Assessment to reinforce environmental science, strengthen coordination on environment, joint knowledge integration hubs & possible strategic alignments completed (date TBC - M. Correa) | L76: 46282 | M76: Finalized
A77: 28 | B77: WP28: Other UN Secretariat development realignments | C77: 30 | D77: Realign macroeconomic analysis capacities across DESA, UNCTAD, and the Regional Commissions to create a unified "single entry point" for Member States, anchored in joint mechanisms | E77: USG DESA;ES ECA;SG UNCTAD | M77: No submission
A78: 28 | B78: WP28: Other UN Secretariat development realignments | C78: 31 | D78: Realign UN Secretariat support for LDCs, LLDCs and SIDS across DESA, UNCTAD and OHRLLS | E78: USG DESA;ES ECA;SG UNCTAD | M78: No submission
A79: 11 | B79: WP11: Special envoy review | C79: 38 | D79: Abolish the Special Coordinator for Development in the Sahel post and its associated office (functions and responsibilities are absorbed and performed by existing entities) | E79: USG Policy | F79: Director, SDU | H79: EOSG (USG Policy) | M79: No submission
A80: 29 | B80: WP29: Mandate registries and tools | C80: 79 | D80: For the UN Secretariat, refine mandates.un.org to serve as sustainable registry; Other entities to build out similar registries for their mandating bodies | E80: USG Policy | F80: Library NY, Global Pulse | H80: EOSG (USG Policy) | M80: No submission
A81: 29 | B81: WP29: Mandate registries and tools | C81: 82 | D81: Develop tools to assist in research for mandate creation | E81: USG Policy | F81: Library NY, Global Pulse | H81: EOSG (USG Policy) | M81: No submission
A82: 30 | B82: WP30: SG reports | C82: 84 | D82: Assess trends in word-limit compliance and develop an action plan for improvements (as part of item 86) | E82: CDC | M82: No submission
A83: 30 | B83: WP30: SG reports | C83: 85 | D83: Assess trends and patterns in report overlap and fragmentation, and develop an action plan for improvement (as part of item 86) | E83: CDC | M83: No submission
A84: 30 | B84: WP30: SG reports | C84: 86 | D84: Constitute a cross-departmental working group to develop an action plan for improvements in reporting format options for different types of information requests | E84: CDC | M84: No submission
A85: 30 | B85: WP30: SG reports | C85: 87 | D85: Display per-report download counts on UN ODS and UN Digital Library pages for each document | E85: CDC | M85: No submission
A86: 31 | B86: WP31: UN Secretariat efficiencies and improvement | C86: 94 | D86: Implement residual actions from Phase I of the Working Group on Efficiencies, as per Rev. estimates for programme budget 2026 and support account for 25/26, not included in or relevant for WP#14 | E86: USG DMSPC;USG DOS | F86: Patrick Carey careyp@un.org | I86: CAP established with initial operating capacity and all Executive Office personnel reporting to DOS. | J86: 46053 | K86: CAP fully operational. | L86: 46234 | M86: Finalized
A87: 31 | B87: WP31: UN Secretariat efficiencies and improvement | C87: 95 | D87: Implement residual actions from Phase II of the Working Group on Efficiencies, not to be included in or relevant for WP#14 | E87: USG DMSPC;USG DOS | F87: Giovanna Ceglie giovanna.ceglie@un.org | I87: Phase II CAPs endorsed. | J87: 46053 | K87: Phase II CAPs approved by General Assembly. | L87: 46387 | M87: Confirmation needed | N87: Consider adjusting final milestone date to earlier potential checkpoint, if possible
A88: 31 | B88: WP31: UN Secretariat efficiencies and improvement | C88: 94 | D88: Implement residual actions from Phase I of the Working Group on Efficiencies, as per Rev. estimates for programme budget 2026 and support account for 25/26, not included in or relevant for WP#14 | E88: USG DMSPC;USG DOS | F88: Patrick Carey careyp@un.org | I88: Core payroll functions for five existing payroll offices consolidated into the proposed Global Payroll Centres. | J88: 46053 | K88: Global Payroll Centre fully operational in New York, Nairobi and Entebbe | L88: 46326 | M88: Finalized
A89: 31 | B89: WP31: UN Secretariat efficiencies and improvement | C89: 95 | D89: Implement residual actions from Phase II of the Working Group on Efficiencies, not to be included in or relevant for WP#14 | E89: USG DMSPC;USG DOS | F89: Cherith A Norman Chalet normanchalet@un.org | I89: Complete analysis of survey on scope of contractual translation services to determine potential management mechanisms and their viability . | J89: 46022 | K89: TBD (subject to outcome of milestone 1) | M89: Confirmation needed | N89: Preliminary final milestone to be added
A90: 31 | B90: WP31: UN Secretariat efficiencies and improvement | C90: 95 | D90: Implement residual actions from Phase II of the Working Group on Efficiencies, not to be included in or relevant for WP#14 | E90: USG DMSPC;USG DOS | F90: Bernardo Mariano Junior bmariano@un.org | I90: Pilot begins of Data Center Consolidation initiative, Pending approval of Phase I of the Secretariat ICT Consolidation and Digital Hubs: establishment of first Digital hub in Valencia. | J90: 46053 | K90: Pilot is concluded, lessons learned exercise completed, Phase I plan created. | L90: 46387 | M90: Confirmation needed | N90: Review ambition and deadline for final milestone
A91: 31 | B91: WP31: UN Secretariat efficiencies and improvement | C91: 95 | D91: Implement residual actions from Phase II of the Working Group on Efficiencies, not to be included in or relevant for WP#14 | E91: USG DMSPC;USG DOS | F91: Paulin Djomo Metanhi djomo@un.org | I91: At the end of December 2025, phase one of the consolidation review is completed. Jan 2026 expected endorsement of consolidation. | J91: 46052 | K91: Subject to Steering Group endorsement. Implementation not expected before Dec 2026. | L91: 46386 | M91: Confirmation needed | N91: Consider adjusting final milestone date to earlier potential checkpoint, if possible
A92: 31 | B92: WP31: UN Secretariat efficiencies and improvement | C92: 95 | D92: Implement residual actions from Phase II of the Working Group on Efficiencies, not to be included in or relevant for WP#14 | E92: USG DMSPC;USG DOS | F92: Patrick Carey careyp@un.org | I92: Phase 1 Travel Processing Office Consolidation Complete and Operational. | J92: 46387 | K92: Phase 2 Travel Processing Office Consolidation (Regional Hubs) Established. Full operational readiness subject to implementation of new travel management company contracts/procurement process (likely through 2028). | L92: 46752 | M92: Confirmation needed | N92: Consider earlier initial milestone; final milestone date falls outside implementation period of UN80 Initiative Action Plan
A93: 14 | B93: WP14: Unified services roadmap | C93: 64 | D93: Integrate supply chains, taking the New Humanitarian Compact as the concrete starting point | E93: Chair HLCM;ED WFP;Co-Chairs BIG | G93: AnneMarie Van Den Berg vandenberga@un.org Corinne Fleischer corinne.fleischer@wfp.org Leila Pakkala lpakkala@unicef.org | I93: Proposal for harmonized in-country logistics, with initial application in Afghanistan, Haiti, Gaza (OPT), Somalia and Sudan finalized | J93: 46112 | K93: Coordinated procurement of identified key items, pooled global logistics, and shared in-country logistics services are operational across the UN system | L93: 46387 | M93: Attention to timeline | N93: Review final deadline to ensure checkpoint on impact of action before end of December 2026

Sheet Sheet2
B2: Action Number | C2: Action | D2: Notes | E2: Questions
D3: 10 Feb: - Deliverable submitted with intermediate milestones | E3: 10 Feb: - What is the form of endorsement for the concept note? - From last TF meeting, did you get in touch with WP7? - Was the definition Rebeca shared on last TF agreed with WP8? - Rebeca Grynspan mentioned that WP7 need more discussion with WP8 -- difference in scope: Hubs on policy. EOD on existing support in country. Hubs: joint policy advice, knowledge product. EOD service packages, tech support. Hubs long-term coherence, knowledge infra, MS needs. EOD demand-driven opertional support system

Sheet Action Tracking
A1: DO NOT SORT; PLEASE ONLY USE FILTER+B2
A3: FROM SHAREPOINT LIST | L3: Actions completed [%] | M3: =COUNTIF(X6:X100, "*Action* completed*")/COUNTA(C6:C100) -> 0 | V3: SANITIZED MILESTONE (DRAFT) | AH3: MANUALLY INPUTTED NOTES | AU3: RISK
A5: WP No. | B5: Work Package | C5: Action No | D5: Indicative Action | E5: Sub-Action | F5: WP Leads | G5: Action Lead(s) | H5: Action Support(s) | I5: ActionEntity(s) | J5: Milestone 1 | K5: Milestone 1 Deadline | L5: Milestone Final | M5: Milestone Final Deadline | N5: Sense-checked | O5: Notes | P5: UpcomingMilestone | Q5: DeliveryDate | R5: Updates | V5: Upcoming Milestone | W5: Delivery Date | X5: Updates | Y5: Notes and Comments | Z5: OLA review status | AA5: WP No. | AB5: Action No | AC5: Check | AD5: Upcoming milestone check | AH5: Notes from Task Force | AI5: Notes on FP/working team level | AJ5: Questions on Initial Milestone | AK5: Notes on Initial Milestone | AL5: Questions on Final Milestone | AM5: WP No. | AN5: Action No | AO5: Column1 | AR5: Risk (Bureaucracy; Buy-in; Progress Stagnation; etc.) | AS5: WP No. | AT5: Action No | AU5: Column1
A6: 1 | B6: WP1: Peace operations (task delegation; review) | C6: 14 | D6: Delegate relevant programmatic tasks such as rule of law, governance and child protection – and the associated resources – to UN system entities best equipped to deliver them. | F6: USG DPPA; USG DPO | G6: Rosemary DiCarlo, USG DPPA, rosemary.dicarlo@un.org; Jean-Pierre Lacroix, USG DPO, jean-pierre.lacroix@un.org Alexander de Croo, Administrator UNDP, alexander.de.croo@undp.org; Tom Fletcher, USG OCHA, fletcher@un.org; Oscar Fernandez Taranco, ASG DCO, fernandez-taranco@un.org; Volker Türk, HC OHCHR, volker.turk@un.org; Elizabeth Spehar, ASG PBSO, spehare@un.org; Faisal Shahkar, UN Police Commissioner DPO OROLSI, faisal.shahkar@un.org; Catherine Russell, ED UNICEF, crussell@unicef.org; Sima Bahous, Executive Director, UN Women sima.bahous@unwomen.org; Vanessa Frazier, SRSG CAAC,, vanessa.frazier@un.org; Pramila Patten, SRSG SVC, pramila.patten@un.org | H6: David Haeri, Director DPET, DPO, haeri@un.org; Asif Khan, Director PMD, DPPA, khan34@un.org | I6: DPPA; DPO; UNDP; OCHA; DCO; OHCHR; UNICEF; UN Women; OSRSG CAAC; OSRSG SVC | J6: Language on delegation included in the draft review of peace ops that includes the overall reset, to be sent to SG for approval. | K6: 46068 | L6: Concept note and roadmap to be finalized by DPO and DPPA, for SG's consideration. | M6: 46183 | N6: Finalized | P6: Draft review of the future of peace operations (requested in GA resolution 79/1) submitted for the Secretary-General's consideration | Q6: =UN80_Action_Plan__2_1[[#This Row],[Milestone 1 Deadline]] -> 46068 | V6: Draft review of the future of peace operations (requested in GA resolution 79/1) submitted for the Secretary-General's consideration | W6: =UN80_Action_Plan__2_1[[#This Row],[DeliveryDate]] -> 46068 | Z6: OK | AA6: 1 | AB6: 14 | AC6: =IF(UN80_Action_Plan__2_1[[#This Row],[Action No]]=Table10[[#This Row],[Action No]],1,0) -> 1 | AD6: =IF( AND(P6=V6, INT(Q6)=INT(W6), R6=X6), 1, _xlfn.TEXTJOIN(", ", TRUE, IF(P6<>V6, "Upcoming milestone mismatch", ""), IF(INT(Q6)<>INT(W6), "Delivery date mismatch", ""), IF(R6<>X6, "Updates mismatch", "") ) ) -> 1 | AJ6: 21 Jan: - Are you clear on the scope? Recall that the SG’s intent is that the mandate stays with the mission, which then delegates resources to entities | AK6: 21 Jan: - Note: This will not be easy due to a) internal resistance at Director-level, b) uncertainty if existing missions are affected or only future ones, c) hair-splitting on how ‘child protection’ done by missions is different from UNICEF. | AL6: - Problem statement and objectives clarified? - Scope of tasks to be delegated defined? - Relevant entities and capacities mapped? - Initial options or models drafted? - Inputs from key stakeholders gathered? | AM6: 1 | AN6: 14 | AO6: =IF(UN80_Action_Plan__2_1[[#This Row],[Action No]]=Table8[[#This Row],[Action No]],1,0) -> 1 | AR6: Yes | AS6: 1 | AT6: 14 | AU6: =IF(UN80_Action_Plan__2_1[[#This Row],[Action No]]=Table9[[#This Row],[Action No]],1,0) -> 1
A7: 1 | B7: WP1: Peace operations (task delegation; review) | C7: 15 | D7: Present comprehensive proposal for the reset of peace operations to Member States upon conclusion of the review mandated by the Pact for the Future. | F7: USG DPPA; USG DPO | G7: Rosemary DiCarlo, USG DPPA, rosemary.dicarlo@un.org; Jean-Pierre Lacroix, USG DPO, jean-pierre.lacroix@un.org | H7: David Haeri, Director DPET, DPO, haeri@un.org; Asif Khan, Director PMD, DPPA, khan34@un.org | I7: DPPA; DPO | J7: Draft of the review of the future of all forms of peace operations, including recommendations on a reset of peace operations, submitted to the Secretary-General | K7: 46068 | L7: Review of the future of peace operations, including recommendations on a reset of peace operations, finalised (final date dependent on SG clearance). | M7: 46112 | N7: Finalized | P7: Draft review of the future of peace operations (requested in GA resolution 79/1) submitted for the Secretary-General's consideration | Q7: =UN80_Action_Plan__2_1[[#This Row],[Milestone 1 Deadline]] -> 46068 | V7: Draft review of the future of peace operations (requested in GA resolution 79/1) submitted for the Secretary-General's consideration | W7: =UN80_Action_Plan__2_1[[#This Row],[DeliveryDate]] -> 46068 | Z7: OK | AA7: 1 | AB7: 15 | AC7: =IF(UN80_Action_Plan__2_1[[#This Row],[Action No]]=Table10[[#This Row],[Action No]],1,0) -> 1 | AD7: =IF( AND(P7=V7, INT(Q7)=INT(W7), R7=X7), 1, _xlfn.TEXTJOIN(", ", TRUE, IF(P7<>V7, "Upcoming milestone mismatch", ""), IF(INT(Q7)<>INT(W7), "Delivery date mismatch", ""), IF(R7<>X7, "Updates mismatch", "") ) ) -> 1 | AI7: 15 Jan: KJ/MR: - USG La Croix talked to SG saying that review may be done only in March - They will talk with USG Rosemary in Feb to SG - There's a note that MR can share - They have SPG channell with SG and Guy not a part of this | AJ7: 21 Jan: - What is the timeline for the peace operations review? - To what body will the report be submitted so it can translate to action? | AK7: 21 Jan: - Note: Information on timelines remains conflicting (refer note to SG different from USG bilateral) and ambition limited. In general, any meaningful changes in SPM and PKM budgets have now ‘missed the budget deadline’. | AL7: - Scope and methodology confirmed? - Data and inputs collected? - Analysis completed and findings captured? - Expert validation conducted? - Assessment note finalized? | AM7: 1 | AN7: 15 | AO7: =IF(UN80_Action_Plan__2_1[[#This Row],[Action No]]=Table8[[#This Row],[Action No]],1,0) -> 1 | AR7: Yes | AS7: 1 | AT7: 15 | AU7: =IF(UN80_Action_Plan__2_1[[#This Row],[Action No]]=Table9[[#This Row],[Action No]],1,0) -> 1
A8: 2 | B8: WP2: New Humanitarian Compact | C8: 16 | D8: Streamline Humanitarian Needs and Response Plans to become shorter and sharper | F8: USG OCHA | G8: Tom Fletcher, USG OCHA, fletcher@un.org | H8: Hansjoerg Strohmeyer, Policy Director, OCHA - strohmeyerh@un.org | I8: OCHA | J8: By Q1 2026, publication of 2026 Humanitarian Response Plans (HNRPs) that are shorter, sharper and increasingly digitized | K8: 46111 | L8: By Q1 2026, publication of 2026 Humanitarian Response Plans (HNRPs) that are shorter, sharper and increasingly digitized | M8: 46111 | N8: Finalized | O8: Substantive work has been done, hence no initial indicative milestone | P8: Humanitarian Response Plans for 2026 published in shorter and more digital format | Q8: 46111.167 | V8: Humanitarian Response Plans for 2026 published in shorter and more digital format | W8: =UN80_Action_Plan__2_1[[#This Row],[Milestone Final Deadline]] -> 46111 | Z8: OK | AA8: 2 | AB8: 16 | AC8: =IF(UN80_Action_Plan__2_1[[#This Row],[Action No]]=Table10[[#This Row],[Action No]],1,0) -> 1 | AD8: =IF( AND(P8=V8, INT(Q8)=INT(W8), R8=X8), 1, _xlfn.TEXTJOIN(", ", TRUE, IF(P8<>V8, "Upcoming milestone mismatch", ""), IF(INT(Q8)<>INT(W8), "Delivery date mismatch", ""), IF(R8<>X8, "Updates mismatch", "") ) ) -> 1 | AI8: 16 Jan: KJ: Big picture where's the juice? Murad: Supply chain, common services, Data Collaborative (most advanced, concrete), beneficiary data (could be hopeful - need to push), Murad: - Internal pressure from quint on substance -- potential to push to further progress - IASC agreed - Led by Gemma KJ: Is it for 2026 or 2027? Murad: - Likely in 2027 -- increased digitization - Gemma is clear on this but he's not aware | AJ8: 21 Jan: - What work is going on to drive another push on simplification and digital transformation for 2027, given that the 2026 Humanitarian Response Plans (HNRPs) are done? | AK8: 21 Jan: - Note: After progress in cutting the plans from 200 to 80 pages each for 2026, OCHA seem unresolved on how to push further. Digital plans unclear. | AM8: 2 | AN8: 16 | AO8: =IF(UN80_Action_Plan__2_1[[#This Row],[Action No]]=Table8[[#This Row],[Action No]],1,0) -> 1 | AS8: 2 | AT8: 16 | AU8: =IF(UN80_Action_Plan__2_1[[#This Row],[Action No]]=Table9[[#This Row],[Action No]],1,0) -> 1
A9: 2 | B9: WP2: New Humanitarian Compact | C9: 17 | D9: Integrate global supply chains, coordinating procurement of key items, pool use of global freight and logistics, and unbranded in-country services open to the entire UN system | F9: USG OCHA | G9: Tom Fletcher, USG OCHA, fletcher@un.org; Catherine Russell, ED UNICEF, crussell@unicef.org; Cindy McCain, ED WFP, cindy.mccain@wfp.org; Atul Khare, USG DOS, khare@un.org | H9: Hansjoerg Strohmeyer, Policy Director, OCHA, strohmeyerh@un.org; AnneMarie Van Den Berg, Assistant Secretary-General, PSCM-DOS, vandenberga@un.org; Corinne Fleischer, Director, Supply Chain, WFP, Corinne.fleischer@wfp.org; Leila Gharagozloo Pakkala, Director, Supply Divisions, UNICEF, lpakkala@unicef.org | I9: OCHA; UNICEF; WFP; DOS | J9: Interagency supply chain design endorsed by participating agencies, and starter locations agreed | K9: 46052 | L9: Integrated UN supply chain operational across agencies, with joint procurement and shared logistics in starter countries, improving speed and cost | M9: 46264 | N9: Finalized | P9: Integrated supply chain operational in starter countries | Q9: 46264.167 | V9: Integrated supply chain operational in starter countries | W9: =UN80_Action_Plan__2_1[[#This Row],[Milestone Final Deadline]] -> 46264 | Z9: OK | AA9: 2 | AB9: 17 | AC9: =IF(UN80_Action_Plan__2_1[[#This Row],[Action No]]=Table10[[#This Row],[Action No]],1,0) -> 1 | AD9: =IF( AND(P9=V9, INT(Q9)=INT(W9), R9=X9), 1, _xlfn.TEXTJOIN(", ", TRUE, IF(P9<>V9, "Upcoming milestone mismatch", ""), IF(INT(Q9)<>INT(W9), "Delivery date mismatch", ""), IF(R9<>X9, "Updates mismatch", "") ) ) -> 1 | AH9: 5 Feb: Hansjoerg - Copenhagen meeting: 3 key areas in 5 starter -- Rationalizing global procurement responsibilities for core relief items (items: tents, vaccine, food, other nutritional/medical - have primary 2ndary vendors) - will req Principal discussion SG/USG - decision making needed -- Align agencies comp adv (market engagement, route, transport modes) -- Integrating in-country delivery (proposal next week in Gaza -- then move to Sudan, Afghanistan, Somalia. By March, have ideas on what areas - joint warehousing etc - to be working together, not in $ count but biz case) Elinor: - Can we deal name of this? Joint common services? Before going to MS -- UN vs. UN system Guy: - Endorsement happened or not? Hansjoerg: - 2 issues upstream not endorsement - Endorsement done for country-level design -- 5 starter in 3rd item -- have discussions on support strx (DOS, WFP, UNICEF Quint) -- will build concrete agreement on who want to join (e.g., WHO, FPA -- interagency agreement) -- country team support - Gaza: WFP, FPA, IOM alrd ok - Design to generate commonalities Guy: - SG ready to convene and have convos Hansjoerg: - Next week meet Hansjoerg and UNICEF person 7 Jan: - Guy: Parallel with unified common services roadmap? - Hansjoerg: -- Common services coordinated with HLCM, BIG -- 95% Phase I global service has been catalogued: incl 17 services (fleet, engineering, booking hub, asset) -- Jan-Mar: Phase II -- End of Mar: issue guidance on Phase III with business case for consolidation among agencies | AJ9: 5 Feb: - For starter country (list) Country teams are briefed, identifying logistics opportunities; HQ teams dispatched for implementation roadmaps in target countries. - What is the status of the inter-agency supply design that you were expecting to be endorsed by 31 Jan? - Beyond UNICEF, WFP, DOS, what other entities are expected to endorse the design – how can we / SG help? - At global level, what are next steps for integrating supply chain functions, because that is the key unlock to progress? - When can we bring the topic of endorsement to the Steering Committee, before the CEB? 7 Jan: - How are these arrangements embedded in the larger Unified Services Roadmap driven by HLCM and BIG? No parallel arrangements, or one-off pilots. ------ - Related: How do we make sure that these are not one-off country pilots? - How can SG help push for sustainable institutional arrangements? | AK9: 5 Feb: - Note: WFP and UNICEF are key. DOS may slow things down. Still unclear what Cindy McCain’s complaint was (Carl may know). Positive: Hansjoerg was part of a D-2 / ASG-level workshop in Copenhagen last weekend (we have readout). A key unlock is to push for global-level consolidation of procurement, global transport, and in-country delivery responsibilities. | AL9: - Expanded service set confirmed across contexts? - Uptake by multiple agencies verified? - Operational performance data collected? - Efficiency gains and improvements assessed? - Findings validated through review process? | AM9: 2 | AN9: 17 | AO9: =IF(UN80_Action_Plan__2_1[[#This Row],[Action No]]=Table8[[#This Row],[Action No]],1,0) -> 1 | AS9: 2 | AT9: 17 | AU9: =IF(UN80_Action_Plan__2_1[[#This Row],[Action No]]=Table9[[#This Row],[Action No]],1,0) -> 1
A10: 2 | B10: WP2: New Humanitarian Compact | C10: 18 | D10: Scale common services with a Global Services Hub and interoperable digital platforms to help consolidate surge rosters, logistics, security, telecoms and engineering support | F10: USG OCHA | G10: Tom Fletcher, USG OCHA, fletcher@un.org; Filippo Grandi, HC UNHCR grandi@unhcr.org; Cindy McCain, ED WFP, cindy.mccain@wfp.org | H10: Hansjoerg Strohmeyer, Policy Director, OCHA, strohmeyerh@un.org; Kelly Tallman Clements, Deputy High Commissioner for Refugees, UNHCR, clements@unhcr.org; Carl Skau, Deputy Executive Director and Chief Operating Officer, World Food Programme (WFP) - carl.skau@wfp.org | I10: OCHA; UNHCR; WFP | J10: Initial package of priority common services identified, based on existing practices (e.g. fleet, booking, engineering, connectivity, security/emergency mgmt | K10: 46052 | L10: Priority common services expanded across several contexts with multiple agencies, with a review demonstrating clearer and more efficient shared delivery | M10: 46264 | N10: Finalized | P10: Priority common services expanded to cover multiple agencies and contexts | Q10: 46264.167 | V10: Priority common services expanded to cover multiple agencies and contexts | W10: =UN80_Action_Plan__2_1[[#This Row],[Milestone Final Deadline]] -> 46264 | Z10: OK | AA10: 2 | AB10: 18 | AC10: =IF(UN80_Action_Plan__2_1[[#This Row],[Action No]]=Table10[[#This Row],[Action No]],1,0) -> 1 | AD10: =IF( AND(P10=V10, INT(Q10)=INT(W10), R10=X10), 1, _xlfn.TEXTJOIN(", ", TRUE, IF(P10<>V10, "Upcoming milestone mismatch", ""), IF(INT(Q10)<>INT(W10), "Delivery date mismatch", ""), IF(R10<>X10, "Updates mismatch", "") ) ) -> 1 | AH10: 5 Feb: Kelly: - Service catalogues -- where services available -- using UN Booking Hub - Linked to Unified Services Roadmap - WFP, UNHCR -- catalogue live (Phase I), fleet resourcing, travel engineering, asset disposal - Looking at SLAs - Use this as enabling -- to expand to Phase II (Jan - Mar; expand partner and solutions, onboarding UN service providers, BIG shared services, practical guide for usage) -- ride-sharing, renewable energy - Phase III (Mar - Sep) consolidation option with biz case -- linked to overall Unified Service Delivery - Need senior management support | AJ10: 5 Feb: - What is the status of the package? - In simple terms, how does this link to / or catalyze the BIG / HLCM agendas? - On the last Task Force, you mentioned Phase II. What is Phase II and what is the status of Phase II? ----- - What is the plan to scale and institutionalize this work? | AK10: 5 Feb: - Note: Here, the key question is how this work (which progress) is linked to the BIG and HLCM agenda. | AM10: 2 | AN10: 18 | AO10: =IF(UN80_Action_Plan__2_1[[#This Row],[Action No]]=Table8[[#This Row],[Action No]],1,0) -> 1 | AS10: 2 | AT10: 18 | AU10: =IF(UN80_Action_Plan__2_1[[#This Row],[Action No]]=Table9[[#This Row],[Action No]],1,0) -> 1
A11: 2 | B11: WP2: New Humanitarian Compact | C11: 20 | D11: Initiate new Humanitarian Data Collaborative, to scale common platforms, collective financing, shared centres, capacities and standards | F11: USG OCHA | G11: Tom Fletcher, USG OCHA, fletcher@un.org; Filippo Grandi, HC UNHCR, grandi@unhcr.org; Catherine Russell, ED UNICEF, crussell@unicef.org; Cindy McCain, ED WFP, cindy.mccain@wfp.org; Amy Pope, Director General IOM, dg@iom.int | H11: Hansjoerg Strohmeyer, Policy Director, OCHA, strohmeyerh@un.org; Jean-Martin Bauer, Director, Assessments, Planning, Policy and Research, WFP, jean-martin.bauer@wfp.org Sarah Telford, Head of Centre for Humanitarian Data, OCHA - telford@un.org | I11: OCHA; UNHCR; UNICEF; WFP; IOM | J11: Humanitarian Cluster Data Workplan finalized, including quick wins, starter countries, governance options and a joint data-sharing ambition | K11: 46052 | L11: Humanitarian Data Collaborative established, scaling platforms, financing and shared capacities and standards | M11: 46264 | N11: Finalized | P11: Data collaborative established, scaling joint platforms, financing, capacities and standards | Q11: 46264.167 | V11: Collaborative established, scaling joint platforms, financing, capacities and standards | W11: =UN80_Action_Plan__2_1[[#This Row],[Milestone Final Deadline]] -> 46264 | Z11: OK | AA11: 2 | AB11: 20 | AC11: =IF(UN80_Action_Plan__2_1[[#This Row],[Action No]]=Table10[[#This Row],[Action No]],1,0) -> 1 | AD11: =IF( AND(P11=V11, INT(Q11)=INT(W11), R11=X11), 1, _xlfn.TEXTJOIN(", ", TRUE, IF(P11<>V11, "Upcoming milestone mismatch", ""), IF(INT(Q11)<>INT(W11), "Delivery date mismatch", ""), IF(R11<>X11, "Updates mismatch", "") ) ) -> Upcoming milestone mismatch | AH11: 14 Jan: Gemma: - Bringing data in 1 platform - Unified 6mo workplan Jan-Jun: implementation on core data harmonization - NGO partners will be engaged Guy: Political buy-in from SC | AJ11: 14 Jan: - What is the progress of the draft workplan? - When can we take to SC? ------ - Governance options validated? - Quick wins and starter countries confirmed? - Joint data-sharing ambition agreed? | AK11: 14 Jan: - Note: This seems to progress well, but needs to land with a ‘launchable’ plan in Q1 / Q2. Plus: Risk of being tangled up in coordination with non-UN entities. | AL11: - Governance model and TORs finalized? - Membership and leadership confirmed? - Shared platforms and financing arrangements activated? - Initial workplan and standards agreed? - Collaborative formally launched and operational? | AM11: 2 | AN11: 20 | AO11: =IF(UN80_Action_Plan__2_1[[#This Row],[Action No]]=Table8[[#This Row],[Action No]],1,0) -> 1 | AS11: 2 | AT11: 20 | AU11: =IF(UN80_Action_Plan__2_1[[#This Row],[Action No]]=Table9[[#This Row],[Action No]],1,0) -> 1
A12: 2 | B12: WP2: New Humanitarian Compact | C12: 21 | D12: Initiate Collaborative Humanitarian Diplomacy Initiative to bring agencies together under the coordination of the Emergency Relief Coordinator | F12: USG OCHA | G12: Tom Fletcher, USG OCHA, fletcher@un.org; Filippo Grandi, HC UNHCR, grandi@unhcr.org; Catherine Russell, ED UNICEF, crussell@unicef.org; Cindy McCain, ED WFP, cindy.mccain@wfp.org; Amy Pope, Director General IOM, dg@iom.int | H12: Hansjoerg Strohmeyer, Policy Director, OCHA, strohmeyerh@un.org; Fredrick Lee-Ohlsson, Director, OED-DIP, WFP, fredrick.lee-ohlsson@wfp.org; Ted Chaiban, Deputy Executive Director, UNICEF, tchaiban@unicef.org; Ugochi Daniels, Deputy Director General for Operations, International Organization for Migration (IOM), udaniels@iom.int; Shahrzad Tadjbakhsh, Director, Division of International Protection, UNHCR, tadjbakh@unhcr.org | I12: OCHA; UNHCR; UNICEF; WFP; IOM | J12: Principals’ Humanitarian Diplomacy mechanism launched, with agreed priorities, meeting cadence, and initial crisis list identified | K12: 46052 | L12: Collab. humanitarian diplomacy functioning system-wide with coordinated messaging, shared strategies and clear impact in priority crises | M12: 46264 | N12: Finalized | P12: Initiative functioning system-wide, with joint messaging and strategies for priority crises | Q12: 46264.167 | V12: Initiative functioning system-wide, with joint messaging and strategies for priority crises | W12: =UN80_Action_Plan__2_1[[#This Row],[Milestone Final Deadline]] -> 46264 | Z12: OK | AA12: 2 | AB12: 21 | AC12: =IF(UN80_Action_Plan__2_1[[#This Row],[Action No]]=Table10[[#This Row],[Action No]],1,0) -> 1 | AD12: =IF( AND(P12=V12, INT(Q12)=INT(W12), R12=X12), 1, _xlfn.TEXTJOIN(", ", TRUE, IF(P12<>V12, "Upcoming milestone mismatch", ""), IF(INT(Q12)<>INT(W12), "Delivery date mismatch", ""), IF(R12<>X12, "Updates mismatch", "") ) ) -> 1 | AI12: 16 Jan: Murad: - Options for concept in IASC -- Humanitarian Negotiation Unit in charge - UNHCR not super happy abt this - Murad not super aware on the outcome of this KJ: How to know if the diplomacy is established? Murad: - Standing biwekly meeting - List of contacts published - Secretariat will coordinate messaging etc. - Have internal meeting with Manu | AJ12: 21 Jan: - How is this mechanism different from the previous efforts? - How will you resource the support to the initiative long-term. | AK12: 21 Jan: - Note: This seems to boil down to a regular principals meeting on about 12 agreed settings. Unclear what else. | AL12: - Governance, roles and workflows confirmed? - Shared messaging and strategies coordinated? - Participation across agencies verified? - Priority-crisis approach implemented? - Evidence of system-wide impact documented? | AM12: 2 | AN12: 21 | AO12: =IF(UN80_Action_Plan__2_1[[#This Row],[Action No]]=Table8[[#This Row],[Action No]],1,0) -> 1 | AS12: 2 | AT12: 21 | AU12: =IF(UN80_Action_Plan__2_1[[#This Row],[Action No]]=Table9[[#This Row],[Action No]],1,0) -> 1
A13: 2 | B13: WP2: New Humanitarian Compact | C13: 22 | D13: Align agencies’ responsibilities: FAO/WFP/IFAD on food security | F13: USG OCHA | G13: Rania DAGASH-KAMARA, Assistant ED Partnerships and Innovation, rania.dagash@wfp.org | H13: Laura Turner, Deputy Director of Emergency Coordination, WFP, Laura.Turner@wfp.org; Ms. Lauren Philips, Director of Partnerships and UN Collaboration, lauren.phillips@fao.org; Mr. Rein Paulsen, Director of the Office of Emergency and Resilience - rein.paulsen@fao.org; Ron Hartman, Director for Global Engagement, Partnerships and Resource Mobilization, r.hartman@ifad.org; Hansjoerg Strohmeyer, Policy Director, OCHA, strohmeyerh@un.org | I13: WFP; FAO; IFAD; OCHA | J13: RBAs agree on a light, practical approach for more coherent work in fragile settings, clarifying complementary roles, choosing small number of priority countries | K13: 46052 | L13: In priority contexts, RBAs show clearer alignment in practice, with better sequencing and less duplication, and share a short lessons-learned note to UN80 bodies | M13: 46264 | N13: Finalized | P13: Relevant entities demonstrate clearer alignment in priority settings | Q13: =UN80_Action_Plan__2_1[[#This Row],[Milestone Final Deadline]] -> 46264 | V13: Approaches for more coherent work finalized for priority settings | W13: =UN80_Action_Plan__2_1[[#This Row],[Milestone 1 Deadline]] -> 46052 | Z13: OK | AA13: 2 | AB13: 22 | AC13: =IF(UN80_Action_Plan__2_1[[#This Row],[Action No]]=Table10[[#This Row],[Action No]],1,0) -> 1 | AD13: =IF( AND(P13=V13, INT(Q13)=INT(W13), R13=X13), 1, _xlfn.TEXTJOIN(", ", TRUE, IF(P13<>V13, "Upcoming milestone mismatch", ""), IF(INT(Q13)<>INT(W13), "Delivery date mismatch", ""), IF(R13<>X13, "Updates mismatch", "") ) ) -> Upcoming milestone mismatch, Delivery date mismatch | AI13: 16 Jan: Murad: - They have an idea -- Murad not aware of the updates - Reach out to WFP - Ally on this progress for TF meeting - Lauren from WFP focal point | AJ13: 21 Jan: - What does success look like for this action? - Are the 3 entities close to agreement on the approach? - Are priority countries confirmed? What are they? | AK13: 21 Jan: - Note: It seems unclear if there is alignment on goals and actions. We should consider bringing relevant USG/ASG into the next TF. | AL13: - Priority contexts confirmed and monitored? - Division of roles and sequencing applied in practice? - Duplication reduced and coordination improved? - Evidence and examples of aligned delivery collected? - Short lessons note drafted and shared? | AM13: 2 | AN13: 22 | AO13: =IF(UN80_Action_Plan__2_1[[#This Row],[Action No]]=Table8[[#This Row],[Action No]],1,0) -> 1 | AS13: 2 | AT13: 22 | AU13: =IF(UN80_Action_Plan__2_1[[#This Row],[Action No]]=Table9[[#This Row],[Action No]],1,0) -> 1
A14: 2 | B14: WP2: New Humanitarian Compact | C14: 23 | D14: Align agencies’ responsibilities: UNHCR/IOM on joint institutional approaches (incl. route-based programming) | F14: USG OCHA | G14: Filippo Grandi, HC UNHCR, grandi@unhcr.org; Amy Pope, Director General, International Organization for Migration (IOM) - dg@iom.int | H14: Shahrzad Tadjbakhsh, Director, Division of International Protection, UNHCR, tadjbakh@unhcr.org; Ugochi Daniels, Deputy Director General for Operations, IOM, udaniels@iom.int; Hansjoerg Strohmeyer, Policy Director, OCHA, strohmeyerh@un.org | I14: UNHCR; IOM; OCHA | J14: 2–3 priority contexts are selected for agreement on context-specific approaches to enhance complementary operationalization of the Route-Based Approach, with comprehensive and connected interventions along routes | K14: 46052 | L14: In those contexts, complementarity is demonstrated by UNHCR and IOM in operationalizing Route-Based programming, with clear roles, planning and coordination, and practical observations and lessons are shared with UN80 bodies | M14: 46264 | N14: Finalized | P14: Benefits of complementarity demonstrated along priority routes | Q14: 46264.167 | V14: Benefits of complementarity demonstrated along priority routes | W14: =UN80_Action_Plan__2_1[[#This Row],[Milestone Final Deadline]] -> 46264 | Z14: OK | AA14: 2 | AB14: 23 | AC14: =IF(UN80_Action_Plan__2_1[[#This Row],[Action No]]=Table10[[#This Row],[Action No]],1,0) -> 1 | AD14: =IF( AND(P14=V14, INT(Q14)=INT(W14), R14=X14), 1, _xlfn.TEXTJOIN(", ", TRUE, IF(P14<>V14, "Upcoming milestone mismatch", ""), IF(INT(Q14)<>INT(W14), "Delivery date mismatch", ""), IF(R14<>X14, "Updates mismatch", "") ) ) -> 1 | AI14: 16 Jan: Murad: - No update here yet -- will have check-in again early next week | AJ14: 21 Jan: - What does success look like for this action? - Are the context-specific approaches agreed? What is the context selected? - How are the approaches different from before? | AK14: 21 Jan: - Note: While ‘less bad’ than food security, OCHA and we don’t have enough info. We should consider bringing the USG/ASG into the next TF. | AL14: - Complementarity in selected contexts assessed? - Roles and sequencing applied in practice? - Parallel efforts reduced? - Evidence of improved joint delivery collected? - Lessons captured and shared with UN80? | AM14: 2 | AN14: 23 | AO14: =IF(UN80_Action_Plan__2_1[[#This Row],[Action No]]=Table8[[#This Row],[Action No]],1,0) -> 1 | AS14: 2 | AT14: 23 | AU14: =IF(UN80_Action_Plan__2_1[[#This Row],[Action No]]=Table9[[#This Row],[Action No]],1,0) -> 1
A15: 2 | B15: WP2: New Humanitarian Compact | C15: 24 | D15: Align agencies’ responsibilities: UNICEF/WFP/UNHCR/IOM on beneficiary data | F15: USG OCHA | G15: Filippo Grandi, HC UNHCR, grandi@unhcr.org; Amy Pope, Director General IOM, dg@iom.int; Catherine Russell, ED UNICEF, crussell@unicef.org; Cindy McCain, ED WFP cindy.mccain@wfp.org | H15: Ryan Beech, Head of Cash Operations, WFP, Ryan.Beech@wfp.org; Hansjoerg Strohmeyer, Policy Director, OCHA, strohmeyerh@un.org; UNICEF/IOM/HCR - To Be Confirmed | I15: UNHCR; IOM; UNICEF; WFP | J15: Agree on shared principles for beneficiary data interoperability, including privacy-by-design, consent, proportionality, and purpose limitation; identify 1–2 priority contexts for initial interoperability application across existing agency systems (e.g. HOPE, PRIMES, SCOPE, BRAVE), based on clearly defined operational use cases | K15: 46052 | L15: Demonstrate reduced duplication and improved service delivery in pilot contexts through secure, federated data exchange; document practical lessons learned and technical patterns to inform future scaling and policy discussions | M15: 46264 | N15: Finalized | P15: Benefits of federated, standards-based beneficiary data exchange demonstrated in priority contexts to inform scale-up | Q15: 46264.167 | V15: Benefits of federated, standards-based beneficiary data exchange demonstrated in priority contexts to inform scale-up | W15: =UN80_Action_Plan__2_1[[#This Row],[Milestone Final Deadline]] -> 46264 | Z15: OK | AA15: 2 | AB15: 24 | AC15: =IF(UN80_Action_Plan__2_1[[#This Row],[Action No]]=Table10[[#This Row],[Action No]],1,0) -> 1 | AD15: =IF( AND(P15=V15, INT(Q15)=INT(W15), R15=X15), 1, _xlfn.TEXTJOIN(", ", TRUE, IF(P15<>V15, "Upcoming milestone mismatch", ""), IF(INT(Q15)<>INT(W15), "Delivery date mismatch", ""), IF(R15<>X15, "Updates mismatch", "") ) ) -> 1 | AI15: 16 Jan: Murad: - No update here yet -- will have check-in again early next week | AJ15: 21 Jan: - What does success look like? - How can we support you? Our intent is to make ‘beneficiary data’ a priority use case in the technology accelerator. | AK15: 21 Jan: - Note: This seems to have started off very well, with good commitment, ambition and plans. Key here is that we want to make ‘beneficiary data’ a use case for the ‘technology accelerator’ (TAP) so it gets light in the SteerCo. | AL15: - Pilot interoperability results reviewed? - Duplication reduced and data flows assessed? - Technical and operational issues captured? - Benefits and constraints analyzed? - Lessons-learned note drafted and shared? | AM15: 2 | AN15: 24 | AO15: =IF(UN80_Action_Plan__2_1[[#This Row],[Action No]]=Table8[[#This Row],[Action No]],1,0) -> 1 | AS15: 2 | AT15: 24 | AU15: =IF(UN80_Action_Plan__2_1[[#This Row],[Action No]]=Table9[[#This Row],[Action No]],1,0) -> 1
A16: 2 | B16: WP2: New Humanitarian Compact | C16: 25 | D16: Align agencies’ responsibilities: WHO/UNICEF/WFP on health and nutrition | F16: USG OCHA | G16: Catherine Russell, ED UNICEF, crussell@unicef.org; Cindy McCain, ED WFP, cindy.mccain@wfp.org | H16: Ted Chaiban, Deputy Executive Director, UNICEF, tchaiban@unicef.org; Ilaria Dettori, Director, Nutrition Services, WFP, ilaria.dettori@wfp.org; Hansjoerg Strohmeyer, Policy Director, OCHA, strohmeyerh@un.org WHO | I16: UNICEF; WFP; OCHA; WHO | J16: Dedicated discussion held with relevant agencies, to identify priority areas where roles and responsibilities in health and nutrition emergency response require greater clarity (including health–nutrition interfaces and acute malnutrition response), with initial parameters agreed for complementarity | K16: 46052 | L16: Clearly defined roles and responsibilities for nutrition and health emergencies, developed separately under the respective Clusters, are compiled into concise reference material for field leadership and for Nutrition and Health Cluster partners respectively, with linkages between the two areas clearly described, and with factual observations shared with UN80 bodies | M16: 46264 | N16: Finalized | P16: Cluster-defined roles for health and nutrition emergencies consolidated into practical guidance material | Q16: 46264.167 | V16: Cluster-defined roles for health and nutrition emergencies consolidated into practical guidance material | W16: =UN80_Action_Plan__2_1[[#This Row],[Milestone Final Deadline]] -> 46264 | Z16: OK | AA16: 2 | AB16: 25 | AC16: =IF(UN80_Action_Plan__2_1[[#This Row],[Action No]]=Table10[[#This Row],[Action No]],1,0) -> 1 | AD16: =IF( AND(P16=V16, INT(Q16)=INT(W16), R16=X16), 1, _xlfn.TEXTJOIN(", ", TRUE, IF(P16<>V16, "Upcoming milestone mismatch", ""), IF(INT(Q16)<>INT(W16), "Delivery date mismatch", ""), IF(R16<>X16, "Updates mismatch", "") ) ) -> 1 | AI16: 16 Jan: Murad: - No update here yet -- will have check-in again early next week | AJ16: 21 Jan: - What does success look like? - What are the priority areas agreed on during the discussion? - How is this different from before? | AK16: 21 Jan: - Note: It seems unclear if there is alignment on goals and actions. We should consider bringing relevant USG/ASG into the next TF. | AL16: - Roles and responsibilities finalized? - Field-level guidance prepared and shared? - Information disseminated to Member States? - Coordination with Nutrition Cluster partners confirmed? - Feedback from field actors collected? | AM16: 2 | AN16: 25 | AO16: =IF(UN80_Action_Plan__2_1[[#This Row],[Action No]]=Table8[[#This Row],[Action No]],1,0) -> 1 | AS16: 2 | AT16: 25 | AU16: =IF(UN80_Action_Plan__2_1[[#This Row],[Action No]]=Table9[[#This Row],[Action No]],1,0) -> 1
A17: 3 | B17: WP3: UNDP/UNOPS | C17: 26 | D17: Conduct a thorough assessment of the benefits of a merger between UNDP and UNOPS; analysis to be presented to the Executive Boards in February 2026 | F17: DSG; Administrator UNDP; ED UNOPS | G17: Amina Mohammed, DSG, amina.mohammed@un.org; Jorge Moreira Da Silva, USG UNOPS, jorge.moreiradasilva@unops.org; Alexander de Croo, Administrator UNDP, alexander.de.croo@undp.org | H17: Sonja Leighton-Kone, ASG, UNOPS, sonjalk@unops.org; Linda Maguire, ASG, UNDP, linda.maguire@undp.org; Rahul Malhotra, Director New York Office, UNOPS, rahulm@unops.org; Fiona Bayat-Renoux, Deputy Chief of Staff, UNDP, Fiona.bayat-renoux@undp.org; Jean-Philippe Bernardini, Senior Political Affairs Officer, EOSG, Bernardini@un.org | I17: EOSG (ODSG); UNDP; UNOPS | J17: Draft initial assessment analysis of the ‘as is’ with high level merger proposal, pros, cons, risk analysis for internal consultations completed | K17: 46040 | L17: Thorough assessment of selected option(s) provided to Member States and guidance given through a General Assembly decision | M17: 46264 | N17: Finalized | P17: Initial analysis for the assessment completed for the Secretary-General's consideration | Q17: 46081.208 | V17: Initial analysis for the assessment completed for the Secretary-General's consideration | W17: 46081 | Z17: OK | AA17: 3 | AB17: 26 | AC17: =IF(UN80_Action_Plan__2_1[[#This Row],[Action No]]=Table10[[#This Row],[Action No]],1,0) -> 1 | AD17: =IF( AND(P17=V17, INT(Q17)=INT(W17), R17=X17), 1, _xlfn.TEXTJOIN(", ", TRUE, IF(P17<>V17, "Upcoming milestone mismatch", ""), IF(INT(Q17)<>INT(W17), "Delivery date mismatch", ""), IF(R17<>X17, "Updates mismatch", "") ) ) -> 1 | AH17: 17 Dec: - Jorge: when meeting with DSG the direction was merge to a new entity - GR: Agree on mapping external or not -->Jorge: integrate policy, finance, ops - Haoliang: need help for independent review, critical exam as option - Jorge: EB UNDP/UNOPS/UNFPA in Feb not to bring in that session to not paralyze other sessions -- ideally separate sessions in merger end of Feb - Haoliang: diff session so need to reach out/approach to ED Board Bureau -- steps need to take soon - Elinor: put into process documents -- documents to go to SG then MS; important to change language | AJ17: 28 Jan: - What is the ETA for the assessment? - Have you completed the vision statement you mentioned last time? - What is the plan for the February regular executive board session, or for creating an extraordinary session (and when)? - What are next steps in getting a proposal to the SG and then to GA (when and how)? 17 Dec: - Scope, methodology, data needs defined? - Document, data, interview collected? - Analysis conducted? - Findings validated with experts? - Draft developed? | AK17: 28 Jan: - Next UNDP / UNOPS / UNFPA Executive Board sessions are 2-5 February, i.e. next week. Assessment is overdue for SG consideration. Leaked assessments, or rumors of them, are making rounds among key donors. | AL17: - Final assessment report completed and cleared? - Options and recommendations clearly presented to Member States? - GA decision and guidance formally recorded? - Follow-up implications for UNDP and UNOPS mapped? - Next steps for implementation communicated? | AM17: 3 | AN17: 26 | AO17: =IF(UN80_Action_Plan__2_1[[#This Row],[Action No]]=Table8[[#This Row],[Action No]],1,0) -> 1 | AR17: Yes | AS17: 3 | AT17: 26 | AU17: =IF(UN80_Action_Plan__2_1[[#This Row],[Action No]]=Table9[[#This Row],[Action No]],1,0) -> 1
A18: 4 | B18: WP4: UNFPA/UN Women | C18: 27 | D18: Conduct a thorough assessment of the benefits of a merger of UNFPA and UN Women and their respective mandates | F18: DSG; ED UNFPA; ED UN Women | G18: Amina Mohammed, DSG, Amina.mohammed@un.org; Sima Bahous, Executive Director, UN Women sima.bahous@unwomen.org; Diene Keita, Executive Director, UNFPA, Keita@unfpa.org | H18: Jean Philippe Bernardini, Senior Political Affairs Officer, EOSG, bernardini@un.org; Sam Choritz, Chief of Staff, UNFPA, choritz@unfpa.org; Mohammad Naciri, Chief of Staff, UN Women, mohammad.naciri@unwomen.org | I18: EOSG (ODSG); UN Women; UNFPA | J18: Strategic merger assessment completed for internal consultations, including risk/benefit considerations | K18: 46052 | L18: By mid-2026, a thorough assessment is provided to Member States for a General Assembly decision | M18: 46233 | N18: Finalized | P18: Initial merger assessment completed for the Secretary-General's consideration | Q18: 46081.208 | V18: Initial merger assessment completed for the Secretary-General's consideration | W18: 46081 | Z18: OK | AA18: 4 | AB18: 27 | AC18: =IF(UN80_Action_Plan__2_1[[#This Row],[Action No]]=Table10[[#This Row],[Action No]],1,0) -> 1 | AD18: =IF( AND(P18=V18, INT(Q18)=INT(W18), R18=X18), 1, _xlfn.TEXTJOIN(", ", TRUE, IF(P18<>V18, "Upcoming milestone mismatch", ""), IF(INT(Q18)<>INT(W18), "Delivery date mismatch", ""), IF(R18<>X18, "Updates mismatch", "") ) ) -> 1 | AH18: 17 Dec: - Sima: suggest DSG/SG talks abt merger separately too; needs comms that are aligned abt strengthening gender equality not liquidity; messaging on GEA - Diane: assmt should show case complimentarity of mandates - Sima: population will be discussed (ICPD) - Diane: population survey re women incl. habitat etc; data on women in hum setting critical not to be confused from other data -- DESA can't do it not on the ground - Sima: segregation of data collctn -- who is going to be responsible of data collection - Guy: assessment has to be with vision statement (why this merger and not others); where assessment goes? - Sima: assessment fo to SG by 19 Jan | AJ18: 28 Jan: - What is the ETA for the assessment? - Have you been able to formulate a vision statement, as suggested last time? - What is the plan for the February regular executive board session, or for creating an extraordinary session (and when)? - What are next steps in getting a proposal to the SG and then to GA (when and how)? 17 Dec: - Scope, methodology, data needs defined? - Document, data, interview collected? - Analysis conducted? - Findings validated with experts? - Draft developed? | AK18: 28 Jan: - Note: Same note and questions. | AL18: - Final assessment report completed and cleared? - Options, risks and benefits clearly presented? - Member States briefed on key findings? - Inputs from Member States captured before GA decision? - Next steps contingent on GA decision outlined? | AM18: 4 | AN18: 27 | AO18: =IF(UN80_Action_Plan__2_1[[#This Row],[Action No]]=Table8[[#This Row],[Action No]],1,0) -> 1 | AS18: 4 | AT18: 27 | AU18: =IF(UN80_Action_Plan__2_1[[#This Row],[Action No]]=Table9[[#This Row],[Action No]],1,0) -> 1
A19: 4 | B19: WP4: UNFPA/UN Women | C19: 28 | D19: Conduct a thorough assessment to consider options to optimize normative functions of UNFPA on population statistics and related activities, including those currently undertaken by DESA | F19: DSG; ED UNFPA; ED UN Women | G19: Amina Mohammed, DSG, Amina.mohammed@un.org; Sima Bahous, Executive Director, UN Women sima.bahous@unwomen.org; Diene Keita, Executive Director, UNFPA, Keita@unfpa.org | H19: Jean Philippe Bernardini, Senior Political Affairs Officer, bernardini@un.org; Sam Choritz, Chief of Staff, UNFPA, choritz@unfpa.org; Mohammad Naciri, Chief of Staff, UN Women, mohammad.naciri@unwomen.org | I19: EOSG (ODSG); UN Women; UNFPA | J19: Options for optimization of the UN’s work on population statistics and related activities finalized for Secretary-General's consideration and integrated in merger analysis | K19: 46052 | L19: A final assessment integrated into the UN Women/UNFPA merger process, as per timelines above | M19: 46233 | N19: Finalized | P19: As part of strategic merger assessment (action 27), initial assessment of the UN system’s work on population statistics and related activities finalized for the Secretary-General's consideration | Q19: 46081.208 | V19: As part of strategic merger assessment (action 27), initial assessment of the UN system’s work on population statistics and related activities finalized for the Secretary-General's consideration | W19: 46081 | Z19: OK | AA19: 4 | AB19: 28 | AC19: =IF(UN80_Action_Plan__2_1[[#This Row],[Action No]]=Table10[[#This Row],[Action No]],1,0) -> 1 | AD19: =IF( AND(P19=V19, INT(Q19)=INT(W19), R19=X19), 1, _xlfn.TEXTJOIN(", ", TRUE, IF(P19<>V19, "Upcoming milestone mismatch", ""), IF(INT(Q19)<>INT(W19), "Delivery date mismatch", ""), IF(R19<>X19, "Updates mismatch", "") ) ) -> 1 | AJ19: 28 Jan: - What progress since the last task force? - What is the status of the options assessment? ETA, % complete, etc.? - What are the next steps? 17 Dec: - Scope, methodology, data needs defined? - Document, data, interview collected? - Analysis conducted? - Findings validated with experts? - Draft developed? | AK19: 28 Jan: - Note: DESA cannot / should not take operational responsibility for UNFPA’s work on the ground. Remember UNFPA census support is about $120 million per year, while DESA work is $8 million… The most obvious partners are UNDP (has elections support experience) or UNICEF (does a lot of survey work). Unclear how the work is progressing. | AL19: - Scope and methodology agreed? - UNFPA/DESA roles and functions mapped? - Options and implications analyzed? - Findings aligned with broader merger assessment? - Final integrated assessment validated? | AM19: 4 | AN19: 28 | AO19: =IF(UN80_Action_Plan__2_1[[#This Row],[Action No]]=Table8[[#This Row],[Action No]],1,0) -> 1 | AS19: 4 | AT19: 28 | AU19: =IF(UN80_Action_Plan__2_1[[#This Row],[Action No]]=Table9[[#This Row],[Action No]],1,0) -> 1
A20: 5 | B20: WP5: UNCT reconfiguration | C20: 39 | D20: Propose a model to reconfigure country teams via system-wide working group, chaired by the Deputy Secretary-General | F20: DSG | G20: Amina J. Mohammed, DSG, Amina.mohammed@un.org; Jorge Moreira Da Silva, USG UNOPS, jorge.moreiradasilva@unops.org | H20: Rahul Malhorta, Director, UNOPS, rahulm@unops.org; Jean Philippe Bernardini, Senior Political Affairs Officer, EOSG, bernardini@un.org | I20: EOSG (ODSG); UNOPS; UNSDG | J20: Outline of the draft proposals presented to the Secretary-General for guidance | K20: 46053 | L20: Recommendations on country configuration finalized for Secretary-General’s consideration, and relayed to Member States in the most appropriate format. | M20: 46263 | N20: Finalized | P20: System-wide working group convened and building blocks for proposals for UN country teams reconfiguration finalized for the Secretary-General's consideration | Q20: 46112.167 | V20: System-wide working group convened and building blocks for proposals for UN country teams reconfiguration finalized for the Secretary-General's consideration | W20: 46112 | Z20: OK | AA20: 5 | AB20: 39 | AC20: =IF(UN80_Action_Plan__2_1[[#This Row],[Action No]]=Table10[[#This Row],[Action No]],1,0) -> 1 | AD20: =IF( AND(P20=V20, INT(Q20)=INT(W20), R20=X20), 1, _xlfn.TEXTJOIN(", ", TRUE, IF(P20<>V20, "Upcoming milestone mismatch", ""), IF(INT(Q20)<>INT(W20), "Delivery date mismatch", ""), IF(R20<>X20, "Updates mismatch", "") ) ) -> 1 | AH20: 17 Dec: - Jens: DSG preparing new roadmap of consultation for this package - Jorge: more alignment from MS on this topic; questions on fx, capability, etc.; draft outline shared with DSG establishing recs; move to proper draft; will be for SG desk 7 Jan - Jorge: when should engage with UNSDG; ideally before SG desk - USG: surge capacity from specialized agencies or other entities - Oscar: Global RC meeting mentioned DCO 2.0; how hub to be constituted | AJ20: 28 Jan: - Looking ahead to UNGA, what is the product, the inter-governmental moment and resolution that will help us lock in the trajectory? Focus on that (the ‘pathway’). - Where are we on the consultation roadmap (mentioned last TF)? - What are the 2-3 solutions we can recommend now (not more diagnostics), and what decisions are needed to advance them? - Where do we risk waiting for dependencies that could delay progress unnecessarily? - What legislative / procedural pathways are anticipated (what resolution when)? 17 Dec: - Initial concept drafted? - Stakeholders mapped? - Concept circulated among stakeholders? - Proposal outline drafted? | AK20: 28 Jan: - Note: Partner impressions at GA briefing: Diagnostics are clear, but solutions (what Jorge calls building blocks) are less well defined. It will be important to push for a ‘portfolio of solutions’ – starting with the ‘most obvious’ (e.g., more multi-country offices). Critically, we need to push the team to define a ‘landing zone’ before GA, i.e., ‘what product when and where with the GA’? | AL20: - Final proposals consolidated for Member State review? - Comments from Member States addressed? - Decision or guidance formally recorded? - Implications for country team configuration clarified? - Next steps for implementation outlined? | AM20: 5 | AN20: 39 | AO20: =IF(UN80_Action_Plan__2_1[[#This Row],[Action No]]=Table8[[#This Row],[Action No]],1,0) -> 1 | AR20: Yes | AS20: 5 | AT20: 39 | AU20: =IF(UN80_Action_Plan__2_1[[#This Row],[Action No]]=Table9[[#This Row],[Action No]],1,0) -> 1
A21: 5 | B21: WP5: UNCT reconfiguration | C21: 40 | D21: Strengthen and recalibrate the Resident Coordinator system to better leverage knowledge hubs, expertise-on-demand, and non-resident entities | F21: DSG | G21: Amina J. Mohammed, DSG, Amina.mohammed@un.org; Oscar Fernandez-Taranco, ASG DCO, fernandez-taranco@un.org | H21: Jean Philippe Bernardini, Senior Political Affairs Officer, EOSG, bernardini@un.org | I21: EOSG (ODSG); DCO; UNSDG | J21: The parameters for the recalibration of the RC system defined (e.g., change in DCO structure, more tailored approach) | K21: 46052 | L21: All measures to recalibrate the RC system (DCO 2.0) implemented, under the Secretary-General’s authority, reflecting guidance from the appropriate legislative bodies | M21: 46263 | N21: Finalized | P21: Initial proposal for strengthening and recalibrating of the RC system prepared for Secretary-General's consideration | Q21: 46112.167 | V21: Initial proposal for strengthening and recalibrating of the RC system prepared for Secretary-General's consideration | W21: 46112 | Z21: OK | AA21: 5 | AB21: 40 | AC21: =IF(UN80_Action_Plan__2_1[[#This Row],[Action No]]=Table10[[#This Row],[Action No]],1,0) -> 1 | AD21: =IF( AND(P21=V21, INT(Q21)=INT(W21), R21=X21), 1, _xlfn.TEXTJOIN(", ", TRUE, IF(P21<>V21, "Upcoming milestone mismatch", ""), IF(INT(Q21)<>INT(W21), "Delivery date mismatch", ""), IF(R21<>X21, "Updates mismatch", "") ) ) -> 1 | AJ21: 28 Jan: - What is the legislative, procedural and political pathway to success? - What is the SG report we will use to get GA buy-in? How far along is it? - If time: How far along on ‘expanding multi-country offices? 17 Dec: - Concept drafted? - Baseline in country established? - Country situation or needs mapped? - Country typology established? - Stakeholders mapped? - Stakeholder discussion held? | AK21: 28 Jan: - Note: This is primarily about the future of DCO, RCs, and RC Offices – essentially the future budget, structures, functions of what DSG / Oscar oversee. Keywords issues are DCO 2.0, more multi-country offices (currently 16). Key issue is ‘pathway’. | AL21: - Recalibration measures fully implemented? - Funding model proposal finalized? - GA decision on funding model recorded? - Roles and capacities across RC system updated? - Next steps for sustained rollout confirmed? | AM21: 5 | AN21: 40 | AO21: =IF(UN80_Action_Plan__2_1[[#This Row],[Action No]]=Table8[[#This Row],[Action No]],1,0) -> 1 | AR21: Yes | AS21: 5 | AT21: 40 | AU21: =IF(UN80_Action_Plan__2_1[[#This Row],[Action No]]=Table9[[#This Row],[Action No]],1,0) -> 1
A22: 6 | B22: WP6: Regional reset | C22: 36 | D22: Establish a system-wide working group, chaired by the Deputy Secretary-General, to develop proposals on how to advance a reset of regional capacities for sustainable development, incl. on how to institutionalize Regional Integrated Platforms | F22: DSG | G22: Amina J. Mohammed, DSG, Amina.mohammed@un.org; Izumi Nakamitsu, USG ODA, nakamitsu@un.org | H22: Jean Philippe Bernardini, Senior Political Affairs Officer, EOSG, bernardini@un.org | I22: EOSG (ODSG); ODA; UNSDG | J22: System-wide working group convened and draft outline finalized and shared with the Secretary-General for guidance | K22: 46053 | L22: All aspects of the regional reset under SG prerogative implemented and proposals presented to Member States on aspects requiring new mandates | M22: 46263 | N22: Finalized | P22: System-wide working group convened and proposal for a regional reset of capacities for sustainable development and institutionalization of Regional Integrated Platforms shared with the Secretary-General for his consideration | Q22: 46112.167 | V22: System-wide working group convened and proposal for a regional reset of capacities for sustainable development and institutionalization of Regional Integrated Platforms shared with the Secretary-General for his consideration | W22: 46112 | Z22: OK | AA22: 6 | AB22: 36 | AC22: =IF(UN80_Action_Plan__2_1[[#This Row],[Action No]]=Table10[[#This Row],[Action No]],1,0) -> 1 | AD22: =IF( AND(P22=V22, INT(Q22)=INT(W22), R22=X22), 1, _xlfn.TEXTJOIN(", ", TRUE, IF(P22<>V22, "Upcoming milestone mismatch", ""), IF(INT(Q22)<>INT(W22), "Delivery date mismatch", ""), IF(R22<>X22, "Updates mismatch", "") ) ) -> 1 | AH22: 12 Jan - UNSDG Meeting: - Expertise on demand part of regional reset discussion 17 Dec: - Jens: packed to DSG meeting on technical issue - Izumi: funding is essential for th regional reset; engaged with regional RCs and heads of regional directors -- most difficult and sensitive; divergent views what's optimal; 2 ODA working with DSG and DCO teams -- entity-level consultation meeting; SDG meeting in Jan - Izumi: w/o UN80 alrd move to regionalization or MCO config -- alrd relocating so add further complication -- hopefully UNSDG Jan meeting can help -- need to be cross-pillar attendance - Oscar: hubs and surge needs to align; planning, crisis response, strategy, coop framework need to come together - Diane: RC and region footprints different -- resource mobilization to be moved in all levels differently - Guy: due date 7 Jan - Jens: funding mech WP can share baseline data in mid-Jan -- can be used in UNCT, reset, RIP; how do finance country and regional; biz model for EOD can be input to these discussions | AJ22: 28 Jan: - Is the working group on track in finalizing and sharing the draft outline with the SG by 31 Jan? If not, by when? - What are the top decisions needed to keep momentum and reduce complexity? 17 Dec: - Stakeholders mapped? - Initial concept drafted - Concept circulated among stakeholders? - Outline drafted? | AK22: 28 Jan: - Note: If any, this is the key work package to push for ‘focus’ and ‘simple solutions’ first. It is also the package most likely to ‘hold up’ others through ‘inter-relationship’ talk. Push colleagues to focus, prioritize, sequence. | AL22: - Final regional reset proposals consolidated? - Inputs from Member States addressed? - Decisions on mandate-related elements recorded? - SG-prerogative measures fully implemented? - Next steps for systemwide rollout clarified? | AM22: 6 | AN22: 36 | AO22: =IF(UN80_Action_Plan__2_1[[#This Row],[Action No]]=Table8[[#This Row],[Action No]],1,0) -> 1 | AR22: Yes | AS22: 6 | AT22: 36 | AU22: =IF(UN80_Action_Plan__2_1[[#This Row],[Action No]]=Table9[[#This Row],[Action No]],1,0) -> 1
A23: 6 | B23: WP6: Regional reset | C23: 37 | D23: Systematize the practice of hosting regional capacities within the Regional Economic Commissions, starting with DCO regional directors and teams | F23: DSG | G23: Amina J. Mohammed, DSG, Amina.mohammed@un.org; Izumi Nakamitsu, USG ODA, nakamitsu@un.org; Oscar Fernandez Taranco, ASG DCO, fernandez-taranco@un.org | H23: Jean Philippe Bernardini, Senior Political Affairs Officer, EOSG, bernardini@un.org; Nadia Hadi, Chief of Staff, DCO, hadin@un.org; Thilmeeza Hussain, Director, Regional Commission Office, thilmeeza.hussain@un.org | I23: EOSG (ODSG); ODA; DCO; UNSDG | J23: Develop initial proposals for co-hosting for further consultation, taking into consideration the unique regional needs and contexts | K23: 46052 | L23: Relocation of respective offices to be hosted by RECs is complete or ongoing, according to implementation plan developed for each region by 29 May 2026 | M23: 46170 | N23: Finalized | P23: Proposal for hosting regional capacities within the regional economic commissions is developed for the Secretary-General's consideration | Q23: 46112.167 | V23: Proposal for hosting regional capacities within the regional economic commissions is developed for the Secretary-General's consideration | W23: 46112 | Z23: OK | AA23: 6 | AB23: 37 | AC23: =IF(UN80_Action_Plan__2_1[[#This Row],[Action No]]=Table10[[#This Row],[Action No]],1,0) -> 1 | AD23: =IF( AND(P23=V23, INT(Q23)=INT(W23), R23=X23), 1, _xlfn.TEXTJOIN(", ", TRUE, IF(P23<>V23, "Upcoming milestone mismatch", ""), IF(INT(Q23)<>INT(W23), "Delivery date mismatch", ""), IF(R23<>X23, "Updates mismatch", "") ) ) -> 1 | AJ23: 28 Jan: - How do we keep this simple? This is about ‘hosting’ colleagues in REC, i.e. giving them a desk – free or ‘for pay’. - How are you progressing on this? What are the potentially available ‘desks’. Who would want one? How do they pay? - Have you talked with DMSPC / DOS about simple cost-recovery setups? 17 Dec: - Initial concept drafted? - Stakeholders mapped? - Regional situation or needs mapped? - Regional typology established? | AK23: 28 Jan: - Note: Colleagues are ‘off track’ on the core task. Help keep this simple. The core goal is an operational action: UN system colleagues getting office space in REC – either for free or being able to pay for it. This is easiest to organize for UN Secretariat entities who can pay via Umoja, if necessary. If anything, the operational implications of hosting are to be resolved with DOS / DMSPC, i.e. setting up cost-recovery budgets / pay. | AL23: - Offices and teams for relocation confirmed? - Regional implementation plans executed as scheduled? - Administrative and HR transitions underway? - Hosting arrangements with RECs operational? - Progress against regional timelines tracked and documented? | AM23: 6 | AN23: 37 | AO23: =IF(UN80_Action_Plan__2_1[[#This Row],[Action No]]=Table8[[#This Row],[Action No]],1,0) -> 1 | AR23: Yes | AS23: 6 | AT23: 37 | AU23: =IF(UN80_Action_Plan__2_1[[#This Row],[Action No]]=Table9[[#This Row],[Action No]],1,0) -> 1
